Workbook

Sheet batteries
A1: group | B1: subgroup | C1: variable | D1: unit | E1: 2020 | F1: 2025 | G1: 2030 | H1: 2035 | I1: 2040 | J1: 2045 | K1: 2050 | L1: Annual change | N1: Source | O1: Comment
A2: Battery | B2: Gross | C2: SoC window | D2: ratio | E2: 0.65 | F2: =1-(1-E2)*(1-$L2) -> 0.825 | G2: =1-(1-F2)*(1-$L2) -> 0.9125 | H2: =1-(1-G2)*(1-$L2) -> 0.95625 | I2: =1-(1-H2)*(1-$L2) -> 0.978125 | J2: =1-(1-I2)*(1-$L2) -> 0.9890625 | K2: =1-(1-J2)*(1-$L2) -> 0.99453125 | L2: 0.5 | N2: Truck OEM engineer (anonymous)
A3: Battery | B3: Gross | C3: Calendar lifetime | D3: years | E3: 15 | F3: =$E3+(F1-$E1)*$L3 -> 16.5 | G3: =$E3+(G1-$E1)*$L3 -> 18 | H3: =$E3+(H1-$E1)*$L3 -> 19.5 | I3: =$E3+(I1-$E1)*$L3 -> 21 | J3: =$E3+(J1-$E1)*$L3 -> 22.5 | K3: =$E3+(K1-$E1)*$L3 -> 24 | L3: 0.3 | N3: See comment.
A4: Battery | B4: Gross | C4: Cycle lifetime | D4: cycles | E4: 1500 | F4: =E4*POWER(1+$L4,5) -> 2007.3384 | G4: =F4*POWER(1+$L4,5) -> 2686.2715 | H4: =G4*POWER(1+$L4,5) -> 3594.8373 | I4: =H4*POWER(1+$L4,5) -> 4810.7032 | J4: =I4*POWER(1+$L4,5) -> 6437.8061 | K4: =J4*POWER(1+$L4,5) -> 8615.2368 | L4: 0.06 | M4: Was 5% | N4: See comment. | O4: Battery parameters and their future development were first estimated based on information from Battery University (https://batteryuniversity.com) and Wikipedia's article on Lithium-ion batteries. As parameters are in practice a chemical trade-off, the joint set of parameters was adjusted based on review by an anonymous truck manufacturer engineer and several experts in a public LinkedIn discussion (https://www.linkedin.com/posts/jakobrogstadius_please-find-problems-in-my-math-these-are-activity-6777180676291653632-jaJB/).
A5: Battery | B5: Gross | C5: Reference charging rate | D5: c | E5: 1 | F5: =E5*POWER(1+$L5,5) -> 1.2166529 | G5: =F5*POWER(1+$L5,5) -> 1.4802443 | H5: =G5*POWER(1+$L5,5) -> 1.8009435 | I5: =H5*POWER(1+$L5,5) -> 2.1911231 | J5: =I5*POWER(1+$L5,5) -> 2.6658363 | K5: =J5*POWER(1+$L5,5) -> 3.2433975 | L5: 0.04 | N5: See comment.
A6: Battery | B6: Gross | C6: Reference discharging rate | D6: c | E6: 1.5 | F6: =E6*POWER(1+$L6,5) -> 1.8249794 | G6: =F6*POWER(1+$L6,5) -> 2.2203664 | H6: =G6*POWER(1+$L6,5) -> 2.7014153 | I6: =H6*POWER(1+$L6,5) -> 3.2866847 | J6: =I6*POWER(1+$L6,5) -> 3.9987545 | K6: =J6*POWER(1+$L6,5) -> 4.8650963 | L6: 0.04 | N6: See comment.
A7: Battery | B7: Gross | C7: Max permitted charging rate | D7: c | E7: {=1.5*E5:K5} -> 1.5 | F7: 1.8249794 | G7: 2.2203664 | H7: 2.7014153 | I7: 3.2866847 | J7: 3.9987545 | K7: 4.8650963 | N7: 1.5 * ref
A8: Battery | B8: Gross | C8: Max permitted discharging rate | D8: c | E8: {=1.5*E6:K6} -> 2.25 | F8: 2.737469 | G8: 3.3305496 | H8: 4.0521229 | I8: 4.9300271 | J8: 5.9981317 | K8: 7.2976444 | N8: 1.5 * ref
A9: Battery | B9: Gross | C9: Specific energy | D9: kWh per kg | E9: 0.2 | F9: =E9*POWER(1+$L9,5) -> 0.23185481 | G9: =F9*POWER(1+$L9,5) -> 0.26878328 | H9: =G9*POWER(1+$L9,5) -> 0.31159348 | I9: =H9*POWER(1+$L9,5) -> 0.36122225 | J9: =I9*POWER(1+$L9,5) -> 0.41875559 | K9: =J9*POWER(1+$L9,5) -> 0.48545249 | L9: 0.03 | N9: See comment.
A10: Battery | B10: Gross | C10: Energy density | D10: kWh per liter | E10: 0.5 | F10: =E10*POWER(1+$L10,5) -> 0.57963704 | G10: =F10*POWER(1+$L10,5) -> 0.67195819 | H10: =G10*POWER(1+$L10,5) -> 0.77898371 | I10: =H10*POWER(1+$L10,5) -> 0.90305562 | J10: =I10*POWER(1+$L10,5) -> 1.046889 | K10: =J10*POWER(1+$L10,5) -> 1.2136312 | L10: 0.03 | N10: See comment.
A11: Battery | B11: Gross | C11: Pack cost | D11: € per kWh | E11: 270 | F11: {=(E11-M11)*POWER(1+$L11,F1:K1-E1)+M11} -> 206.13697 | G11: 159.26763 | H11: 124.87003 | I11: 99.625498 | J11: 81.098433 | K11: 67.501345 | L11: -0.06 | M11: 30 | N11: Link, S., Stephan, A., Speth, D. et al. Rapidly declining costs of truck batteries and fuel cells enable large-scale road freight electrification. Nat Energy 9, 1032–1039 (2024). https://doi.org/10.1038/s41560-024-01531-9
A12: Battery | B12: Gross | C12: Production emissions | D12: kg CO₂ per kWh | E12: 150 | F12: =E12*POWER(1+$L12,5) -> 98.862228 | G12: =F12*POWER(1+$L12,5) -> 65.158268 | H12: =G12*POWER(1+$L12,5) -> 42.944611 | I12: =H12*POWER(1+$L12,5) -> 28.303999 | J12: =I12*POWER(1+$L12,5) -> 18.654643 | K12: =J12*POWER(1+$L12,5) -> 12.294931 | L12: -0.08 | N12: Statement by Northvolt that emissions will be 25% of a Chinese competitor, claimed at 160-180. Trucks in Sweden are mostly Volvo and Scania, which will use Northvolt. Remaining emissions are from raw materials production.
A13: Battery | B13: Gross | C13: End of life definition | D13: ratio of gross | E13: 0.8 | F13: =E13*POWER(1+$L13,5) -> 0.8 | G13: =F13*POWER(1+$L13,5) -> 0.8 | H13: =G13*POWER(1+$L13,5) -> 0.8 | I13: =H13*POWER(1+$L13,5) -> 0.8 | J13: =I13*POWER(1+$L13,5) -> 0.8 | K13: =J13*POWER(1+$L13,5) -> 0.8 | L13: 0 | N13: See comment.
A14: Battery | B14: Net | C14: End of life definition | D14: ratio of net | E14: {=E13:K13} -> 0.8 | F14: 0.8 | G14: 0.8 | H14: 0.8 | I14: 0.8 | J14: 0.8 | K14: 0.8 | O14: X% of net battery capacity
A15: Battery | B15: Net | C15: Calendar lifetime | D15: years | E15: {=0.9*E3:K3/E2:K2} -> 20.769231 | F15: 18 | G15: 17.753425 | H15: 18.352941 | I15: 19.322684 | J15: 20.473934 | K15: 21.718775 | N15: Inspired by Battery University | O15: See sheet "battery SoH example" for reasoning
A16: Battery | B16: Net | C16: Cycle lifetime | D16: cycles | E16: {=E4:K8/E2:K2} -> 2307.6923 | F16: 2433.1374 | G16: 2943.8592 | H16: 3759.307 | I16: 4918.2908 | J16: 6508.9982 | K16: 8662.6104
A17: Battery | B17: Net | C17: Reference charging rate | D17: c | E17: 1.5384615 | F17: 1.4747308 | G17: 1.6221855 | H17: 1.8833396 | I17: 2.2401259 | J17: 2.6953164 | K17: 3.2612324
A18: Battery | B18: Net | C18: Reference discharging rate | D18: c | E18: 2.3076923 | F18: 2.2120962 | G18: 2.4332783 | H18: 2.8250094 | I18: 3.3601888 | J18: 4.0429745 | K18: 4.8918486
A19: Battery | B19: Net | C19: Max permitted charging rate | D19: c | E19: 2.3076923 | F19: 2.2120962 | G19: 2.4332783 | H19: 2.8250094 | I19: 3.3601888 | J19: 4.0429745 | K19: 4.8918486
A20: Battery | B20: Net | C20: Max permitted discharging rate | D20: c | E20: 3.4615385 | F20: 3.3181443 | G20: 3.6499174 | H20: 4.2375141 | I20: 5.0402833 | J20: 6.0644618 | K20: 7.3377728
A21: Battery | B21: Net | C21: Specific energy | D21: kWh per kg | E21: {=E9:K10*E2:K2} -> 0.13 | F21: 0.19128022 | G21: 0.24526474 | H21: 0.29796127 | I21: 0.35332051 | J21: 0.41417545 | K21: 0.48279768
A22: Battery | B22: Net | C22: Energy density | D22: kWh per liter | E22: 0.325 | F22: 0.47820056 | G22: 0.61316185 | H22: 0.74490317 | I22: 0.88330128 | J22: 1.0354386 | K22: 1.2069942
A23: Battery | B23: Net | C23: Pack cost | D23: € per kWh | E23: {=E11:K11/E2:K2} -> 415.38462 | F23: 249.86299 | G23: 174.53987 | H23: 130.58304 | I23: 101.85354 | J23: 81.995256 | K23: 67.872523 | N23: Very similar to means of near-market until 2030, then scientific until 2040, then extrapolation, from https://www.nature.com/articles/s41560-024-01531-9/figures/1
A24: Battery | B24: Net | C24: Production emissions | D24: kg CO₂ per kWh | E24: {=E12:K12/E2:K2} -> 230.76923 | F24: 119.833 | G24: 71.406321 | H24: 44.909397 | I24: 28.936996 | J24: 18.860934 | K24: 12.362538
A26: Battery | B26: Gross | C26: Residual value if recycled this year | D26: ratio | E26: {=0.3/(1+EXP(-(E$1:K$1-2035)*0.3))} -> 0.0032960828 | F26: 0.014227762 | G26: 0.054727657 | H26: 0.15 | I26: 0.24527234 | J26: 0.28577224 | K26: 0.29670392 | O26: Replaced by equation in simulation. Calculated based on price of new batteries in year of decommissioning.
A27: Battery | B27: Net | C27: Residual value if recycled this year | D27: ratio | E27: {=_xlfn.ANCHORARRAY(E26)/E2:K2} -> 0.0050708966 | F27: 0.017245772 | G27: 0.059975515 | H27: 0.15686275 | I27: 0.25075767 | J27: 0.28893244 | K27: 0.29833544 | O27: Replaced by equation in simulation. Calculated based on price of new batteries in year of decommissioning.
C28: Min useable range | D28: km | E28: 700 | F28: =E28*POWER(1+$L28,5) -> 700 | G28: =F28*POWER(1+$L28,5) -> 700 | H28: =G28*POWER(1+$L28,5) -> 700 | I28: =H28*POWER(1+$L28,5) -> 700 | J28: =I28*POWER(1+$L28,5) -> 700 | K28: =J28*POWER(1+$L28,5) -> 700 | L28: 0 | AE28: 0
B29: HGV40 | C29: Min peak power | D29: kW | E29: {=vehicles!E88:K88} -> 550 | F29: 550 | G29: 550 | H29: 550 | I29: 550 | J29: 550 | K29: 550 | AE29: Battery ageing | AF29: =OFFSET(E55,0,AE28) -> 0.24031586
C30: Minimum pack size to power motor | D30: kWh | E30: {=_xlfn.ANCHORARRAY(E29)/_xlfn.ANCHORARRAY(E8)} -> 244.44444 | F30: 200.91551 | G30: 165.13791 | H30: 135.73132 | I30: 111.56125 | J30: 91.695218 | K30: 75.366786 | AE30: Capital interest | AF30: =OFFSET(E56,0,AE28) -> 0.04263717
B31: HGV40 | C31: Energy consumption | D31: kWh per km | E31: {=vehicles!E106:K106} -> 1.1242076 | F31: 1.0908836 | G31: 1.0585475 | H31: 1.0271699 | I31: 0.99672235 | J31: 0.96717735 | K31: 0.93850813 | AE31: Lost cargo capacity | AF31: =OFFSET(E54,0,AE28) -> 0.084142613
C32: Net battery capacity | D32: kWh | E32: {=IF(E28:K28*_xlfn.ANCHORARRAY(E31)>_xlfn.ANCHORARRAY(E30)*E2:K2,E28:K28*_xlfn.ANCHORARRAY(E31),_xlfn.ANCHORARRAY(E30)*E2:K2)} -> 786.9453 | F32: 763.61855 | G32: 740.98325 | H32: 719.01891 | I32: 697.70564 | J32: 677.02415 | K32: 656.95569 | AE32: Lost time | AF32: =OFFSET(E69,0,AE28) -> 0.025427077
B33: HGV40 | C33: {=vehicles!C84:K84} -> Annual distance | D33: km | E33: 115000 | F33: 115000 | G33: 115000 | H33: 115000 | I33: 115000 | J33: 115000 | K33: 115000 | AE33: CO₂ (SCC) | AF33: =OFFSET(E75,0,AE28) -> 0.0090825113
C34: Annual energy use | D34: kWh | E34: {=E33:K33*_xlfn.ANCHORARRAY(E31)} -> 129283.87 | F34: 125451.62 | G34: 121732.96 | H34: 118124.54 | I34: 114623.07 | J34: 111225.4 | K34: 107928.44 | AE34: 0
C35: Ratio of energy directly to propulsion | D35: % of energy | E35: 0.4 | F35: =E35*POWER(1+$L35,5) -> 0.4 | G35: =F35*POWER(1+$L35,5) -> 0.4 | H35: =G35*POWER(1+$L35,5) -> 0.4 | I35: =H35*POWER(1+$L35,5) -> 0.4 | J35: =I35*POWER(1+$L35,5) -> 0.4 | K35: =J35*POWER(1+$L35,5) -> 0.4 | L35: 0
C36: Cycles per year, net | D36: cycle eq. of energy use | E36: {=(1-E35:K35)*_xlfn.ANCHORARRAY(E34)/_xlfn.ANCHORARRAY(E32)} -> 98.571429 | F36: 98.571429 | G36: 98.571429 | H36: 98.571429 | I36: 98.571429 | J36: 98.571429 | K36: 98.571429
B37: HGV40 | C37: Battery weight | D37: ton | E37: {=_xlfn.ANCHORARRAY(E32)/(E2:K2*E9:K9*1000)} -> 6.0534254 | F37: 3.9921459 | G37: 3.0211569 | H37: 2.4131288 | I37: 1.9747103 | J37: 1.6346313 | K37: 1.3607267
C38: {=vehicles!C90:K90} -> Cargo capacity value | D38: euro per ton-km | E38: 0.025 | F38: 0.025 | G38: 0.025 | H38: 0.025 | I38: 0.025 | J38: 0.025 | K38: 0.025
C39: Cost of weight | D39: euro per cycled kWh | E39: {=E38:K38*_xlfn.ANCHORARRAY(E37)/_xlfn.ANCHORARRAY(E31)} -> 0.13461538 | F39: 0.09148881 | G39: 0.071351471 | H39: 0.058732466 | I39: 0.049530099 | J39: 0.042252625 | K39: 0.036247068
B40: HGV40 | C40: Battery volume | D40: m3 | E40: {=_xlfn.ANCHORARRAY(E32)/(E2:K2*E10:K10*1000)} -> 2.4213702 | F40: 1.5968583 | G40: 1.2084627 | H40: 0.96525151 | I40: 0.78988411 | J40: 0.65385252 | K40: 0.54429068
C41: {=vehicles!C91:K91} -> Cargo capacity value | D41: euro per m3-km | E41: 0.007 | F41: 0.007 | G41: 0.007 | H41: 0.007 | I41: 0.007 | J41: 0.007 | K41: 0.007
C42: Cost of volume | D42: € per cycled kWh | E42: {=E41:K41*_xlfn.ANCHORARRAY(E40)/_xlfn.ANCHORARRAY(E31)} -> 0.015076923 | F42: 0.010246747 | G42: 0.0079913648 | H42: 0.0065780362 | I42: 0.0055473711 | J42: 0.004732294 | K42: 0.0040596716 | AE42: Battery capacity
C43: Lost cargo capacity | D43: € per cycled kWh | E43: {=(_xlfn.ANCHORARRAY(E39)+_xlfn.ANCHORARRAY(E42))/2} -> 0.074846154 | F43: 0.050867779 | G43: 0.039671418 | H43: 0.032655251 | I43: 0.027538735 | J43: 0.02349246 | K43: 0.02015337 | AD43: =OFFSET(AF29,AE34,0)*100 -> 24.031586 | AE43: {=TRANSPOSE(_xlfn.ANCHORARRAY(X57))} -> 100 | AF43: 133.35214 | AG43: 177.82794 | AH43: 237.13737 | AI43: 316.22777 | AJ43: 421.6965 | AK43: 562.34133 | AL43: 749.89421 | AM43: 1000 | AN43: 1333.5214
AC44: {=AE29:AE33} -> Battery ageing | AD44: {=_xlfn.SEQUENCE(5,1,0,1)} -> 0 | AE44: 14.75241 | AF44: 14.75241 | AG44: 15.418746 | AH44: 16.483296 | AI44: 17.865959 | AJ44: 19.644308 | AK44: 21.909762 | AL44: 24.782291 | AM44: 28.445092 | AN44: 33.191342
C45: Lifetime | D45: years | E45: {=1/(_xlfn.ANCHORARRAY(E36)/E16:K16+1/_xlfn.ANCHORARRAY(E15))} -> 11.005648 | F45: 10.409334 | G45: 11.134505 | H45: 12.390373 | I45: 13.928653 | J45: 15.628306 | K45: 17.414908 | AC45: Capital interest | AD45: 1 | AE45: 0.86086957 | AF45: 0.86086957 | AG45: 1.0831543 | AH45: 1.4444095 | AI45: 1.926151 | AJ45: 2.5685637 | AK45: 3.4252347 | AL45: 4.5676239 | AM45: 6.0910243 | AN45: 8.1225115
C46: Residual value at recycling year | D46: ratio | E46: {=0.3/(1+EXP(-(E$1:K$1-2035+_xlfn.ANCHORARRAY(E45))*0.3))} -> 0.06953304 | F46: 0.15919846 | G46: 0.25889709 | H46: 0.29288178 | I46: 0.29897799 | J46: 0.29986264 | K46: 0.29998206 | AC46: Lost cargo capacity | AD46: 2 | AE46: 1.6988889 | AF46: 1.6988889 | AG46: 2.1375582 | AH46: 2.8504797 | AI46: 3.8011758 | AJ46: 5.0689494 | AK46: 6.7595527 | AL46: 9.0140083 | AM46: 12.020373 | AN46: 16.029425
C47: Lifetime | D47: cycle eq. of energy use | E47: {=_xlfn.ANCHORARRAY(E45)*_xlfn.ANCHORARRAY(E34)/_xlfn.ANCHORARRAY(E32)} -> 1808.0708 | F47: 1710.1049 | G47: 1829.2402 | H47: 2035.5613 | I47: 2288.2787 | J47: 2567.5073 | K47: 2861.0206 | AC47: Lost time | AD47: 3 | AE47: 15.462693 | AF47: 15.462693 | AG47: 11.531986 | AH47: 8.1972291 | AI47: 5.9307297 | AJ47: 4.3385071 | AK47: 3.1968271 | AL47: 2.3672263 | AM47: 1.75896 | AN47: 1.3101951
C48: Battery ageing | D48: € per spent kWh | E48: {=(E11:K11/E2:K2)*(1-_xlfn.ANCHORARRAY(E46))/_xlfn.ANCHORARRAY(E47)} -> 0.21376467 | F48: 0.1228493 | G48: 0.070713515 | H48: 0.045362252 | I48: 0.031203182 | J48: 0.022359407 | K48: 0.016606655 | AC48: CO₂ (SCC) | AD48: 4 | AE48: 0.52414143 | AF48: 0.52414143 | AG48: 0.54923269 | AH48: 0.59001078 | AI48: 0.64438923 | AJ48: 0.71690407 | AK48: 0.81360416 | AL48: 0.9425558 | AM48: 1.1145156 | AN48: 1.3438276
B49: World
C50: Cost of capital | D50: % per year | E50: {=world!E3:K3} -> 0.03 | F50: 0.03 | G50: 0.03 | H50: 0.03 | I50: 0.03 | J50: 0.03 | K50: 0.03
C51: Battery price | D51: € | E51: {=E11:K11*_xlfn.ANCHORARRAY(E32)/E2:K2} -> 326884.97 | F51: 190800.01 | G51: 129331.12 | H51: 93891.675 | I51: 71063.793 | J51: 55512.768 | K51: 44589.241
C52: Capital interest | D52: € per cycled kWh | E52: {=E50:K50*_xlfn.ANCHORARRAY(E51)/(2*E34:K34)} -> 0.037926421 | F52: 0.022813577 | G52: 0.015936249 | H52: 0.011922799 | I52: 0.0092996714 | J52: 0.0074865234 | K52: 0.0061970565
C54: =C43 -> Lost cargo capacity | D54: € per km | E54: {=_xlfn.ANCHORARRAY(E$43)*_xlfn.ANCHORARRAY(E$31)} -> 0.084142613 | F54: 0.055490828 | G54: 0.04199408 | H54: 0.03354249 | I54: 0.027448473 | J54: 0.022721375 | K54: 0.018914101 | P54: €c/km TCO, 2050 | X54: TCO/km. 2050 rel. to 2020
C55: =C48 -> Battery ageing | D55: € per km | E55: {=_xlfn.ANCHORARRAY(E48)*_xlfn.ANCHORARRAY(E$31)} -> 0.24031586 | F55: 0.13401429 | G55: 0.074853615 | H55: 0.046594738 | I55: 0.031100909 | J55: 0.021625512 | K55: 0.015585481 | Q55: Annual change in cost per kWh capacity | Y55: =Q55 -> Annual change in cost per kWh capacity
C56: =C52 -> Capital interest | D56: € per km | E56: {=_xlfn.ANCHORARRAY(E52)*_xlfn.ANCHORARRAY(E$31)} -> 0.04263717 | F56: 0.024886958 | G56: 0.016869276 | H56: 0.01224674 | I56: 0.0092691903 | J56: 0.0072407958 | K56: 0.0058159879 | P56: =100*(K54+K55+K56+K69+K75) -> 4.3998883 | Q56: 0.05 | R56: 0.02 | S56: 0 | T56: -0.02 | U56: -0.05 | X56: =(K54+K55+K56+K69+K75)/(E54+E55+E56+E69+E75) -> 0.10955754 | Y56: 0.05 | Z56: 0.02 | AA56: 0 | AB56: -0.02 | AC56: -0.05
B57: HGV40 | O57: Min usable range | P57: {=POWER(10,((_xlfn.SEQUENCE(10)-1))/8+2)} -> 100 | Q57: 18.134683 | R57: 13.040765 | S57: 11.394528 | T57: 10.472325 | U57: 9.8010457 | W57: Min usable range | X57: {=P57:P66} -> 100 | Y57: 0.54460139 | Z57: 0.39162628 | AA57: 0.34218827 | AB57: 0.31449365 | AC57: 0.29433451
C58: {=vehicles!C97:K97} -> Driver cost | D58: euro per h | E58: 33.6 | F58: 33.6 | G58: 33.6 | H58: 33.6 | I58: 33.6 | J58: 33.6 | K58: 33.6 | P58: 133.35214 | Q58: 15.079604 | R58: 9.2073813 | S58: 7.3096148 | T58: 6.2465073 | U58: 5.4726629 | X58: 133.35214 | Y58: 0.45285453 | Z58: 0.27650622 | AA58: 0.21951453 | AB58: 0.18758842 | AC58: 0.16434915
B59: HGV40 | C59: Probability of no charging at natural stop | D59: ratio | E59: 1 | F59: =E59*POWER(1+$L59,5) -> 0.69568837 | G59: =F59*POWER(1+$L59,5) -> 0.48398231 | H59: =G59*POWER(1+$L59,5) -> 0.33670086 | I59: =H59*POWER(1+$L59,5) -> 0.23423887 | J59: =I59*POWER(1+$L59,5) -> 0.16295726 | K59: =J59*POWER(1+$L59,5) -> 0.11336747 | L59: -0.07 | P59: 177.82794 | Q59: 13.904455 | R59: 6.9940105 | S59: 4.7607148 | T59: 3.5096475 | U59: 2.5989857 | X59: 177.82794 | Y59: 0.452609 | Z59: 0.22766459 | AA59: 0.15496777 | AB59: 0.11424382 | AC59: 0.084600534
C60: Workday length | D60: hours away from depot | E60: {=vehicles!E86:K86} -> 11 | F60: 11 | G60: 11 | H60: 11 | I60: 11 | J60: 11 | K60: 11 | P60: 237.13737 | Q60: 15.506893 | R60: 7.2117055 | S60: 4.530893 | T60: 3.0291318 | U60: 1.9359879 | X60: 237.13737 | Y60: 0.52449416 | Z60: 0.24392362 | AA60: 0.15324971 | AB60: 0.10245521 | AC60: 0.065481484
C61: Natural stops per day | D61: count | E61: {=_xlfn.FLOOR.MATH(_xlfn.ANCHORARRAY(E60)/4.5)} -> 2 | F61: 2 | G61: 2 | H61: 2 | I61: 2 | J61: 2 | K61: 2 | P61: 316.22777 | Q61: 19.025098 | R61: 8.8831493 | S61: 5.6055062 | T61: 3.7694072 | U61: 2.4328962 | X61: 316.22777 | Y61: 0.6306299 | Z61: 0.29445207 | AA61: 0.18580718 | AB61: 0.12494552 | AC61: 0.080643846
B62: HGV40 | C62: Driving per day | D62: hours | E62: {=_xlfn.ANCHORARRAY(E60)-_xlfn.ANCHORARRAY(E61)*0.75-2} -> 7.5 | F62: 7.5 | G62: 7.5 | H62: 7.5 | I62: 7.5 | J62: 7.5 | K62: 7.5 | P62: 421.6965 | Q62: 23.716912 | R62: 11.112148 | S62: 7.0385795 | T62: 4.7566122 | U62: 3.0955502 | X62: 421.6965 | Y62: 0.73342431 | Z62: 0.34363323 | AA62: 0.21766178 | AB62: 0.14709398 | AC62: 0.095727123
C63: Range buffer at charging | D63: km | E63: {=vehicles!E107:K107} -> 50 | F63: 50 | G63: 50 | H63: 50 | I63: 50 | J63: 50 | K63: 50 | L63: breaks, loading, unloading | P63: 562.34133 | Q63: 29.973687 | R63: 14.084626 | S63: 8.9496489 | T63: 6.0730924 | U63: 3.9792242 | X63: 562.34133 | Y63: 0.83018149 | Z63: 0.39010201 | AA63: 0.24787851 | AB63: 0.1682065 | AC63: 0.11021261
C64: Charging stop duration, overhead | D64: hours | E64: 0.2 | F64: =E64*POWER(1+$L64,5) -> 0.2 | G64: =F64*POWER(1+$L64,5) -> 0.2 | H64: =G64*POWER(1+$L64,5) -> 0.2 | I64: =H64*POWER(1+$L64,5) -> 0.2 | J64: =I64*POWER(1+$L64,5) -> 0.2 | K64: =J64*POWER(1+$L64,5) -> 0.2 | L64: 0 | P64: 749.89421 | Q64: 38.317321 | R64: 18.048529 | S64: 11.498124 | T64: 7.8286608 | U64: 5.1576294 | X64: 749.89421 | Y64: 0.91946039 | Z64: 0.43309153 | AA64: 0.27590837 | AB64: 0.18785613 | AC64: 0.1237622
C65: Extra charging stop duration | D65: hours | E65: {=(_xlfn.ANCHORARRAY(E32)/E2-_xlfn.ANCHORARRAY(E63)*_xlfn.ANCHORARRAY(E31))/(E17:K17*E32/E2)+E64:K64} -> 0.81982143 | F65: 0.82744029 | G65: 0.75349863 | H65: 0.66261569 | I65: 0.57740573 | J65: 0.50437088 | K65: 0.44409732 | P65: 1000 | Q65: 49.443797 | R65: 23.334504 | S65: 14.896586 | T65: 10.169758 | U65: 6.7290627 | X65: 1000 | Y65: 1.0002798 | Z65: 0.47207204 | AA65: 0.30136751 | AB65: 0.20574075 | AC65: 0.13613327
C66: Mean speed | D66: km per hour | E66: 60 | F66: =E66*POWER(1+$L66,5) -> 60 | G66: =F66*POWER(1+$L66,5) -> 60 | H66: =G66*POWER(1+$L66,5) -> 60 | I66: =H66*POWER(1+$L66,5) -> 60 | J66: =I66*POWER(1+$L66,5) -> 60 | K66: =J66*POWER(1+$L66,5) -> 60 | L66: 0 | P66: 1333.5214 | Q66: 64.281231 | R66: 30.383484 | S66: 19.428517 | T66: 13.291667 | U66: 8.8246056 | X66: 1333.5214 | Y66: 1.071402 | Z66: 0.50641417 | AA66: 0.32382318 | AB66: 0.22153775 | AC66: 0.14708337
C67: Extra charging stops | D67: stops per day | E67: =MAX(0,E78-E61*(1-E59)) -> 0.41538462 | F67: =MAX(0,F78-F61*(1-F59)) -> 0 | G67: =MAX(0,G78-G61*(1-G59)) -> 0 | H67: =MAX(0,H78-H61*(1-H59)) -> 0 | I67: =MAX(0,I78-I61*(1-I59)) -> 0 | J67: =MAX(0,J78-J61*(1-J59)) -> 0 | K67: =MAX(0,K78-K61*(1-K59)) -> 0
C68: Extra charging stops | D68: stops per km | E68: {=E67:K67/_xlfn.ANCHORARRAY(E79)} -> 0.00092307692 | F68: 0 | G68: 0 | H68: 0 | I68: 0 | J68: 0 | K68: 0 | P68: =Q69 -> 0 | Q68: {=E1:K1} -> 2020 | R68: 2025 | S68: 2030 | T68: 2035 | U68: 2040 | V68: 2045 | W68: 2050
C69: Cost of lost time | D69: € per km | E69: {=_xlfn.ANCHORARRAY(E65)*E58:K58*_xlfn.ANCHORARRAY(E68)} -> 0.025427077 | F69: 0 | G69: 0 | H69: 0 | I69: 0 | J69: 0 | K69: 0 | P69: =OFFSET(E77,0,P68)*100 -> 40.160523 | Q69: {=_xlfn.SEQUENCE(1,7,0,1)} -> 0 | R69: 1 | S69: 2 | T69: 3 | U69: 4 | V69: 5 | W69: 6
C70: Lost time | D70: € per cycled kWh | E70: {=_xlfn.ANCHORARRAY(E69)/_xlfn.ANCHORARRAY(E31)} -> 0.022617778 | F70: 0 | G70: 0 | H70: 0 | I70: 0 | J70: 0 | K70: 0 | O70: Min usable range | P70: {=P57:P66} -> 100 | Q70: 33.299003 | R70: 22.179141 | S70: 15.204529 | T70: 12.033835 | U70: 11.406483 | V70: 11.156778 | W70: 9.6825875
B71: World | P71: 133.35214 | Q71: 33.299003 | R71: 22.179141 | S71: 15.204529 | T71: 11.297187 | U71: 8.4394009 | V71: 6.5900392 | W71: 5.3361053
C72: {=world!C8:K8} -> SCC | D72: euro per kg | E72: 0.08 | F72: 0.165 | G72: 0.25 | H72: 0.3875 | I72: 0.525 | J72: 0.6625 | K72: 0.8 | P72: 177.82794 | Q72: 30.720678 | R72: 19.535164 | S72: 11.955495 | T72: 7.4923088 | U72: 4.9594196 | V72: 3.417682 | W72: 2.4382844
C73: Production emissions | D73: kg CO₂ per cycled kWh | E73: {=E12:K12*(_xlfn.ANCHORARRAY(E32)/E2:K2)/(_xlfn.ANCHORARRAY(E34)*_xlfn.ANCHORARRAY(E45))} -> 0.12763285 | F73: 0.070073481 | G73: 0.039036056 | H73: 0.022062414 | I73: 0.012645748 | J73: 0.00734601 | K73: 0.0043210238 | P73: 237.13737 | Q73: 29.565425 | R73: 17.36494 | S73: 9.5189972 | T73: 5.2041866 | U73: 3.2280227 | V73: 2.3359784 | W73: 1.7430847
C74: CO₂ (SCC) | D74: € per cycled kWh | E74: {=E72:K72*_xlfn.ANCHORARRAY(E73)} -> 0.010210628 | F74: 0.011562124 | G74: 0.0097590139 | H74: 0.0085491853 | I74: 0.0066390177 | J74: 0.0048667316 | K74: 0.003456819 | P74: 316.22777 | Q74: 30.168405 | R74: 16.71266 | S74: 8.5197273 | T74: 5.5790572 | U74: 3.9476674 | V74: 2.90416 | W74: 2.1970468
C75: =C74 -> CO₂ (SCC) | D75: € per km | E75: {=_xlfn.ANCHORARRAY(E74)/_xlfn.ANCHORARRAY(E31)} -> 0.0090825113 | F75: 0.010598861 | G75: 0.0092192499 | H75: 0.0083230491 | I75: 0.0066608497 | J75: 0.0050318916 | K75: 0.0036833128 | P75: 421.6965 | Q75: 32.337232 | R75: 17.30135 | S75: 10.07969 | T75: 6.8065855 | U75: 4.9088597 | V75: 3.6619922 | W75: 2.8024284
P76: 562.34133 | Q76: 36.104981 | R76: 19.5828 | S76: 12.196056 | T76: 8.4535323 | U76: 6.1917544 | V76: 4.6726808 | W76: 3.6097266
C77: sum | D77: €/km | E77: {=_xlfn.ANCHORARRAY(E54)+_xlfn.ANCHORARRAY(E55)+_xlfn.ANCHORARRAY(E56)+_xlfn.ANCHORARRAY(E69)+_xlfn.ANCHORARRAY(E75)} -> 0.40160523 | F77: 0.22499094 | G77: 0.14293622 | H77: 0.10070702 | I77: 0.074479421 | J77: 0.056619575 | K77: 0.043998883 | P77: 749.89421 | Q77: 41.673705 | R77: 23.556691 | S77: 15.058187 | T77: 10.657552 | U77: 7.9033147 | V77: 6.0205254 | W77: 4.6862819
C78: min charging stops per day | E78: {=(1-E35)*_xlfn.ANCHORARRAY(E79)*_xlfn.ANCHORARRAY(E31)/(_xlfn.ANCHORARRAY(E32)-_xlfn.ANCHORARRAY(E63)*_xlfn.ANCHORARRAY(E31))} -> 0.41538462 | F78: 0.41538462 | G78: 0.41538462 | H78: 0.41538462 | I78: 0.41538462 | J78: 0.41538462 | K78: 0.41538462 | P78: 1000 | Q78: 49.429965 | R78: 28.87595 | S78: 18.912326 | T78: 13.60239 | U78: 10.186263 | V78: 7.8179516 | W78: 6.1218952
C79: daily distance based on assumptions per day | E79: {=_xlfn.ANCHORARRAY(E62)*E66:K66} -> 450 | F79: 450 | G79: 450 | H79: 450 | I79: 450 | J79: 450 | K79: 450 | P79: 1333.5214 | Q79: 59.997302 | R79: 36.021248 | S79: 24.083279 | T79: 17.533482 | U79: 13.230998 | V79: 10.214889 | W79: 8.0363189
C80: daily distance based on assumptions per year | E80: {=E33:K33/230} -> 500 | F80: 500 | G80: 500 | H80: 500 | I80: 500 | J80: 500 | K80: 500

Sheet bat plots
C17: 2020 | D17: 2025 | E17: 2030 | F17: 2035 | G17: 2040 | H17: 2045 | I17: 2050 | M17: 2020 | N17: 2025 | O17: 2030 | P17: 2035 | Q17: 2040 | R17: 2045 | S17: 2050
A18: Min usable range | B18: 100 | C18: 47.007859 | D18: 34.433249 | E18: 27.405201 | F18: 24.080284 | G18: 22.12328 | H18: 19.539022 | I18: 17.64977 | K18: Min usable range | L18: 100 | M18: 47.007859 | N18: 37.385148 | O18: 31.261046 | P18: 27.76917 | Q18: 25.566391 | R18: 22.831916 | S18: 20.790056
B19: 133.35214 | C19: 47.007859 | D19: 33.780518 | E19: 24.745821 | F19: 19.009405 | G19: 15.440586 | H19: 13.024816 | I19: 11.293314 | L19: 133.35214 | M19: 47.007859 | N19: 36.752664 | O19: 28.694635 | P19: 22.913814 | Q19: 19.252407 | R19: 16.758178 | S19: 14.929041
B20: 177.82794 | C20: 41.63618 | D20: 27.88761 | E20: 19.152885 | F20: 13.835893 | G20: 10.643812 | H20: 8.5393226 | I20: 7.0752252 | L20: 177.82794 | M20: 41.63618 | N20: 31.038349 | O20: 23.346245 | P20: 18.105845 | Q20: 14.954638 | R20: 12.861504 | S20: 11.371857
B21: 237.13737 | C21: 38.042117 | D21: 24.320113 | E21: 15.683007 | F21: 10.645883 | G21: 7.6850439 | H21: 5.7694621 | I21: 4.4709868 | L21: 237.13737 | M21: 38.042117 | N21: 27.701686 | O21: 20.203359 | P21: 15.425818 | Q21: 12.66822 | R21: 10.878025 | S21: 9.6491132
B22: 316.22777 | C22: 36.916304 | D22: 22.79174 | E22: 13.979517 | F22: 9.018163 | G22: 6.1003721 | H22: 4.2252134 | I22: 2.973457 | L22: 316.22777 | M22: 36.916304 | N22: 26.469169 | O22: 18.948414 | P22: 14.50298 | Q22: 11.985942 | R22: 10.383302 | S22: 9.3271857
B23: 421.6965 | C23: 37.807927 | D23: 22.843058 | E23: 13.642523 | F23: 8.5596424 | G23: 5.6844608 | H23: 4.0647652 | I23: 2.9625574 | L23: 421.6965 | M23: 37.807927 | N23: 26.898048 | O23: 19.239207 | P23: 15.007763 | Q23: 12.77776 | R23: 11.623005 | S23: 10.884046
B24: 562.34133 | C24: 40.611085 | D24: 24.326124 | E24: 14.734465 | F24: 10.053481 | G24: 7.1324866 | H24: 5.1717345 | I24: 3.8112977 | L24: 562.34133 | M24: 40.611085 | N24: 28.866594 | O24: 21.213245 | P24: 17.805204 | Q24: 15.839321 | R24: 14.59748 | S24: 13.82347
B25: 749.89421 | C25: 45.438093 | D25: 27.470482 | E25: 18.00576 | F25: 12.585399 | G25: 9.064291 | H25: 6.6479669 | I25: 4.9431161 | L25: 749.89421 | M25: 45.438093 | N25: 32.650181 | O25: 25.711136 | P25: 22.089294 | Q25: 19.924737 | R25: 18.564296 | S25: 17.743285
B26: 1000 | C26: 52.583449 | D26: 33.14623 | E26: 22.422686 | F26: 15.968059 | G26: 11.640905 | H26: 8.6165932 | I26: 6.452423 | L26: 1000 | M26: 52.583449 | N26: 39.192492 | O26: 31.808645 | P26: 27.817703 | Q26: 25.374426 | R26: 23.854306 | S26: 22.970459
B27: 1333.5214 | C27: 62.562248 | D27: 40.823478 | E27: 28.354254 | F27: 20.482887 | G27: 15.077184 | H27: 11.241822 | I27: 8.465118 | L27: 1333.5214 | M27: 62.562248 | N27: 48.063298 | O27: 40.01544 | P27: 35.466446 | Q27: 32.642731 | R27: 30.908751 | S27: 29.941019

Sheet electricity price curves
A1: hour of day | B1: Average of SE1 | C1: Average of SE2 | D1: Average of SE3 | E1: Average of SE4 | F1: Avg of DE-LU | H1: Norm SE1 | I1: Norm SE2 | J1: Norm SE3 | K1: Norm SE4
A2: 0 | B2: 36.990822 | C2: 36.990822 | D2: 42.218301 | E2: 55.548164 | F2: 81.629342 | H2: {=(B2:B25-MIN(B2:B25))/(MAX(B2:B25)-MIN(B2:B25))} -> 0.17581161 | I2: {=(C2:C25-MIN(C2:C25))/(MAX(C2:C25)-MIN(C2:C25))} -> 0.1745215 | J2: {=(D2:D25-MIN(D2:D25))/(MAX(D2:D25)-MIN(D2:D25))} -> 0.0833495 | K2: {=(E2:E25-MIN(E2:E25))/(MAX(E2:E25)-MIN(E2:E25))} -> 0.11415546
A3: 1 | B3: 35.669534 | C3: 35.669534 | D3: 39.641589 | E3: 51.892 | F3: 76.48011 | H3: 0.084069837 | I3: 0.083452928 | J3: 0.032668253 | K3: 0.051017005
A4: 2 | B4: 34.67074 | C4: 34.67074 | D4: 38.161096 | E4: 49.407205 | F4: 73.568904 | H4: 0.014719926 | I4: 0.01461191 | J4: 0.0035484956 | K4: 0.0081069867
A5: 3 | B5: 34.45874 | C5: 34.45874 | D5: 37.980685 | E5: 48.937753 | F5: 71.295288 | H5: 0 | I5: 0 | J5: 0 | K5: 0
A6: 4 | B6: 35.411342 | C6: 35.411342 | D6: 39.86389 | E6: 51.194055 | F6: 72.421945 | H6: 0.066142649 | I6: 0.06565729 | J6: 0.037040689 | K6: 0.03896416
A7: 5 | B7: 37.960438 | C7: 37.954274 | D7: 46.132795 | E7: 57.525863 | F7: 78.102795 | H7: 0.24313558 | I7: 0.24092657 | J7: 0.1603435 | K7: 0.14830841
A8: 6 | B8: 41.062932 | C8: 41.048247 | D8: 59.311973 | E8: 77.939315 | F8: 95.316575 | H8: 0.45855289 | I8: 0.45417586 | J8: 0.4195642 | K8: 0.50082915
A9: 7 | B9: 44.892685 | C9: 44.950247 | D9: 76.736685 | E9: 97.677589 | F9: 112.38271 | H9: 0.7244665 | I9: 0.72311771 | J9: 0.76229013 | K9: 0.84169021
A10: 8 | B10: 48.860986 | C10: 48.967452 | D10: 88.55926 | E10: 106.84485 | F10: 118.65364 | H10: 1 | I10: 1 | J10: 0.99482787 | K10: 1
A11: 9 | B11: 48.387808 | C11: 48.494493 | D11: 86.461315 | E11: 102.40334 | F11: 112.35071 | H11: 0.96714554 | I11: 0.96740173 | J11: 0.95356348 | K11: 0.92329944
A12: 10 | B12: 47.398795 | C12: 47.481014 | D12: 83.152384 | E12: 96.26326 | F12: 104.57049 | H12: 0.89847474 | I12: 0.89754857 | J12: 0.88848024 | K12: 0.81726611
A13: 11 | B13: 46.065781 | C13: 46.157452 | D13: 79.696959 | E13: 92.132027 | F13: 100.40745 | H13: 0.80591879 | I13: 0.80632327 | J13: 0.82051564 | K13: 0.74592368
A14: 12 | B14: 45.407836 | C14: 45.456027 | D14: 76.134192 | E14: 87.451452 | F14: 95.088603 | H14: 0.76023528 | I14: 0.7579782 | J14: 0.75043972 | K14: 0.66509463
... A25: 23 | B25: 37.442137 | C25: 37.435534 | D25: 44.660493 | E25: 59.560767 | F25: 84.852767 | H25: 0.20714805 | I25: 0.2051729 | J25: 0.13138487 | K25: 0.18344926
A26: Min | B26: =MIN(B2:B25) -> 34.45874 | C26: =MIN(C2:C25) -> 34.45874 | D26: =MIN(D2:D25) -> 37.980685 | E26: =MIN(E2:E25) -> 48.937753 | F26: =MIN(F2:F25) -> 71.295288 | H26: =AVERAGE(_xlfn.ANCHORARRAY(H2)) -> 0.55779397 | I26: =AVERAGE(_xlfn.ANCHORARRAY(I2)) -> 0.55794904 | J26: =AVERAGE(_xlfn.ANCHORARRAY(J2)) -> 0.55110628 | K26: =AVERAGE(_xlfn.ANCHORARRAY(K2)) -> 0.54534204
A27: Max | B27: =MAX(B2:B25) -> 48.860986 | C27: =MAX(C2:C25) -> 48.967452 | D27: =MAX(D2:D25) -> 88.822219 | E27: =MAX(E2:E25) -> 106.84485 | F27: =MAX(F2:F25) -> 125.2554
A28: Avg | B28: =AVERAGE(B2:B25) -> 42.492226 | C28: =AVERAGE(C2:C25) -> 42.553862 | D28: =AVERAGE(D2:D25) -> 65.999774 | E28: =AVERAGE(E2:E25) -> 80.516927 | F28: =AVERAGE(F2:F25) -> 96.849918
B30: Average Nordpool spot 2021, €/MWh

Sheet infra
A1: group | B1: subgroup | C1: variable | D1: unit | E1: 2020 | F1: 2025 | G1: 2030 | H1: 2035 | I1: 2040 | J1: 2045 | K1: 2050 | L1: Annual change | M1: Source | N1: Comment
A2: Infrastructure | B2: ERS | C2: base cost | D2: euro per km | E2: 1500000 | F2: {=E2*POWER(1+$L2,F$1:K$1-$E$1)} -> 1426485.1 | G2: 1356573.1 | H2: 1290087.5 | I2: 1226860.4 | J2: 1166732 | K2: 1109550.6 | L2: -0.01 | M2: See comment | N2: Increased from 1.2m to 1.5m after Hallsberg. ERS cost parameters are aggregates of numbers from Siemens, Elonroad and Electreon, provided in private communication. Representatives did not wish to be individually quoted. Numbers are inherrently speculative and based on cost levels reached during scale-up of technology so far built at pilot scale. | T2: kW | U2: 3000 | V2: 3000 | W2: 3000 | X2: 3000 | Y2: 3000 | Z2: 3000 | AA2: 3000
A3: Infrastructure | B3: ERS | C3: power cost | D3: euro per kW-km | E3: 700 | F3: {=E3*POWER(1+$L3,F$1:K$1-$E$1)} -> 665.69303 | G3: 633.06745 | H3: 602.04085 | I3: 572.53486 | J3: 544.47495 | K3: 517.79026 | L3: -0.01 | M3: See comment | N3: Increased from 150 to 700 after Hallsberg.
A4: Infrastructure | B4: ERS | C4: maintenance cost | D4: ratio per year | E4: 0.02 | F4: {=E4*POWER(1+$L4,F$1:K$1-$E$1)} -> 0.02 | G4: 0.02 | H4: 0.02 | I4: 0.02 | J4: 0.02 | K4: 0.02 | L4: 0 | M4: See comment | U4: {=E1:K1} -> 2020 | V4: 2025 | W4: 2030 | X4: 2035 | Y4: 2040 | Z4: 2045 | AA4: 2050
A5: Infrastructure | B5: ERS | C5: write off period | D5: years | E5: 25 | F5: {=E5*POWER(1+$L5,F$1:K$1-$E$1)} -> 25 | G5: 25 | H5: 25 | I5: 25 | J5: 25 | K5: 25 | L5: 0 | M5: See comment | T5: ERS (base) | U5: =E2 -> 1500000 | V5: =F2 -> 1426485.1 | W5: =G2 -> 1356573.1 | X5: =H2 -> 1290087.5 | Y5: =I2 -> 1226860.4 | Z5: =J2 -> 1166732 | AA5: =K2 -> 1109550.6 | AD5: 3000000
A6: Infrastructure | B6: ERS | C6: profit margin | D6: ratio | E6: {=E24:K24} -> 0.1 | F6: 0.1 | G6: 0.1 | H6: 0.1 | I6: 0.1 | J6: 0.1 | K6: 0.1 | M6: Same as station | T6: ERS (power) | U6: =U2*E3 -> 2100000 | V6: =V2*F3 -> 1997079.1 | W6: =W2*G3 -> 1899202.4 | X6: =X2*H3 -> 1806122.5 | Y6: =Y2*I3 -> 1717604.6 | Z6: =Z2*J3 -> 1633424.9 | AA6: =AA2*K3 -> 1553370.8 | AD6: 1500000
A7: Infrastructure | B7: ERS | C7: pick up cost base light | D7: euro | E7: 500 | F7: {=E7*POWER(1+$L7,F$1:K$1-$E$1)} -> 451.9604 | G7: 408.5364 | H7: 369.28455 | I7: 333.80399 | J7: 301.73236 | K7: 272.74216 | L7: -0.02 | M7: See comment | T7: Grid connections | U7: =(E44+E45*U2*E18+E17)/E18 -> 901500 | V7: =(F44+F45*V2*F18+F17)/F18 -> 901500 | W7: =(G44+G45*W2*G18+G17)/G18 -> 901500 | X7: =(H44+H45*X2*H18+H17)/H18 -> 901500 | Y7: =(I44+I45*Y2*I18+I17)/I18 -> 901500 | Z7: =(J44+J45*Z2*J18+J17)/J18 -> 901500 | AA7: =(K44+K45*AA2*K18+K17)/K18 -> 901500 | AC7: 1500 | AD7: =(AD5-AD6)/AC7 -> 1000
A8: Infrastructure | B8: ERS | C8: pick up cost base heavy | D8: euro | E8: 2000 | F8: {=E8*POWER(1+$L8,F$1:K$1-$E$1)} -> 1807.8416 | G8: 1634.1456 | H8: 1477.1382 | I8: 1335.2159 | J8: 1206.9295 | K8: 1090.9686 | L8: -0.02 | M8: See comment | T8: Capital interest | U8: =(U7+U5)*(world!E2/2)*infra!E5 -> 600375 | V8: =(V7+V5)*(world!F2/2)*infra!F5 -> 581996.27 | W8: =(W7+W5)*(world!G2/2)*infra!G5 -> 564518.28 | X8: =(X7+X5)*(world!H2/2)*infra!H5 -> 547896.88 | Y8: =(Y7+Y5)*(world!I2/2)*infra!I5 -> 532090.1 | Z8: =(Z7+Z5)*(world!J2/2)*infra!J5 -> 517058.01 | AA8: =(AA7+AA5)*(world!K2/2)*infra!K5 -> 502762.64
A9: Infrastructure | B9: ERS | C9: pick-up cost | D9: euro per kW | E9: 50 | F9: {=E9*POWER(1+$L9,F$1:K$1-$E$1)} -> 45.19604 | G9: 40.85364 | H9: 36.928455 | I9: 33.380399 | J9: 30.173236 | K9: 27.274216 | L9: -0.02 | M9: See comment | T9: Maintenance | U9: =E4*E5*(U5+U6) -> 1800000 | V9: =F4*F5*(V5+V6) -> 1711782.1 | W9: =G4*G5*(W5+W6) -> 1627887.7 | X9: =H4*H5*(X5+X6) -> 1548105 | Y9: =I4*I5*(Y5+Y6) -> 1472232.5 | Z9: =J4*J5*(Z5+Z6) -> 1400078.4 | AA9: =K4*K5*(AA5+AA6) -> 1331460.7
A10: Infrastructure | B10: ERS | C10: pick-up lifespan | D10: years | E10: 10 | F10: {=E10*POWER(1+$L10,F$1:K$1-$E$1)} -> 10 | G10: 10 | H10: 10 | I10: 10 | J10: 10 | K10: 10 | L10: 0 | M10: See comment | T10: Standardization risk | U10: =E14*E13*SUM(U5:U8) -> 765281.25 | V10: =F14*F13*SUM(V5:V8) -> 241191.84 | W10: =G14*G13*SUM(W5:W8) -> 76049.811 | X10: =H14*H13*SUM(X5:X8) -> 23990.149 | Y10: =I14*I13*SUM(Y5:Y8) -> 7571.3308 | Z10: =J14*J13*SUM(Z5:Z8) -> 2390.6781 | AA10: =K14*K13*SUM(AA5:AA8) -> 755.23949
A11: Infrastructure | B11: ERS | C11: pick up weight light | D11: kg | E11: 50 | F11: {=E11*POWER(1+$L11,F$1:K$1-$E$1)} -> 47.549502 | G11: 45.219104 | H11: 43.002918 | I11: 40.895347 | J11: 38.891068 | K11: 36.985019 | L11: -0.01 | M11: See comment | U11: =SUM(U5:U10) -> 7667156.2 | V11: =SUM(V5:V10) -> 6860034.4 | W11: =SUM(W5:W10) -> 6425731.3 | X11: =SUM(X5:X10) -> 6117702.1 | Y11: =SUM(Y5:Y10) -> 5857858.9 | Z11: =SUM(Z5:Z10) -> 5621184 | AA11: =SUM(AA5:AA10) -> 5399399.9
A12: Infrastructure | B12: ERS | C12: pick up weight heavy | D12: kg | E12: 300 | F12: {=E12*POWER(1+$L12,F$1:K$1-$E$1)} -> 285.29701 | G12: 271.31462 | H12: 258.01751 | I12: 245.37208 | J12: 233.34641 | K12: 221.91011 | L12: -0.01 | M12: See comment
A13: Infrastructure | B13: ERS | C13: standardization risk | D13: ratio | E13: 0.5 | F13: {=E13*POWER(1+$L13,F$1:K$1-$E$1)} -> 0.16384 | G13: 0.053687091 | H13: 0.017592186 | I13: 0.0057646075 | J13: 0.0018889466 | K13: 0.00061897002 | L13: -0.2 | M13: Risk of having picked a different standard than neighboring countries
A14: Infrastructure | B14: ERS | C14: cost of standard change | D14: ratio | E14: 0.3 | F14: {=E14*POWER(1+$L14,F$1:K$1-$E$1)} -> 0.3 | G14: 0.3 | H14: 0.3 | I14: 0.3 | J14: 0.3 | K14: 0.3 | L14: 0 | M14: Cost of retrofitting a new standard
A15: Infrastructure | B15: ERS | C15: utilization | D15: ratio | E15: {=H78:H79} -> 0.26531548 | F15: {=E15*POWER(1+$L15,F$1:K$1-$E$1)} -> 0.26531548 | G15: 0.26531548 | H15: 0.26531548 | I15: 0.26531548 | J15: 0.26531548 | K15: 0.26531548 | L15: 0
A16: Infrastructure | B16: ERS | C16: electricity price | D16: ratio | E16: 0.72604476 | F16: {=E16*POWER(1+$L16,F$1:K$1-$E$1)} -> 0.72604476 | G16: 0.72604476 | H16: 0.72604476 | I16: 0.72604476 | J16: 0.72604476 | K16: 0.72604476 | L16: 0
A17: Infrastructure | B17: ERS | C17: grid connection cable | D17: euro | E17: =20*500 -> 10000 | F17: {=E17*POWER(1+$L17,F$1:K$1-$E$1)} -> 10000 | G17: 10000 | H17: 10000 | I17: 10000 | J17: 10000 | K17: 10000 | L17: 0 | M17: 20 euro/m, 500 m (All digging costs from: https://www.diva-portal.org/smash/get/diva2:207284/FULLTEXT01.pdf)
A18: Infrastructure | B18: ERS | C18: grid connection interval | D18: km | E18: 10 | F18: {=E18*POWER(1+$L18,F$1:K$1-$E$1)} -> 10 | G18: 10 | H18: 10 | I18: 10 | J18: 10 | K18: 10 | L18: 0 | M18: See comment
A19: Infrastructure | B19: ERS | C19: reference | D19: aadt | E19: 2000 | F19: {=E19*POWER(1+$L19,F$1:K$1-$E$1)} -> 2000 | G19: 2000 | H19: 2000 | I19: 2000 | J19: 2000 | K19: 2000 | L19: 0 | M19: Bidirectional AADT Heavy in Sweden is ~4k on the largest roads. Assume half use ERS.
A20: Infrastructure | B20: Rest Stop | C20: hardware cost | D20: euro per kW | E20: 300 | F20: {=E20*POWER(1+$L20,F$1:K$1-$E$1)} -> 285.29701 | G20: 271.31462 | H20: 258.01751 | I20: 245.37208 | J20: 233.34641 | K20: 221.91011 | L20: -0.01 | M20: 300 from Andreas Kammel. 500 (probably includes grid) from a mix of Trafikverket, Karlström 2020 ("Kunskapssammanställning stationär laddning till tunga lastbilar"), Scania offer, Future Energy (FE). FE clearly states that hardware cost per kW increases with higher power.
A21: Infrastructure | B21: Rest Stop | C21: hardware maintenance | D21: ratio per year | E21: 0.1 | F21: {=E21*POWER(1+$L21,F$1:K$1-$E$1)} -> 0.097524875 | G21: 0.095111013 | H21: 0.092756897 | I21: 0.090461048 | J21: 0.088222024 | K21: 0.086038419 | L21: -0.005 | M21: Guess based on discussions with ChargeNode
A22: Infrastructure | B22: Rest Stop | C22: grid connection cable | D22: euro | E22: =20*750 -> 15000 | F22: {=E22*POWER(1+$L22,F$1:K$1-$E$1)} -> 15000 | G22: 15000 | H22: 15000 | I22: 15000 | J22: 15000 | K22: 15000 | L22: 0 | M22: 20 euro/m, 750 m
A23: Infrastructure | B23: Rest Stop | C23: write off period | D23: years | E23: 15 | F23: =E23+$L23*(F$1-E$1) -> 15 | G23: =F23+$L23*(G$1-F$1) -> 15 | H23: =G23+$L23*(H$1-G$1) -> 15 | I23: =H23+$L23*(I$1-H$1) -> 15 | J23: =I23+$L23*(J$1-I$1) -> 15 | K23: =J23+$L23*(K$1-J$1) -> 15 | L23: 0 | M23: TRV says 25. Kristoffer Ahlén, Price and Product Manager at Preem, says 10.
A24: Infrastructure | B24: Rest Stop | C24: profit margin | D24: ratio | E24: 0.1 | F24: {=E24*POWER(1+$L24,F$1:K$1-$E$1)} -> 0.1 | G24: 0.1 | H24: 0.1 | I24: 0.1 | J24: 0.1 | K24: 0.1 | L24: 0 | M24: Guess
A25: Infrastructure | B25: Rest Stop | C25: utilization | D25: ratio | E25: {=G78:G79} -> 0.19898661 | F25: {=E25*POWER(1+$L25,F$1:K$1-$E$1)} -> 0.19898661 | G25: 0.19898661 | H25: 0.19898661 | I25: 0.19898661 | J25: 0.19898661 | K25: 0.19898661 | L25: 0
A26: Infrastructure | B26: Rest Stop | C26: electricity price | D26: ratio | E26: 0.72604476 | F26: {=E26*POWER(1+$L26,F$1:K$1-$E$1)} -> 0.72604476 | G26: 0.72604476 | H26: 0.72604476 | I26: 0.72604476 | J26: 0.72604476 | K26: 0.72604476 | L26: 0
A27: Infrastructure | B27: Rest Stop | C27: reference | D27: vehicles per day | E27: 100 | F27: {=E27*POWER(1+$L27,F$1:K$1-$E$1)} -> 100 | G27: 100 | H27: 100 | I27: 100 | J27: 100 | K27: 100 | L27: 0 | M27: Seed value. Bidirectional AADT Heavy in Sweden is ~4k on the largest roads. If vehicles must stop every 5th opportunity and half use stations.
A28: Infrastructure | B28: Depot | C28: hardware cost | D28: euro per kW | E28: =E20 -> 300 | F28: {=E28*POWER(1+$L28,F$1:K$1-$E$1)} -> 285.29701 | G28: 271.31462 | H28: 258.01751 | I28: 245.37208 | J28: 233.34641 | K28: 221.91011 | L28: -0.01
A29: Infrastructure | B29: Depot | C29: hardware maintenance | D29: ratio per year | E29: 0.1 | F29: {=E29*POWER(1+$L29,F$1:K$1-$E$1)} -> 0.097524875 | G29: 0.095111013 | H29: 0.092756897 | I29: 0.090461048 | J29: 0.088222024 | K29: 0.086038419 | L29: -0.005 | M29: Guess based on discussions with ChargeNode
A30: Infrastructure | B30: Depot | C30: grid connection cable | D30: euro | E30: =50*100 -> 5000 | F30: {=E30*POWER(1+$L30,F$1:K$1-$E$1)} -> 5000 | G30: 5000 | H30: 5000 | I30: 5000 | J30: 5000 | K30: 5000 | L30: 0 | M30: 50 euro/m, 100 m
A31: Infrastructure | B31: Depot | C31: write off period | D31: years | E31: 7 | F31: =E31+$L31*(F$1-E$1) -> 7 | G31: =F31+$L31*(G$1-F$1) -> 7 | H31: =G31+$L31*(H$1-G$1) -> 7 | I31: =H31+$L31*(I$1-H$1) -> 7 | J31: =I31+$L31*(J$1-I$1) -> 7 | K31: =J31+$L31*(K$1-J$1) -> 7 | L31: 0 | M31: Guess
A32: Infrastructure | B32: Depot | C32: profit margin | D32: ratio | E32: 0.1 | F32: {=E32*POWER(1+$L32,F$1:K$1-$E$1)} -> 0.1 | G32: 0.1 | H32: 0.1 | I32: 0.1 | J32: 0.1 | K32: 0.1 | L32: 0 | M32: Guess, haulier rents infra
A33: Infrastructure | B33: Depot | C33: utilization | D33: ratio | E33: {=E78:E79} -> 0.34132097 | F33: {=E33*POWER(1+$L33,F$1:K$1-$E$1)} -> 0.34132097 | G33: 0.34132097 | H33: 0.34132097 | I33: 0.34132097 | J33: 0.34132097 | K33: 0.34132097 | L33: 0
A34: Infrastructure | B34: Depot | C34: electricity price | D34: ratio | E34: 0.37642925 | F34: {=E34*POWER(1+$L34,F$1:K$1-$E$1)} -> 0.37642925 | G34: 0.37642925 | H34: 0.37642925 | I34: 0.37642925 | J34: 0.37642925 | K34: 0.37642925 | L34: 0
A35: Infrastructure | B35: Depot | C35: reference | D35: vehicles per day | E35: 20 | F35: {=E35*POWER(1+$L35,F$1:K$1-$E$1)} -> 20 | G35: 20 | H35: 20 | I35: 20 | J35: 20 | K35: 20 | L35: 0 | M35: Seed value. Guess. | V35: AADT | W35: 4000
A36: Infrastructure | B36: Destination | C36: hardware cost | D36: euro per kW | E36: =E20 -> 300 | F36: {=E36*POWER(1+$L36,F$1:K$1-$E$1)} -> 285.29701 | G36: 271.31462 | H36: 258.01751 | I36: 245.37208 | J36: 233.34641 | K36: 221.91011 | L36: -0.01 | V36: km/h | W36: 85
A37: Infrastructure | B37: Destination | C37: hardware maintenance | D37: ratio per year | E37: 0.1 | F37: {=E37*POWER(1+$L37,F$1:K$1-$E$1)} -> 0.097524875 | G37: 0.095111013 | H37: 0.092756897 | I37: 0.090461048 | J37: 0.088222024 | K37: 0.086038419 | L37: -0.005 | M37: As rest stop | V37: Peak trucks/h | W37: =(W35/24)/H78 -> 628.18298
A38: Infrastructure | B38: Destination | C38: grid connection cable | D38: euro | E38: =E30 -> 5000 | F38: {=E38*POWER(1+$L38,F$1:K$1-$E$1)} -> 5000 | G38: 5000 | H38: 5000 | I38: 5000 | J38: 5000 | K38: 5000 | L38: 0 | M38: As depot | V38: Peak trucks/km | W38: =W37/W36 -> 7.390388
A39: Infrastructure | B39: Destination | C39: write off period | D39: years | E39: 10 | F39: =E39+$L39*(F$1-E$1) -> 10 | G39: =F39+$L39*(G$1-F$1) -> 10 | H39: =G39+$L39*(H$1-G$1) -> 10 | I39: =H39+$L39*(I$1-H$1) -> 10 | J39: =I39+$L39*(J$1-I$1) -> 10 | K39: =J39+$L39*(K$1-J$1) -> 10 | L39: 0 | M39: Guess | V39: Mean kW/truck-km | W39: 150
A40: Infrastructure | B40: Destination | C40: profit margin | D40: ratio | E40: 0.1 | F40: {=E40*POWER(1+$L40,F$1:K$1-$E$1)} -> 0.1 | G40: 0.1 | H40: 0.1 | I40: 0.1 | J40: 0.1 | K40: 0.1 | L40: 0 | M40: As depot | V40: Coverage | W40: 0.4
A41: Infrastructure | B41: Destination | C41: utilization | D41: ratio | E41: {=F78:F79} -> 0.13418254 | F41: {=E41*POWER(1+$L41,F$1:K$1-$E$1)} -> 0.13418254 | G41: 0.13418254 | H41: 0.13418254 | I41: 0.13418254 | J41: 0.13418254 | K41: 0.13418254 | L41: 0 | V41: kW/km | W41: =(W39/W40)*W38 -> 2771.3955
A42: Infrastructure | B42: Destination | C42: electricity price | D42: ratio | E42: 0.82451782 | F42: {=E42*POWER(1+$L42,F$1:K$1-$E$1)} -> 0.82451782 | G42: 0.82451782 | H42: 0.82451782 | I42: 0.82451782 | J42: 0.82451782 | K42: 0.82451782 | L42: 0
A43: Infrastructure | B43: Destination | C43: reference | D43: vehicles per day | E43: 50 | F43: {=E43*POWER(1+$L43,F$1:K$1-$E$1)} -> 50 | G43: 50 | H43: 50 | I43: 50 | J43: 50 | K43: 50 | L43: 0 | M43: Seed value. Guess.
A44: Infrastructure | B44: Grid | C44: initial acccess base | D44: euro | E44: 5000 | F44: {=E44*POWER(1+$L44,F$1:K$1-$E$1)} -> 5000 | G44: 5000 | H44: 5000 | I44: 5000 | J44: 5000 | K44: 5000 | L44: 0 | M44: Figure from Ellevio (Swedish DSO) used in past project
A45: Infrastructure | B45: Grid | C45: initial acccess | D45: euro per kW | E45: 300 | F45: {=E45*POWER(1+$L45,F$1:K$1-$E$1)} -> 300 | G45: 300 | H45: 300 | I45: 300 | J45: 300 | K45: 300 | L45: 0 | M45: As above. Adjusted from 100 to 300 based on feedback from Andreas Kammel.
A46: Infrastructure | B46: Grid | C46: fee at 10 percent utilization | D46: euro per kWh | E46: 0.06 | F46: {=E46*POWER(1+$L46,F$1:K$1-$E$1)} -> 0.06 | G46: 0.06 | H46: 0.06 | I46: 0.06 | J46: 0.06 | K46: 0.06 | L46: 0 | M46: As above
E48: Utilization
D49: Hour of day | E49: Depot | F49: Destination | G49: Rest Stop | H49: ERS | J49: Day of week | K49: Utilization
D50: 0 | E50: 1 | F50: 0 | G50: {=H50:H73} -> 0.15 | H50: 0.15 | J50: Mon | K50: 1
D51: 1 | E51: 1 | F51: 0 | G51: 0.15 | H51: 0.15 | J51: Tue | K51: 1
D52: 2 | E52: 1 | F52: 0 | G52: 0.15 | H52: 0.15 | J52: Wed | K52: 1
D53: 3 | E53: 1 | F53: 0 | G53: 0.15 | H53: 0.15 | J53: Thu | K53: 1
D54: 4 | E54: 1 | F54: 0 | G54: 0.2 | H54: 0.2 | J54: Fri | K54: 1
D55: 5 | E55: 0.85 | F55: 0 | G55: 0.3 | H55: 0.3 | J55: Sat | K55: 0.4
D56: 6 | E56: 0.7 | F56: 0 | G56: 0.5 | H56: 0.5 | J56: Sun | K56: 0.4
D57: 7 | E57: 0.3 | F57: 0.2 | G57: 0.6 | H57: 0.6 | J57: Average | K57: =AVERAGE(K50:K56) -> 0.82857143
D58: 8 | E58: 0.1 | F58: 0.5 | G58: 0.75 | H58: 0.75
D59: 9 | E59: 0.05 | F59: 1 | G59: 0.9 | H59: 0.9 | J59: Month | K59: Utilization
D60: 10 | E60: 0.05 | F60: 1 | G60: 1 | H60: 1 | J60: Jan | K60: 0.8
D61: 11 | E61: 0.05 | F61: 1 | G61: 1 | H61: 1 | J61: Feb | K61: 1
D62: 12 | E62: 0.8 | F62: 0.7 | G62: 1 | H62: 1 | J62: Mar | K62: 1
D63: 13 | E63: 0.8 | F63: 0.7 | G63: 1 | H63: 1 | J63: Apr | K63: 1
D64: 14 | E64: 0.05 | F64: 1 | G64: 1 | H64: 1 | J64: Maj | K64: 1
D65: 15 | E65: 0.05 | F65: 1 | G65: 0.9 | H65: 0.9 | J65: Jun | K65: 0.8
D66: 16 | E66: 0.05 | F66: 1 | G66: 0.8 | H66: 0.8 | J66: Jul | K66: 0.4
D67: 17 | E67: 0.3 | F67: 0.5 | G67: 0.7 | H67: 0.7 | J67: Aug | K67: 0.8
D68: 18 | E68: 0.7 | F68: 0.2 | G68: 0.6 | H68: 0.6 | J68: Sep | K68: 1
D69: 19 | E69: 0.8 | F69: 0 | G69: 0.4 | H69: 0.4 | J69: Okt | K69: 1
D70: 20 | E70: 0.9 | F70: 0 | G70: 0.3 | H70: 0.3 | J70: Nov | K70: 1
D71: 21 | E71: 1 | F71: 0 | G71: 0.2 | H71: 0.2 | J71: Dec | K71: 0.8
D72: 22 | E72: 1 | F72: 0 | G72: 0.15 | H72: 0.15 | J72: Average | K72: =AVERAGE(K60:K71) -> 0.88333333
D73: 23 | E73: 1 | F73: 0 | G73: 0.15 | H73: 0.15
D74: Average | E74: =AVERAGE(E50:E73) -> 0.60625 | F74: =AVERAGE(F50:F73) -> 0.36666667 | G74: =AVERAGE(G50:G73) -> 0.54375 | H74: =AVERAGE(H50:H73) -> 0.54375
C76: variable | D76: unit | E76: {=E49:H49} -> Depot | F76: Destination | G76: Rest Stop | H76: ERS
C77: Overcapacity (demand variability) | D77: percent | E77: 0.3 | F77: 1 | G77: 1 | H77: 0.5
C78: Annual utilization | D78: percent | E78: {=E74:H74*K57*K72/(1+E77:H77)} -> 0.34132097 | F78: 0.13418254 | G78: 0.19898661 | H78: 0.26531548
C79: Electricity price | D79: ratio min to max | E79: {=SUMPRODUCT(_xlfn.ANCHORARRAY('electricity price curves'!$J2)*infra!E50:E73)/SUM(infra!E50:E73)} -> 0.37642925 | F79: {=SUMPRODUCT(_xlfn.ANCHORARRAY('electricity price curves'!$J2)*infra!F50:F73)/SUM(infra!F50:F73)} -> 0.82451782 | G79: {=SUMPRODUCT(_xlfn.ANCHORARRAY('electricity price curves'!$J2)*infra!G50:G73)/SUM(infra!G50:G73)} -> 0.72604476 | H79: {=SUMPRODUCT(_xlfn.ANCHORARRAY('electricity price curves'!$J2)*infra!H50:H73)/SUM(infra!H50:H73)} -> 0.72604476
C80: Grid fee | D80: euro per kWh | E80: {=E46/(10*_xlfn.ANCHORARRAY(E78))} -> 0.017578762 | F80: 0.044715207 | G80: 0.030152783 | H80: 0.022614587
C81: Electricity price €/kWh | D81: euro per kWh | E81: {=world!E27+E79:H79*(world!E28-world!E27)} -> 0.091607451 | F81: 0.11578636 | G81: 0.11047274 | H81: 0.11047274
C82: Fees | D82: euro per kWh | E82: {=_xlfn.ANCHORARRAY(E81)+_xlfn.ANCHORARRAY(E80)} -> 0.10918621 | F82: 0.16050157 | G82: 0.14062553 | H82: 0.13308733
F84: Peak vehicles | I84: Peak power | L84: Annual capex | O84: Annual opex | R84: Cost per kWh
C85: kWh per visit | D85: Vehicles per day | E85: Energy per day | F85: depot | G85: destination | H85: station | I85: depot | J85: destination | K85: station | L85: depot | M85: destination | N85: station | O85: depot | P85: destination | Q85: station | R85: depot | S85: destination | T85: station
C86: 300 | D86: 5 | E86: {=D86:D93*C86} -> 1500 | F86: {=IF(_xlfn.CEILING.MATH(D86:D93*TRANSPOSE(vehicles!F13:F15)/(24*E78:G78))<D86:D93,_xlfn.CEILING.MATH(D86:D93*TRANSPOSE(vehicles!F13:F15)/(24*E78:G78)),D86:D93)} -> 5 | G86: 2 | H86: 1 | I86: {=_xlfn.ANCHORARRAY(F86)*C86/TRANSPOSE(vehicles!F13:F15)} -> 166.66667 | J86: 600 | K86: 400 | L86: {=(($E$44+$E$45*I86:I93+E30)+(E28*I86:I93)*(1+E31*E29))*(1+world!E4*E31/2)/E31} -> 25789.286 | M86: {=(($E$44+$E$45*J86:J93+E38)+(E36*J86:J93)*(1+E39*E37))*(1+world!E3*E39/2)/E39} -> 63250 | N86: {=(($E$44+$E$45*K86:K93+E22)+(E20*K86:K93)*(1+E23*E21))*(1+world!E3*E23/2)/E23} -> 35933.333 | O86: {=_xlfn.ANCHORARRAY(E86)*365*(E80:G80+E81:G81)} -> 59779.451 | P86: 87874.608 | Q86: 76992.475 | R86: {=(L86:N93+_xlfn.ANCHORARRAY(O86))/(_xlfn.ANCHORARRAY(E86)*365)} -> 0.15628993 | S86: 0.27602668 | T86: 0.20625718
D87: 10 | E87: 3000 | F87: 10 | G87: 4 | H87: 2 | I87: 333.33333 | J87: 1200 | K87: 800 | L87: 49800 | M87: 125350 | N87: 70233.333 | O87: 119558.9 | P87: 175749.22 | Q87: 153984.95 | R87: 0.15466566 | S87: 0.27497645 | T87: 0.20476556
D88: 20 | E88: 6000 | F88: 20 | G88: 7 | H88: 4 | I88: 666.66667 | J88: 2100 | K88: 1600 | L88: 97821.429 | M88: 218500 | N88: 138833.33 | O88: 239117.81 | P88: 351498.43 | Q88: 307969.9 | R88: 0.15385353 | S88: 0.26027326 | T88: 0.20401974
D89: 50 | E89: 15000 | F89: 50 | G89: 16 | H89: 8 | I89: 1666.6667 | J89: 4800 | K89: 3200 | L89: 241885.71 | M89: 497950 | N89: 276033.33 | O89: 597794.51 | P89: 878746.08 | Q89: 769924.75 | R89: 0.15336625 | S89: 0.25145134 | T89: 0.19104257
D90: 100 | E90: 30000 | F90: 100 | G90: 32 | H90: 16 | I90: 3333.3333 | J90: 9600 | K90: 6400 | L90: 481992.86 | M90: 994750 | N90: 550433.33 | O90: 1195589 | P90: 1757492.2 | Q90: 1539849.5 | R90: 0.15320383 | S90: 0.25134632 | T90: 0.19089341
D91: 200 | E91: 60000 | F91: 200 | G91: 63 | H91: 32 | I91: 6666.6667 | J91: 18900 | K91: 12800 | L91: 962207.14 | M91: 1957300 | N91: 1099233.3 | O91: 2391178.1 | P91: 3514984.3 | Q91: 3079699 | R91: 0.15312261 | S91: 0.249876 | T91: 0.19081883
D92: 500 | E92: 150000 | F92: 500 | G92: 156 | H92: 79 | I92: 16666.667 | J92: 46800 | K92: 31600 | L92: 2402850 | M92: 4844950 | N92: 2711333.3 | O92: 5977945.1 | P92: 8787460.8 | Q92: 7699247.5 | R92: 0.15307388 | S92: 0.2489938 | T92: 0.1901476 | V92: Konstant mängd energi att leverera
D93: 1000 | E93: 300000 | F93: 1000 | G93: 311 | H93: 158 | I93: 33333.333 | J93: 93300 | K93: 63200 | L93: 4803921.4 | M93: 9657700 | N93: 5421033.3 | O93: 11955890 | P93: 17574922 | Q93: 15398495 | R93: 0.15305764 | S93: 0.24869974 | T93: 0.19013268 | V93: Variera mängd väg
C94: BIDIRECTIONAL ERS
C95: kW per vehicle | D95: Bidirectional AADT | E95: kWh/km-day | F95: kWh/km-y | G95: Peak v/km | H95: Peak kW/km | I95: HW/ers-km | J95: Grid/ers-km | K95: Capex/ers-km-y | L95: Opex/ers-km-y | M95: Cost per kWh | N95: €/kWh (excl. nrg) | Q95: Prop. kWh/km-y | R95: Pot. kWh/km-y
C96: 150 | D96: {=100*D86:D90} -> 500 | E96: {=_xlfn.ANCHORARRAY(D96)*C96/C98} -> 882.35294 | F96: {=_xlfn.ANCHORARRAY(E96)*365} -> 322058.82 | G96: {=_xlfn.CEILING.MATH(_xlfn.ANCHORARRAY(D96)/(24*H78*C98))} -> 1 | H96: {=C96*_xlfn.ANCHORARRAY(G96)} -> 150 | I96: {=(H2+H3*_xlfn.ANCHORARRAY(H96))*(1+H4*H5)*(1+H13*H14)} -> 2081518.4 | J96: {=(H44+H45*_xlfn.ANCHORARRAY(H96)*H18+H17)/H18} -> 46500 | K96: {=(_xlfn.ANCHORARRAY(I96)+_xlfn.ANCHORARRAY(J96))*(1+world!H2*H5/2)/H5} -> 106400.92 | L96: {=_xlfn.ANCHORARRAY(F96)*(H80+H81)} -> 42861.949 | M96: {=(_xlfn.ANCHORARRAY(K96)+_xlfn.ANCHORARRAY(L96))/_xlfn.ANCHORARRAY(F96)+C102} -> 0.47816095 | N96: {=(_xlfn.ANCHORARRAY(K96)+_xlfn.ANCHORARRAY(F96)*H80)/_xlfn.ANCHORARRAY(F96)} -> 0.35299187 | Q96: {=_xlfn.ANCHORARRAY(D96)*vehicles!E77*365} -> 1825000 | R96: {=_xlfn.ANCHORARRAY(D96)*C96/C98*365} -> 322058.82
C97: Speed km/h | D97: 1000 | E97: 1764.7059 | F97: 644117.65 | G97: 2 | H97: 300 | I97: 2217692.5 | J97: 91500 | K97: 115459.62 | L97: 85723.898 | M97: 0.32703605 | N97: 0.20186697 | Q97: 3650000 | R97: 644117.65
C98: 85 | D98: 2000 | E98: 3529.4118 | F98: 1288235.3 | G98: 4 | H98: 600 | I98: 2490040.6 | J98: 181500 | K98: 133577.03 | L98: 171447.8 | M98: 0.25147361 | N98: 0.12630452 | Q98: 7300000 | R98: 1288235.3
C99: ERS energy ratio | D99: 5000 | E99: 8823.5294 | F99: 3220588.2 | G99: 10 | H99: 1500 | I99: 3307085.2 | J99: 451500 | K99: 187929.26 | L99: 428619.49 | M99: 0.20613614 | N99: 0.080967052 | Q99: 18250000 | R99: 3220588.2
C100: 0.5 | D100: 10000 | E100: 17647.059 | F100: 6441176.5 | G100: 19 | H100: 2850 | I100: 4532652.1 | J100: 856500 | K100: 269457.61 | L100: 857238.98 | M100: 0.18961727 | N100: 0.064448188 | Q100: 36500000 | R100: 6441176.5
C101: Pickup €/kWh
C102: =(E8+E9*C96)/(E10*vehicles!E84*vehicles!E106*C100) -> 0.014696342
T103: x | U103: x | V103: x | W103: x | X103: y | Y103: y | Z103: y | AA103: y
...

Sheet world
A1: group | B1: subgroup | C1: variable | D1: unit | E1: 2020 | F1: 2025 | G1: 2030 | H1: 2035 | I1: 2040 | J1: 2045 | K1: 2050 | L1: Annual change | M1: Sources | N1: Comments
A2: World | B2: Economy | C2: Public sector interest rate | D2: percent | E2: 0.02 | F2: {=E2*POWER(1+$L2,F$1:K$1-$E$1)} -> 0.02 | G2: 0.02 | H2: 0.02 | I2: 0.02 | J2: 0.02 | K2: 0.02 | L2: 0 | M2: https://www.pwc.se/sv/pdf-reports/corporate-finance/riskpremiestudien-2021.pdf, https://www.riksgalden.se/sv/var-verksamhet/statslanerantan/ | N2: Statslåneräntan speglar den riskfria räntan (se riksgalden.se). Tar medelvärde av PWC-studien och senaste 50-åriga statsobligationen som gavs ut.
A3: World | B3: Economy | C3: Private sector interest public charging and trucks | D3: percent | E3: 0.03 | F3: {=E3*POWER(1+$L3,F$1:K$1-$E$1)} -> 0.03 | G3: 0.03 | H3: 0.03 | I3: 0.03 | J3: 0.03 | K3: 0.03 | L3: 0 | M3: 6% above base interest, companies with credit rating AAA/AA (https://firmalan.com/sv/lana-pengar/jamfor-lan/)
A4: World | B4: Economy | C4: Private sector interest depot charging | D4: percent | E4: 0.07 | F4: {=E4*POWER(1+$L4,F$1:K$1-$E$1)} -> 0.07 | G4: 0.07 | H4: 0.07 | I4: 0.07 | J4: 0.07 | K4: 0.07 | L4: 0 | M4: 10% above base interest. Depot chargers should offer poor security. (https://firmalan.com/sv/lana-pengar/jamfor-lan/)
A5: World | B5: Economy | C5: Heavy traffic volume vs 2020 | D5: percent | E5: 2.5 | F5: {=E5*POWER(1+$L5,F$1:K$1-$E$1)} -> 2.6667803 | G5: 2.8446868 | H5: 3.0344619 | I5: 3.2368973 | J5: 3.4528375 | K5: 3.6831836 | L5: 0.013 | M5: Trafikverket's base forecast for road cargo 2017-2040, Fig 6.4 (https://trafikverket.diva-portal.org/smash/get/diva2:1749263/FULLTEXT01.pdf)
A6: World | B6: Economy | C6: Logistic BEV penalty | D6: percent | E6: 0.15 | F6: {=_xlfn.SEQUENCE(1,6,E6+(L6-E6)/6,(L6-E6)/6)} -> 0.125 | G6: 0.1 | H6: 0.075 | I6: 0.05 | J6: 0.025 | K6: 0 | L6: 0 | M6: Guess | N6: Based on reasoning that BEVs will be less flexible/viable on fewer routes in the beginning. Single-route TCO must be this much lower to beat diesel.
A7: World | B7: Charging | C7: Extra stop overhead | D7: h | E7: =15/60 -> 0.25 | F7: {=E7*POWER(1+$L7,F$1:K$1-$E$1)} -> 0.21468351 | G7: 0.18435603 | H7: 0.1583128 | I7: 0.13594859 | J7: 0.11674368 | K7: 0.10025177 | L7: -0.03 | M7: Guess. Getting to the charger, plugging in, paying, battery conditioning, will get smoother. | N7: Getting to the charger, plugging in, paying, battery conditioning, will get smoother
A8: World | B8: CO₂ | C8: SCC | D8: euro per kg | E8: 0.08 | F8: =AVERAGE(E8,G8) -> 0.165 | G8: 0.25 | H8: =AVERAGE(G8,I8) -> 0.3875 | I8: 0.525 | J8: =AVERAGE(I8,K8) -> 0.6625 | K8: 0.8 | M8: https://www.eib.org/attachments/lucalli/20240105_eib_sasb_report_2023_en.pdf | N8: EIB shadow cost of carbon
A9: World | B9: CO₂ | C9: Tax | D9: ratio of SCC | E9: 0.7 | F9: =E9+$L9 -> 0.75 | G9: =F9+$L9 -> 0.8 | H9: =G9+$L9 -> 0.85 | I9: =H9+$L9 -> 0.9 | J9: =I9+$L9 -> 0.95 | K9: =J9+$L9 -> 1 | L9: 0.05 | M9: To match current CO₂ tax.
A10: World | B10: FossilDiesel | C10: Price | D10: euro per liter | E10: 0.6 | F10: {=E10*POWER(1+$L10,F$1:K$1-$E$1)} -> 0.63687443 | G10: 0.67601507 | H10: 0.71756118 | I10: 0.76166062 | J10: 0.80847029 | K10: 0.85815676 | L10: 0.012 | M10: Approximate product cost in Sweden in april 2023, estimated from product costs of FAME and HVO and blend ratios. Highly unreliable forecast.
A11: World | B11: RenewableDiesel | C11: Price | D11: euro per liter | E11: 1.5 | F11: =E11 -> 1.5 | G11: {=F11*POWER(1+$L11,G$1:K$1-$F$1)} -> 1.5921861 | H11: 1.6900377 | I11: 1.793903 | J11: 1.9041515 | K11: 2.0211757 | L11: 0.012 | M11: alliance.eu/efuels/costs-outlook), which is likely a biased source. | N11: Probably need to vary this in experiments
A12: World | B12: RenewableDiesel | C12: Supply cap | D12: liter per year | E12: =E13*0.35*4000000000*E5 -> 175000000 | F12: {=E12*POWER(1+$L12,F$1:K$1-$E$1)} -> 1.9321414e+08 | G12: 2.1332402e+08 | H12: 2.3552696e+08 | I12: 2.6004079e+08 | J12: 2.8710605e+08 | K12: 3.1698828e+08 | L12: 0.02 | M12: "Blend guess" ratio of total fuel used in 2020 according to the simulation. | N12: In 2018: All diesel for trucks and cars = 56.3 TWh/y, 23% renewable, diesel 10 kWh/liter = 1.259e9 liter/year. I ended up ignoring that number and set this based on total fuel in the sim instead. Biofuels seem to contribute around 7% of total transport energy in 2022 (https://www.epure.org/wp-content/uploads/2022/10/221011-DEF-REP-Overview-of-biofuels-policies-and-markets-across-the-EU-October-2022.pdf) | O12: Sweden already uses a large percentage of the world supply
A13: World | B13: RenewableDiesel | C13: Blend guess | D13: ratio | E13: 0.05 | F13: 0.06 | G13: 0.08 | H13: =1-(1-G13)*(1-$L13)^5 -> 0.28812154 | I13: =1-(1-H13)*(1-$L13)^5 -> 0.44916202 | J13: =1-(1-I13)*(1-$L13)^5 -> 0.57377207 | K13: =1-(1-J13)*(1-$L13)^5 -> 0.67019295 | L13: 0.05 | M13: https://www.energimyndigheten.se/globalassets/nyheter/2020/er-2020_26-drivmedel-2019.pdf | N13: High ratio is enabled by lower diesel consumption due to electrification | O13: It's complicated. Reduktionsplikten for 2020 is 30% CO2e reduction for diesel, which requires >30% biofuels. Actual sales seem to amount to 29% renewables for diesel + HVO100 + FAME100. Forecast based on a mix of Swedish reduktionsplikt and e-Fuel Alliance forecast. Increasing share is by reduced ICEV market share.
A14: World | B14: FossilDiesel | C14: Emissions | D14: kg CO₂ per liter | E14: 3.23 | F14: {=E14*POWER(1+$L14,F$1:K$1-$E$1)} -> 3.23 | G14: 3.23 | H14: 3.23 | I14: 3.23 | J14: 3.23 | K14: 3.23 | L14: 0 | M14: Auke Hoekstra (2020) "Electric trucks: economically and environmentally desirable but misunderstood" | N14: https://www.elaad.nl/uploads/files/Auke_Hoekstra_-_Electric_trucks_economically_and_environmentally_desirable_but_misunderstood.pdf | O14: This paper says 2.8 (fig 5.1, (1060*20/(1060-850))/(36 MJ/liter)): https://theicct.org/wp-content/uploads/2021/06/LNG-in-trucks_May2020.pdf
A15: World | B15: RenewableDiesel | C15: Emissions | D15: kg CO₂ per liter | E15: 0.67 | F15: {=E15*POWER(1+$L15,F$1:K$1-$E$1)} -> 0.51843323 | G15: 0.40115375 | H15: 0.31040512 | I15: 0.24018557 | J15: 0.18585101 | K15: 0.14380797 | L15: -0.05 | M15: 2020 value from https://www.miljofordon.se/bilar/miljoepaaverkan/ Most of biodiesel's emission is from use of fossil oil, which is expected to gradually be displaced by sustainable sources.
A16: World | B16: Diesel | C16: Price | D16: euro per liter | E16: {=(1-E13:K13)*E10:K10+E13:K13*E11:K11} -> 0.645 | F16: 0.68866196 | G16: 0.74930875 | H16: 0.9977526 | I16: 1.2253047 | J16: 1.4371416 | K16: 1.6376039 | L16: n/a | M16: =""
A17: World | B17: Diesel | C17: Emissions | D17: kg CO₂ per liter | E17: {=(1-E13:K13)*E14:K14+E13:K13*E15:K15} -> 3.102 | F17: 3.067306 | G17: 3.0036923 | H17: 2.3888018 | I17: 1.8870889 | J17: 1.4833523 | K17: 1.1616559 | L17: n/a | M17: =""
A18: World | B18: Diesel | C18: CO₂ tax | D18: euro per liter | E18: {=E17:K17*E9:K9*E8:K8} -> 0.173712 | F18: 0.37957912 | G18: 0.60073846 | H18: 0.7868116 | I18: 0.89164952 | J18: 0.93358488 | K18: 0.92932468 | L18: n/a | M18: CO₂ tax on diesel in Sweden in 2022. | N18: Swedish diesel CO₂ tax is 2.5 SEK/liter as of june 2023, plus VAT which we exclude
A19: World | B19: Diesel | C19: Pollution tax | D19: euro per liter | E19: 0.02 | F19: {=E19*POWER(1+$L19,F$1:K$1-$E$1)} -> 0.0322102 | G19: 0.051874849 | H19: 0.083544963 | I19: 0.13455 | J19: 0.21669412 | K19: 0.34898805 | L19: 0.1 | M19: Guess | N19: ICEs release NOx, particles and noise. I assume these will be penalized.
A20: World | B20: Diesel | C20: Road tax | D20: euro per liter | E20: 0.4 | F20: {=E20*POWER(1+$L20,F$1:K$1-$E$1)} -> 0.4 | G20: 0.4 | H20: 0.4 | I20: 0.4 | J20: 0.4 | K20: 0.4 | L20: 0 | M20: Swedish energy tax has ranged between 1.5 and 2.5 SEK/liter. German energy tax is approx €0.5/liter.
A21: World | B21: Electricity | C21: Conversion ratio | D21: kWh per liter | E21: =vehicles!X25 -> 4.1637318 | F21: =E21 -> 4.1637318 | G21: =F21 -> 4.1637318 | H21: =G21 -> 4.1637318 | I21: =H21 -> 4.1637318 | J21: =I21 -> 4.1637318 | K21: =J21 -> 4.1637318 | L21: n/a | M21: =""
A22: World | B22: Electricity | C22: Road tax | D22: euro per kWh | E22: {=E20:K20/E21:K21} -> 0.096067668 | F22: 0.096067668 | G22: 0.096067668 | H22: 0.096067668 | I22: 0.096067668 | J22: 0.096067668 | K22: 0.096067668 | L22: n/a | M22: =""
A23: SE12 | B23: SE12 | C23: Price min | D23: euro per kWh | E23: {=E31:E33} -> 0.071295288 | F23: {=E23*POWER(1+$L23,F$1:K$1-$E$1)} -> 0.071295288 | G23: 0.071295288 | H23: 0.071295288 | I23: 0.071295288 | J23: 0.071295288 | K23: 0.071295288 | L23: {=L31:L33} -> 0 | M23: Values from OtherRegion
A24: SE12 | B24: SE12 | C24: Price max | D24: euro per kWh | E24: 0.1252554 | F24: {=E24*POWER(1+$L24,F$1:K$1-$E$1)} -> 0.1252554 | G24: 0.1252554 | H24: 0.1252554 | I24: 0.1252554 | J24: 0.1252554 | K24: 0.1252554 | L24: 0 | M24: Values from OtherRegion
A25: SE12 | B25: SE12 | C25: CO₂ emissions | D25: kg per kWh | E25: 0.265 | F25: {=E25*POWER(1+$L25,F$1:K$1-$E$1)} -> 0.1746566 | G25: 0.11511294 | H25: 0.075868812 | I25: 0.050003732 | J25: 0.032956536 | K25: 0.021721044 | L25: -0.08 | M25: Values from OtherRegion
A26: SE12 | B26: SE12 | C26: CO₂ tax | D26: euro per kWh | E26: {=E25:K25*E9:K9*E8:K8} -> 0.01484 | F26: 0.021613755 | G26: 0.023022588 | H26: 0.02498929 | I26: 0.023626763 | J26: 0.02074202 | K26: 0.017376835 | L26: n/a | M26: =""
A27: SE34 | B27: SE34 | C27: Price min | D27: euro per kWh | E27: {=E31:E33} -> 0.071295288 | F27: {=E27*POWER(1+$L27,F$1:K$1-$E$1)} -> 0.071295288 | G27: 0.071295288 | H27: 0.071295288 | I27: 0.071295288 | J27: 0.071295288 | K27: 0.071295288 | L27: {=L31:L33} -> 0 | M27: Values from OtherRegion
A28: SE34 | B28: SE34 | C28: Price max | D28: euro per kWh | E28: 0.1252554 | F28: {=E28*POWER(1+$L28,F$1:K$1-$E$1)} -> 0.1252554 | G28: 0.1252554 | H28: 0.1252554 | I28: 0.1252554 | J28: 0.1252554 | K28: 0.1252554 | L28: 0 | M28: Values from OtherRegion | P28: {=E28:K28-E27:K27} -> 0.05396011 | Q28: 0.05396011 | R28: 0.05396011 | S28: 0.05396011 | T28: 0.05396011 | U28: 0.05396011 | V28: 0.05396011
A29: SE34 | B29: SE34 | C29: CO₂ emissions | D29: kg per kWh | E29: 0.265 | F29: {=E29*POWER(1+$L29,F$1:K$1-$E$1)} -> 0.1746566 | G29: 0.11511294 | H29: 0.075868812 | I29: 0.050003732 | J29: 0.032956536 | K29: 0.021721044 | L29: -0.08 | M29: Values from OtherRegion
A30: SE34 | B30: SE34 | C30: CO₂ tax | D30: euro per kWh | E30: {=E29:K29*E9:K9*E8:K8} -> 0.01484 | F30: 0.021613755 | G30: 0.023022588 | H30: 0.02498929 | I30: 0.023626763 | J30: 0.02074202 | K30: 0.017376835 | L30: n/a | M30: =""
A31: OtherRegion | B31: OtherRegion | C31: Price min | D31: euro per kWh | E31: ='electricity price curves'!F26/1000 -> 0.071295288 | F31: {=E31*POWER(1+$L31,F$1:K$1-$E$1)} -> 0.071295288 | G31: 0.071295288 | H31: 0.071295288 | I31: 0.071295288 | J31: 0.071295288 | K31: 0.071295288 | L31: 0 | M31: Nordpool spot prices (DE-LU), min average price per hour, 2021
A32: OtherRegion | B32: OtherRegion | C32: Price max | D32: euro per kWh | E32: ='electricity price curves'!F27/1000 -> 0.1252554 | F32: {=E32*POWER(1+$L32,F$1:K$1-$E$1)} -> 0.1252554 | G32: 0.1252554 | H32: 0.1252554 | I32: 0.1252554 | J32: 0.1252554 | K32: 0.1252554 | L32: 0 | M32: Nordpool spot prices (DE-LU), max average price per hour, 2021
A33: OtherRegion | B33: OtherRegion | C33: CO₂ emissions | D33: kg per kWh | E33: 0.265 | F33: {=E33*POWER(1+$L33,F$1:K$1-$E$1)} -> 0.1746566 | G33: 0.11511294 | H33: 0.075868812 | I33: 0.050003732 | J33: 0.032956536 | K33: 0.021721044 | L33: -0.08 | M33: Greenhouse gas emission intensity of electricity generation in Europe (https://www.eea.europa.eu/ims/greenhouse-gas-emission-intensity-of-1)
A34: OtherRegion | B34: OtherRegion | C34: CO₂ tax | D34: euro per kWh | E34: {=E33:K33*E9:K9*E8:K8} -> 0.01484 | F34: 0.021613755 | G34: 0.023022588 | H34: 0.02498929 | I34: 0.023626763 | J34: 0.02074202 | K34: 0.017376835 | L34: n/a | M34: =""
C37: Effective diesel price, incl tax | D37: euro per liter | E37: {=_xlfn.ANCHORARRAY(E16)+_xlfn.ANCHORARRAY(E18)+E19:K19+E20:K20} -> 1.238712 | F37: 1.5004513 | G37: 1.8019221 | H37: 2.2681092 | I37: 2.6515042 | J37: 2.9874206 | K37: 3.3159166
C38: Effective diesel tax ratio | D38: percent | E38: {=(_xlfn.ANCHORARRAY(E18)+E19:K19+E20:K20)/_xlfn.ANCHORARRAY(E37)} -> 0.47929785 | F38: 0.54103011 | G38: 0.5841614 | H38: 0.56009498 | I38: 0.53788318 | J38: 0.51893563 | K38: 0.5061384
C39: Equivalent reduktionsplikt | D39: percent | E39: {=1-_xlfn.ANCHORARRAY(E17)/E14:K14} -> 0.039628483 | F39: 0.050369661 | G39: 0.070064303 | H39: 0.26043287 | I39: 0.41576194 | J39: 0.54075779 | K39: 0.64035422 | N39: =1.64*0.35 -> 0.574
C40: Equivalent diesel emissions | D40: kg CO₂ per kWh | E40: {=_xlfn.ANCHORARRAY(E17)/(vehicles!E106:K106/vehicles!E103:K103)} -> 0.74500476 | F40: 0.74038539 | G40: 0.72868472 | H40: 0.58243548 | I40: 0.46242739 | J40: 0.36532466 | K40: 0.28753826
C41: Electricity vs diesel cost | D41: ratio | E41: {=AVERAGE(E27:E28)*E21:K21/_xlfn.ANCHORARRAY(E16)} -> 0.63440646 | F41: 0.59418435 | G41: 0.54609287 | H41: 0.41011385 | I41: 0.33395136 | J41: 0.28472641 | K41: 0.2498725
A43: Backup of values used in RISE REPORT
A44: group | B44: subgroup | C44: variable | D44: unit | E44: 2020 | F44: 2025 | G44: 2030 | H44: 2035 | I44: 2040 | J44: 2045 | K44: 2050 | L44: Annual change | M44: Sources | N44: Comments
A45: World | B45: Economy | C45: Public sector interest rate | D45: percent | E45: 0.02 | F45: 0.02 | G45: 0.02 | H45: 0.02 | I45: 0.02 | J45: 0.02 | K45: 0.02 | L45: 0 | M45: https://www.pwc.se/sv/pdf-reports/corporate-finance/riskpremiestudien-2021.pdf, samt https://www.riksgalden.se/sv/var-verksamhet/statslanerantan/ | N45: Statslåneräntan speglar den riskfria räntan (se riksgalden.se). Tar medelvärde av PWC-studien och senaste 50-åriga statsobligationen som gavs ut.
A46: World | B46: Economy | C46: Private sector interest public charging | D46: percent | E46: 0.06 | F46: 0.06 | G46: 0.06 | H46: 0.06 | I46: 0.06 | J46: 0.06 | K46: 0.06 | L46: 0 | M46: https://firmalan.com/sv/lana-pengar/jamfor-lan/ | N46: Företag med hög kreditvärdighet, AAA/AA. Förutsätter att ränta rör företagslån. För stora företag är företagsobligationer ett alternativ
A47: World | B47: Economy | C47: Private sector interest depot and trucks | D47: percent | E47: 0.12 | F47: 0.12 | G47: 0.12 | H47: 0.12 | I47: 0.12 | J47: 0.12 | K47: 0.12 | L47: 0 | M47: https://firmalan.com/sv/lana-pengar/jamfor-lan/ | N47: Företag med kreditvärdighet A/B, förutsätter företagslån.
A48: World | B48: Charging | C48: Extra stop overhead | D48: h | E48: 0.16666667 | F48: 0.14312234 | G48: 0.12290402 | H48: 0.10554186 | I48: 0.09063239 | J48: 0.077829118 | K48: 0.066834511 | L48: -0.03 | N48: Getting to the charger, plugging in, paying, battery conditioning, will get smoother
A49: World | B49: CO₂ | C49: SCC | D49: euro per kg | E49: 0.7 | F49: 0.7 | G49: 0.7 | H49: 0.7 | I49: 0.7 | J49: 0.7 | K49: 0.7 | L49: 0 | M49: https://www.trafikverket.se/contentassets/4b1c1005597d47bda386d81dd3444b24/asek-2021/12_klimateffekter_a70.pdf | N49: ASEK 7.0
A50: World | B50: CO₂ | C50: Tax | D50: ratio of SCC | E50: 0.12 | F50: 0.17 | G50: 0.22 | H50: 0.27 | I50: 0.32 | J50: 0.37 | K50: 0.42 | L50: 0.05 | N50: Koldioxidskatt på 2.29 kr/liter idag. Gissning om framtiden.
A51: World | B51: Diesel | C51: Price | D51: euro per liter | E51: 1 | F51: 1.1592741 | G51: 1.3439164 | H51: 1.5579674 | I51: 1.8061112 | J51: 2.0937779 | K51: 2.4272625 | L51: 0.03 | M51: https://drivkraftsverige.se/statistik/priser/mer-prisstatistik/arsmedelspriser-motorbranslen/ | N51: Approximation of calculation below, corresponding to an increasing mix-in of biofuels
A52: World | B52: Diesel | C52: Emissions | D52: kg CO₂ per liter | E52: 2.6 | F52: 2.119969 | G52: 1.7285649 | H52: 1.4094246 | I52: 1.1492063 | J52: 0.93703146 | K52: 0.76402987 | L52: -0.04 | N52: Approximation of calculation below, corresponding to an increasing mix-in of biofuels
A53: World | B53: Diesel | C53: CO₂ tax | D53: euro per liter | E53: 0.2184 | F53: 0.25227631 | G53: 0.26619899 | H53: 0.26638125 | I53: 0.25742222 | J53: 0.24269115 | K53: 0.22462478
A54: World | B54: Diesel | C54: Road tax | D54: euro per liter | E54: 0.251 | F54: 0.251 | G54: 0.251 | H54: 0.251 | I54: 0.251 | J54: 0.251 | K54: 0.251 | L54: 0 | M54: https://www.ekonomifakta.se/fakta/energi/styrmedel/konsumtionsskatter-pa-diesel/ | N54: Energiskatt på 2.51 kr/liter idag. Gissning om framtiden
A55: World | B55: Electricity | C55: Conversion ratio | D55: kWh per liter | E55: 4.1637318 | F55: 4.1637318 | G55: 4.1637318 | H55: 4.1637318 | I55: 4.1637318 | J55: 4.1637318 | K55: 4.1637318
A56: World | B56: Electricity | C56: Road tax | D56: euro per kWh | E56: 0.060282462 | F56: 0.060282462 | G56: 0.060282462 | H56: 0.060282462 | I56: 0.060282462 | J56: 0.060282462 | K56: 0.060282462
A57: SE12 | B57: SE12 | C57: Price min | D57: euro per kWh | E57: 0.03445874 | F57: 0.036216482 | G57: 0.038063886 | H57: 0.040005527 | I57: 0.042046211 | J57: 0.04419099 | K57: 0.046445175 | L57: 0.01 | M57: https://www.nordpoolgroup.com/Market-data1/Dayahead/Area-Prices/SE/Hourly/?view=table | N57: Nordpool spotpriser medel per timme 2021
A58: SE12 | B58: SE12 | C58: Price max | D58: euro per kWh | E58: 0.048914219 | F58: 0.051409336 | G58: 0.054031729 | H58: 0.05678789 | I58: 0.059684643 | J58: 0.06272916 | K58: 0.065928977 | L58: 0.01 | M58: https://www.nordpoolgroup.com/Market-data1/Dayahead/Area-Prices/SE/Hourly/?view=table | N58: Nordpool spotpriser medel per timme 2021
A59: SE12 | B59: SE12 | C59: CO₂ emissions | D59: kg per kWh | E59: 0.01 | F59: 0.0085873403 | G59: 0.0073742413 | H59: 0.0063325119 | I59: 0.0054379434 | J59: 0.0046697471 | K59: 0.0040100707 | L59: -0.03 | N59: Svensk elproduktion
A60: SE12 | B60: SE12 | C60: CO₂ tax | D60: euro per kWh | E60: 0.00084 | F60: 0.0010218935 | G60: 0.0011356332 | H60: 0.0011968447 | I60: 0.0012180993 | J60: 0.0012094645 | K60: 0.0011789608
A61: SE34 | B61: SE34 | C61: Price min | D61: euro per kWh | E61: 0.043459219 | F61: 0.045676076 | G61: 0.048006015 | H61: 0.050454804 | I61: 0.053028506 | J61: 0.055733493 | K61: 0.058576461 | L61: 0.01 | M61: https://www.nordpoolgroup.com/Market-data1/Dayahead/Area-Prices/SE/Hourly/?view=table | N61: Nordpool spotpriser medel per timme 2021
A62: SE34 | B62: SE34 | C62: Price max | D62: euro per kWh | E62: 0.097833534 | F62: 0.10282403 | G62: 0.10806909 | H62: 0.1135817 | I62: 0.1193755 | J62: 0.12546485 | K62: 0.13186482 | L62: 0.01 | M62: https://www.nordpoolgroup.com/Market-data1/Dayahead/Area-Prices/SE/Hourly/?view=table | N62: Nordpool spotpriser medel per timme 2021
A63: SE34 | B63: SE34 | C63: CO₂ emissions | D63: kg per kWh | E63: 0.09 | F63: 0.069640284 | G63: 0.053886325 | H63: 0.041696211 | I63: 0.032263733 | J63: 0.024965062 | K63: 0.019317489 | L63: -0.05 | M63: https://naturvardsverket.diva-portal.org/smash/get/diva2:1540012/FULLTEXT01.pdf | N63: Nordisk elmix, approaching current Swedish level of 0.005
A64: SE34 | B64: SE34 | C64: CO₂ tax | D64: euro per kWh | E64: 0.00756 | F64: 0.0082871938 | G64: 0.008298494 | H64: 0.0078805838 | I64: 0.0072270762 | J64: 0.0064659509 | K64: 0.0056793417
A65: OtherRegion | B65: OtherRegion | C65: Price min | D65: euro per kWh | E65: 0.06 | F65: 0.063060603 | G65: 0.066277328 | H65: 0.069658137 | I65: 0.073211402 | J65: 0.07694592 | K65: 0.080870935 | L65: 0.01 | M65: Guess
A66: OtherRegion | B66: OtherRegion | C66: Price max | D66: euro per kWh | E66: 0.2 | F66: 0.21020201 | G66: 0.22092443 | H66: 0.23219379 | I66: 0.24403801 | J66: 0.2564864 | K66: 0.26956978 | L66: 0.01 | M66: Guess
A67: OtherRegion | B67: OtherRegion | C67: CO₂ emissions | D67: kg per kWh | E67: 0.3 | F67: 0.23213428 | G67: 0.17962108 | H67: 0.13898737 | I67: 0.10754578 | J67: 0.083216872 | K67: 0.064391629 | L67: -0.05 | M67: Guess
A68: OtherRegion | B68: OtherRegion | C68: CO₂ tax | D68: euro per kWh | E68: 0.01644552 | F68: 0.014699057 | G68: 0.012001552 | H68: 0.0092929308 | I68: 0.0069488528 | J68: 0.0050691956 | K68: 0.0036304529
A72: Backup of variables

Sheet world (SE)
A1: group | B1: subgroup | C1: variable | D1: unit | E1: 2020 | F1: 2025 | G1: 2030 | H1: 2035 | I1: 2040 | J1: 2045 | K1: 2050 | L1: Annual change | M1: Sources | N1: Comments
A2: World | B2: Economy | C2: Public sector interest rate | D2: percent | E2: 0.03 | F2: {=E2*POWER(1+$L2,F$1:K$1-$E$1)} -> 0.03 | G2: 0.03 | H2: 0.03 | I2: 0.03 | J2: 0.03 | K2: 0.03 | L2: 0 | M2: https://www.pwc.se/sv/pdf-reports/corporate-finance/riskpremiestudien-2021.pdf, samt https://www.riksgalden.se/sv/var-verksamhet/statslanerantan/ | N2: Statslåneräntan speglar den riskfria räntan (se riksgalden.se). Tar medelvärde av PWC-studien och senaste 50-åriga statsobligationen som gavs ut.
A3: World | B3: Economy | C3: Private sector interest public charging and trucks | D3: percent | E3: 0.08 | F3: {=E3*POWER(1+$L3,F$1:K$1-$E$1)} -> 0.08 | G3: 0.08 | H3: 0.08 | I3: 0.08 | J3: 0.08 | K3: 0.08 | L3: 0 | M3: https://firmalan.com/sv/lana-pengar/jamfor-lan/ | N3: +6% på basränta. Företag med hög kreditvärdighet, AAA/AA. Förutsätter att ränta rör företagslån. För stora företag är företagsobligationer ett alternativ
A4: World | B4: Economy | C4: Private sector interest depot charging | D4: percent | E4: 0.12 | F4: {=E4*POWER(1+$L4,F$1:K$1-$E$1)} -> 0.12 | G4: 0.12 | H4: 0.12 | I4: 0.12 | J4: 0.12 | K4: 0.12 | L4: 0 | M4: https://firmalan.com/sv/lana-pengar/jamfor-lan/ | N4: +10% på basränta. Företag med kreditvärdighet A/B, förutsätter företagslån. Depåladdare är sämre säkerhet än lastbilar.
A5: World | B5: Economy | C5: Heavy traffic volume vs 2020 | D5: percent | E5: 1 | F5: {=E5*POWER(1+$L5,F$1:K$1-$E$1)} -> 1.1040808 | G5: 1.2189944 | H5: 1.3458683 | I5: 1.4859474 | J5: 1.640606 | K5: 1.8113616 | L5: 0.02 | M5: https://trafikverket.diva-portal.org/smash/get/diva2:1749263/FULLTEXT01.pdf | N5: TRVs basprognos för gods på väg 2017-2040, Fig 6.4
A6: World | B6: Charging | C6: Extra stop overhead | D6: h | E6: =15/60 -> 0.25 | F6: {=E6*POWER(1+$L6,F$1:K$1-$E$1)} -> 0.21468351 | G6: 0.18435603 | H6: 0.1583128 | I6: 0.13594859 | J6: 0.11674368 | K6: 0.10025177 | L6: -0.03 | M6: Guess | N6: Getting to the charger, plugging in, paying, battery conditioning, will get smoother
A7: World | B7: CO₂ | C7: SCC | D7: euro per kg | E7: 0.7 | F7: {=E7*POWER(1+$L7,F$1:K$1-$E$1)} -> 0.7 | G7: 0.7 | H7: 0.7 | I7: 0.7 | J7: 0.7 | K7: 0.7 | L7: 0 | M7: https://www.trafikverket.se/contentassets/4b1c1005597d47bda386d81dd3444b24/asek-2021/12_klimateffekter_a70.pdf | N7: ASEK 7.0 says 7 SEK/kg. US EPA has proposed $190/ton https://www.epa.gov/system/files/documents/2022-11/epa_scghg_report_draft_0.pdf, $185/ton https://www.nature.com/articles/s41586-022-05224-9,
A8: World | B8: CO₂ | C8: Tax | D8: ratio of SCC | E8: 0.2 | F8: =E8+$L8 -> 0.25 | G8: =F8+$L8 -> 0.3 | H8: =G8+$L8 -> 0.35 | I8: =H8+$L8 -> 0.4 | J8: =I8+$L8 -> 0.45 | K8: =J8+$L8 -> 0.5 | L8: 0.05 | M8: Koldioxidskatt på 2.29 kr/liter idag. Gissning om framtiden.
A9: World | B9: FossilDiesel | C9: Price | D9: euro per liter | E9: 1 | F9: {=E9*POWER(1+$L9,F$1:K$1-$E$1)} -> 1.0510101 | G9: 1.1046221 | H9: 1.160969 | I9: 1.22019 | J9: 1.282432 | K9: 1.3478489 | L9: 0.01 | N9: Approximate product cost in Sweden in april 2023, estimated from product costs of FAME and HVO and blend ratios. Cannot forecast. Run sensitivity analysis.
A10: World | B10: RenewableDiesel | C10: Price | D10: euro per liter | E10: 2 | F10: =E10 -> 2 | G10: {=F10*POWER(1+$L10,G$1:K$1-$F$1)} -> 1.9019801 | H10: 1.8087642 | I10: 1.7201167 | J10: 1.6358139 | K10: 1.5556427 | L10: -0.01 | N10: Probably need to vary this in experiments | O10: Cannot derive cost of biofuels in Sweden. E-fuel Alliance forecasts 1.61-1.99/l @ 2025 --> 0.70-1.33 @ 2050 https://www.efuel-alliance.eu/efuels/costs-outlook
A11: World | B11: RenewableDiesel | C11: Supply cap | D11: liter per year | E11: =E12*1640000000 -> 574000000 | F11: {=E11*POWER(1+$L11,F$1:K$1-$E$1)} -> 6.0327977e+08 | G11: 6.340531e+08 | H11: 6.6639618e+08 | I11: 7.0038908e+08 | J11: 7.3611597e+08 | K11: 7.7366528e+08 | L11: 0.01 | M11: https://www.energimyndigheten.se/globalassets/statistik/drivmedel-2018.pdf | N11: In 2018: All diesel for trucks and cars = 56.3 TWh/y, 23% renewable, diesel 10 kWh/liter = 1.259e9 liter/year. I ended up ignoring that number and set this based on total fuel in the sim instead. Biofuels seem to contribute around 7% of total transport energy in 2022 (https://www.epure.org/wp-content/uploads/2022/10/221011-DEF-REP-Overview-of-biofuels-policies-and-markets-across-the-EU-October-2022.pdf) | O11: Sweden already uses a large percentage of the world supply
A12: World | B12: RenewableDiesel | C12: Blend guess | D12: ratio | E12: 0.35 | F12: 0.4 | G12: 0.5 | H12: =1-(1-G12)*(1-$L12)^5 -> 0.77814734 | I12: =1-(1-H12)*(1-$L12)^5 -> 0.9015628 | J12: =1-(1-I12)*(1-$L12)^5 -> 0.95632289 | K12: =1-(1-J12)*(1-$L12)^5 -> 0.98062023 | L12: 0.15 | M12: https://www.energimyndigheten.se/globalassets/nyheter/2020/er-2020_26-drivmedel-2019.pdf | N12: High ratio is enabled by lower diesel consumption due to electrification | O12: It's complicated. Reduktionsplikten for 2020 is 30% CO2e reduction for diesel, which requires >30% biofuels. Actual sales seem to amount to 29% renewables for diesel + HVO100 + FAME100. Forecast based on a mix of Swedish reduktionsplikt and e-Fuel Alliance forecast. Increasing share is by reduced ICEV market share.
A13: World | B13: FossilDiesel | C13: Emissions | D13: kg CO₂ per liter | E13: 3.23 | F13: {=E13*POWER(1+$L13,F$1:K$1-$E$1)} -> 3.23 | G13: 3.23 | H13: 3.23 | I13: 3.23 | J13: 3.23 | K13: 3.23 | L13: 0 | N13: Hoekstra 2020 | O13: https://www.elaad.nl/uploads/files/Auke_Hoekstra_-_Electric_trucks_economically_and_environmentally_desirable_but_misunderstood.pdf
A14: World | B14: RenewableDiesel | C14: Emissions | D14: kg CO₂ per liter | E14: 0.67 | F14: {=E14*POWER(1+$L14,F$1:K$1-$E$1)} -> 0.51843323 | G14: 0.40115375 | H14: 0.31040512 | I14: 0.24018557 | J14: 0.18585101 | K14: 0.14380797 | L14: -0.05 | N14: From Swedish source: https://www.miljofordon.se/bilar/miljoepaaverkan/ Most of biodiesel's emission is from use of fossil oil, which is expected to gradually be displaced by sustainable sources.
A15: World | B15: Diesel | C15: Price | D15: euro per liter | E15: {=(1-E12:K12)*E9:K9+E12:K12*E10:K10} -> 1.35 | F15: 1.430606 | G15: 1.5033011 | H15: 1.6650491 | I15: 1.6709053 | J15: 1.6203792 | K15: 1.5516157 | L15: n/a | M15: https://drivkraftsverige.se/statistik/priser/mer-prisstatistik/arsmedelspriser-motorbranslen/
A16: World | B16: Diesel | C16: Emissions | D16: kg CO₂ per liter | E16: {=(1-E12:K12)*E13:K13+E12:K12*E14:K14} -> 2.334 | F16: 2.1453733 | G16: 1.8155769 | H16: 0.958125 | I16: 0.53449454 | J16: 0.31881064 | K16: 0.20361765 | L16: n/a | M16: n/a
A17: World | B17: Diesel | C17: CO₂ tax | D17: euro per liter | E17: {=E16:K16*E8:K8*E7:K7} -> 0.32676 | F17: 0.37544033 | G17: 0.38127114 | H17: 0.23474063 | I17: 0.14965847 | J17: 0.10042535 | K17: 0.071266177 | L17: n/a | M17: n/a | N17: Swedish diesel CO₂ tax is 2.5 SEK/liter as of june 2023, plus VAT which we exclude
A18: World | B18: Diesel | C18: Pollution tax | D18: euro per liter | E18: 0.02 | F18: {=E18*POWER(1+$L18,F$1:K$1-$E$1)} -> 0.0322102 | G18: 0.051874849 | H18: 0.083544963 | I18: 0.13455 | J18: 0.21669412 | K18: 0.34898805 | L18: 0.1 | M18: Guess | N18: ICEs release NOx, particles and noise. I assume these will be penalized.
A19: World | B19: Diesel | C19: Road tax | D19: euro per liter | E19: 0.2 | F19: {=E19*POWER(1+$L19,F$1:K$1-$E$1)} -> 0.2 | G19: 0.2 | H19: 0.2 | I19: 0.2 | J19: 0.2 | K19: 0.2 | L19: 0 | M19: https://www.ekonomifakta.se/fakta/energi/styrmedel/konsumtionsskatter-pa-diesel/ | N19: Swedish energy tax has ranged between 1.5 and 2.5 SEK/liter. German energy tax is approx €0.5/liter.
A20: World | B20: Electricity | C20: Conversion ratio | D20: kWh per liter | E20: =vehicles!X25 -> 4.1637318 | F20: =E20 -> 4.1637318 | G20: =F20 -> 4.1637318 | H20: =G20 -> 4.1637318 | I20: =H20 -> 4.1637318 | J20: =I20 -> 4.1637318 | K20: =J20 -> 4.1637318 | L20: n/a | M20: n/a
A21: World | B21: Electricity | C21: Road tax | D21: euro per kWh | E21: {=E19:K19/E20:K20} -> 0.048033834 | F21: 0.048033834 | G21: 0.048033834 | H21: 0.048033834 | I21: 0.048033834 | J21: 0.048033834 | K21: 0.048033834 | L21: n/a | M21: n/a
A22: SE12 | B22: SE12 | C22: Price min | D22: euro per kWh | E22: ='electricity price curves'!B26/1000 -> 0.03445874 | F22: {=E22*POWER(1+$L22,F$1:K$1-$E$1)} -> 0.03445874 | G22: 0.03445874 | H22: 0.03445874 | I22: 0.03445874 | J22: 0.03445874 | K22: 0.03445874 | L22: 0 | M22: https://www.nordpoolgroup.com/Market-data1/Dayahead/Area-Prices/SE/Hourly/?view=table | N22: Nordpool spot prices, min average price per hour, 2021
A23: SE12 | B23: SE12 | C23: Price max | D23: euro per kWh | E23: ='electricity price curves'!B27/1000 -> 0.048860986 | F23: {=E23*POWER(1+$L23,F$1:K$1-$E$1)} -> 0.048860986 | G23: 0.048860986 | H23: 0.048860986 | I23: 0.048860986 | J23: 0.048860986 | K23: 0.048860986 | L23: 0 | M23: https://www.nordpoolgroup.com/Market-data1/Dayahead/Area-Prices/SE/Hourly/?view=table | N23: Nordpool spot prices, max average price per hour, 2021
A24: SE12 | B24: SE12 | C24: CO₂ emissions | D24: kg per kWh | E24: 0.01 | F24: {=E24*POWER(1+$L24,F$1:K$1-$E$1)} -> 0.009039208 | G24: 0.0081707281 | H24: 0.007385691 | I24: 0.0066760797 | J24: 0.0060346473 | K24: 0.0054548432 | L24: -0.02 | M24: n/a | N24: Svensk elproduktion
A25: SE12 | B25: SE12 | C25: CO₂ tax | D25: euro per kWh | E25: {=E24:K24*E8:K8*E7:K7} -> 0.0014 | F25: 0.0015818614 | G25: 0.0017158529 | H25: 0.0018094943 | I25: 0.0018693023 | J25: 0.0019009139 | K25: 0.0019091951 | L25: n/a | M25: n/a
A26: SE34 | B26: SE34 | C26: Price min | D26: euro per kWh | E26: =AVERAGE('electricity price curves'!D26:E26)/1000 -> 0.043459219 | F26: {=E26*POWER(1+$L26,F$1:K$1-$E$1)} -> 0.043459219 | G26: 0.043459219 | H26: 0.043459219 | I26: 0.043459219 | J26: 0.043459219 | K26: 0.043459219 | L26: 0 | M26: https://www.nordpoolgroup.com/Market-data1/Dayahead/Area-Prices/SE/Hourly/?view=table | N26: Nordpool spot prices, min average price per hour, 2021
A27: SE34 | B27: SE34 | C27: Price max | D27: euro per kWh | E27: =AVERAGE('electricity price curves'!D27:E27)/1000 -> 0.097833534 | F27: {=E27*POWER(1+$L27,F$1:K$1-$E$1)} -> 0.097833534 | G27: 0.097833534 | H27: 0.097833534 | I27: 0.097833534 | J27: 0.097833534 | K27: 0.097833534 | L27: 0 | M27: https://www.nordpoolgroup.com/Market-data1/Dayahead/Area-Prices/SE/Hourly/?view=table | N27: Nordpool spot prices, max average price per hour, 2021 | P27: {=E27:K27-E26:K26} -> 0.054374315 | Q27: 0.054374315 | R27: 0.054374315 | S27: 0.054374315 | T27: 0.054374315 | U27: 0.054374315 | V27: 0.054374315
A28: SE34 | B28: SE34 | C28: CO₂ emissions | D28: kg per kWh | E28: 0.09 | F28: {=E28*POWER(1+$L28,F$1:K$1-$E$1)} -> 0.069640284 | G28: 0.053886325 | H28: 0.041696211 | I28: 0.032263733 | J28: 0.024965062 | K28: 0.019317489 | L28: -0.05 | M28: https://naturvardsverket.diva-portal.org/smash/get/diva2:1540012/FULLTEXT01.pdf | N28: Nordisk elmix, approaching current Swedish level of 0.005
A29: SE34 | B29: SE34 | C29: CO₂ tax | D29: euro per kWh | E29: {=E28:K28*E8:K8*E7:K7} -> 0.0126 | F29: 0.01218705 | G29: 0.011316128 | H29: 0.010215572 | I29: 0.0090338452 | J29: 0.0078639944 | K29: 0.0067611211 | L29: n/a | M29: n/a
A30: OtherRegion | B30: OtherRegion | C30: Price min | D30: euro per kWh | E30: ='electricity price curves'!F26/1000 -> 0.071295288 | F30: {=E30*POWER(1+$L30,F$1:K$1-$E$1)} -> 0.071295288 | G30: 0.071295288 | H30: 0.071295288 | I30: 0.071295288 | J30: 0.071295288 | K30: 0.071295288 | L30: 0 | M30: Germany | N30: Nordpool spot prices (DE-LU), min average price per hour, 2021
A31: OtherRegion | B31: OtherRegion | C31: Price max | D31: euro per kWh | E31: ='electricity price curves'!F27/1000 -> 0.1252554 | F31: {=E31*POWER(1+$L31,F$1:K$1-$E$1)} -> 0.1252554 | G31: 0.1252554 | H31: 0.1252554 | I31: 0.1252554 | J31: 0.1252554 | K31: 0.1252554 | L31: 0 | M31: Germany | N31: Nordpool spot prices (DE-LU), max average price per hour, 2021
A32: OtherRegion | B32: OtherRegion | C32: CO₂ emissions | D32: kg per kWh | E32: 0.265 | F32: {=E32*POWER(1+$L32,F$1:K$1-$E$1)} -> 0.1746566 | G32: 0.11511294 | H32: 0.075868812 | I32: 0.050003732 | J32: 0.032956536 | K32: 0.021721044 | L32: -0.08 | M32: EU: https://www.eea.europa.eu/data-and-maps/daviz/co2-emission-intensity-13/#tab-googlechartid_chart_11
A33: OtherRegion | B33: OtherRegion | C33: CO₂ tax | D33: euro per kWh | E33: {=E32:K32*E8:K8*E7:K7} -> 0.0371 | F33: 0.030564906 | G33: 0.024173717 | H33: 0.018587859 | I33: 0.014001045 | J33: 0.010381309 | K33: 0.0076023654 | L33: n/a | M33: n/a
C36: Effective diesel price, incl tax | D36: euro per liter | E36: {=_xlfn.ANCHORARRAY(E15)+_xlfn.ANCHORARRAY(E17)+E18:K18+E19:K19} -> 1.89676 | F36: 2.0382566 | G36: 2.1364471 | H36: 2.1833347 | I36: 2.1551138 | J36: 2.1374986 | K36: 2.1718699
C37: Effective diesel tax ratio | D37: percent | E37: {=(_xlfn.ANCHORARRAY(E17)+E18:K18+E19:K19)/_xlfn.ANCHORARRAY(E36)} -> 0.28825998 | F37: 0.29812269 | G37: 0.29635463 | H37: 0.23738257 | I37: 0.22467884 | J37: 0.24192739 | K37: 0.28558534
C38: Equivalent reduktionsplikt | D38: percent | E38: {=1-_xlfn.ANCHORARRAY(E16)/E13:K13} -> 0.27739938 | F38: 0.33579774 | G38: 0.4379019 | H38: 0.70336687 | I38: 0.83452182 | J38: 0.90129701 | K38: 0.93696048 | N38: =1.64*0.35 -> 0.574
C39: Equivalent diesel emissions | D39: kg CO₂ per kWh | E39: {=_xlfn.ANCHORARRAY(E16)/(vehicles!E106:K106/vehicles!E103:K103)} -> 0.56055484 | F39: 0.51784956 | G39: 0.44045228 | H39: 0.23360916 | I39: 0.13097682 | J39: 0.078517683 | K39: 0.050400352
C40: Electricity vs diesel cost | D40: ratio | E40: {=AVERAGE(E26:E27)*E20:K20/_xlfn.ANCHORARRAY(E15)} -> 0.21789079 | F40: 0.20561395 | G40: 0.19567109 | H40: 0.176663 | I40: 0.17604382 | J40: 0.18153317 | K40: 0.18957823
A42: Backup of values used in RISE REPORT
A43: group | B43: subgroup | C43: variable | D43: unit | E43: 2020 | F43: 2025 | G43: 2030 | H43: 2035 | I43: 2040 | J43: 2045 | K43: 2050 | L43: Annual change | M43: Sources | N43: Comments
A44: World | B44: Economy | C44: Public sector interest rate | D44: percent | E44: 0.02 | F44: 0.02 | G44: 0.02 | H44: 0.02 | I44: 0.02 | J44: 0.02 | K44: 0.02 | L44: 0 | M44: https://www.pwc.se/sv/pdf-reports/corporate-finance/riskpremiestudien-2021.pdf, samt https://www.riksgalden.se/sv/var-verksamhet/statslanerantan/ | N44: Statslåneräntan speglar den riskfria räntan (se riksgalden.se). Tar medelvärde av PWC-studien och senaste 50-åriga statsobligationen som gavs ut.
A45: World | B45: Economy | C45: Private sector interest public charging | D45: percent | E45: 0.06 | F45: 0.06 | G45: 0.06 | H45: 0.06 | I45: 0.06 | J45: 0.06 | K45: 0.06 | L45: 0 | M45: https://firmalan.com/sv/lana-pengar/jamfor-lan/ | N45: Företag med hög kreditvärdighet, AAA/AA. Förutsätter att ränta rör företagslån. För stora företag är företagsobligationer ett alternativ
A46: World | B46: Economy | C46: Private sector interest depot and trucks | D46: percent | E46: 0.12 | F46: 0.12 | G46: 0.12 | H46: 0.12 | I46: 0.12 | J46: 0.12 | K46: 0.12 | L46: 0 | M46: https://firmalan.com/sv/lana-pengar/jamfor-lan/ | N46: Företag med kreditvärdighet A/B, förutsätter företagslån.
A47: World | B47: Charging | C47: Extra stop overhead | D47: h | E47: 0.16666667 | F47: 0.14312234 | G47: 0.12290402 | H47: 0.10554186 | I47: 0.09063239 | J47: 0.077829118 | K47: 0.066834511 | L47: -0.03 | N47: Getting to the charger, plugging in, paying, battery conditioning, will get smoother
A48: World | B48: CO₂ | C48: SCC | D48: euro per kg | E48: 0.7 | F48: 0.7 | G48: 0.7 | H48: 0.7 | I48: 0.7 | J48: 0.7 | K48: 0.7 | L48: 0 | M48: https://www.trafikverket.se/contentassets/4b1c1005597d47bda386d81dd3444b24/asek-2021/12_klimateffekter_a70.pdf | N48: ASEK 7.0
A49: World | B49: CO₂ | C49: Tax | D49: ratio of SCC | E49: 0.12 | F49: 0.17 | G49: 0.22 | H49: 0.27 | I49: 0.32 | J49: 0.37 | K49: 0.42 | L49: 0.05 | N49: Koldioxidskatt på 2.29 kr/liter idag. Gissning om framtiden.
A50: World | B50: Diesel | C50: Price | D50: euro per liter | E50: 1 | F50: 1.1592741 | G50: 1.3439164 | H50: 1.5579674 | I50: 1.8061112 | J50: 2.0937779 | K50: 2.4272625 | L50: 0.03 | M50: https://drivkraftsverige.se/statistik/priser/mer-prisstatistik/arsmedelspriser-motorbranslen/ | N50: Approximation of calculation below, corresponding to an increasing mix-in of biofuels
A51: World | B51: Diesel | C51: Emissions | D51: kg CO₂ per liter | E51: 2.6 | F51: 2.119969 | G51: 1.7285649 | H51: 1.4094246 | I51: 1.1492063 | J51: 0.93703146 | K51: 0.76402987 | L51: -0.04 | N51: Approximation of calculation below, corresponding to an increasing mix-in of biofuels
A52: World | B52: Diesel | C52: CO₂ tax | D52: euro per liter | E52: 0.2184 | F52: 0.25227631 | G52: 0.26619899 | H52: 0.26638125 | I52: 0.25742222 | J52: 0.24269115 | K52: 0.22462478
A53: World | B53: Diesel | C53: Road tax | D53: euro per liter | E53: 0.251 | F53: 0.251 | G53: 0.251 | H53: 0.251 | I53: 0.251 | J53: 0.251 | K53: 0.251 | L53: 0 | M53: https://www.ekonomifakta.se/fakta/energi/styrmedel/konsumtionsskatter-pa-diesel/ | N53: Energiskatt på 2.51 kr/liter idag. Gissning om framtiden
A54: World | B54: Electricity | C54: Conversion ratio | D54: kWh per liter | E54: 4.1637318 | F54: 4.1637318 | G54: 4.1637318 | H54: 4.1637318 | I54: 4.1637318 | J54: 4.1637318 | K54: 4.1637318
A55: World | B55: Electricity | C55: Road tax | D55: euro per kWh | E55: 0.060282462 | F55: 0.060282462 | G55: 0.060282462 | H55: 0.060282462 | I55: 0.060282462 | J55: 0.060282462 | K55: 0.060282462
A56: SE12 | B56: SE12 | C56: Price min | D56: euro per kWh | E56: 0.03445874 | F56: 0.036216482 | G56: 0.038063886 | H56: 0.040005527 | I56: 0.042046211 | J56: 0.04419099 | K56: 0.046445175 | L56: 0.01 | M56: https://www.nordpoolgroup.com/Market-data1/Dayahead/Area-Prices/SE/Hourly/?view=table | N56: Nordpool spotpriser medel per timme 2021
A57: SE12 | B57: SE12 | C57: Price max | D57: euro per kWh | E57: 0.048914219 | F57: 0.051409336 | G57: 0.054031729 | H57: 0.05678789 | I57: 0.059684643 | J57: 0.06272916 | K57: 0.065928977 | L57: 0.01 | M57: https://www.nordpoolgroup.com/Market-data1/Dayahead/Area-Prices/SE/Hourly/?view=table | N57: Nordpool spotpriser medel per timme 2021
A58: SE12 | B58: SE12 | C58: CO₂ emissions | D58: kg per kWh | E58: 0.01 | F58: 0.0085873403 | G58: 0.0073742413 | H58: 0.0063325119 | I58: 0.0054379434 | J58: 0.0046697471 | K58: 0.0040100707 | L58: -0.03 | N58: Svensk elproduktion
A59: SE12 | B59: SE12 | C59: CO₂ tax | D59: euro per kWh | E59: 0.00084 | F59: 0.0010218935 | G59: 0.0011356332 | H59: 0.0011968447 | I59: 0.0012180993 | J59: 0.0012094645 | K59: 0.0011789608
A60: SE34 | B60: SE34 | C60: Price min | D60: euro per kWh | E60: 0.043459219 | F60: 0.045676076 | G60: 0.048006015 | H60: 0.050454804 | I60: 0.053028506 | J60: 0.055733493 | K60: 0.058576461 | L60: 0.01 | M60: https://www.nordpoolgroup.com/Market-data1/Dayahead/Area-Prices/SE/Hourly/?view=table | N60: Nordpool spotpriser medel per timme 2021
A61: SE34 | B61: SE34 | C61: Price max | D61: euro per kWh | E61: 0.097833534 | F61: 0.10282403 | G61: 0.10806909 | H61: 0.1135817 | I61: 0.1193755 | J61: 0.12546485 | K61: 0.13186482 | L61: 0.01 | M61: https://www.nordpoolgroup.com/Market-data1/Dayahead/Area-Prices/SE/Hourly/?view=table | N61: Nordpool spotpriser medel per timme 2021
A62: SE34 | B62: SE34 | C62: CO₂ emissions | D62: kg per kWh | E62: 0.09 | F62: 0.069640284 | G62: 0.053886325 | H62: 0.041696211 | I62: 0.032263733 | J62: 0.024965062 | K62: 0.019317489 | L62: -0.05 | M62: https://naturvardsverket.diva-portal.org/smash/get/diva2:1540012/FULLTEXT01.pdf | N62: Nordisk elmix, approaching current Swedish level of 0.005
A63: SE34 | B63: SE34 | C63: CO₂ tax | D63: euro per kWh | E63: 0.00756 | F63: 0.0082871938 | G63: 0.008298494 | H63: 0.0078805838 | I63: 0.0072270762 | J63: 0.0064659509 | K63: 0.0056793417
A64: OtherRegion | B64: OtherRegion | C64: Price min | D64: euro per kWh | E64: 0.06 | F64: 0.063060603 | G64: 0.066277328 | H64: 0.069658137 | I64: 0.073211402 | J64: 0.07694592 | K64: 0.080870935 | L64: 0.01 | M64: Guess
A65: OtherRegion | B65: OtherRegion | C65: Price max | D65: euro per kWh | E65: 0.2 | F65: 0.21020201 | G65: 0.22092443 | H65: 0.23219379 | I65: 0.24403801 | J65: 0.2564864 | K65: 0.26956978 | L65: 0.01 | M65: Guess
A66: OtherRegion | B66: OtherRegion | C66: CO₂ emissions | D66: kg per kWh | E66: 0.3 | F66: 0.23213428 | G66: 0.17962108 | H66: 0.13898737 | I66: 0.10754578 | J66: 0.083216872 | K66: 0.064391629 | L66: -0.05 | M66: Guess
A67: OtherRegion | B67: OtherRegion | C67: CO₂ tax | D67: euro per kWh | E67: 0.01644552 | F67: 0.014699057 | G67: 0.012001552 | H67: 0.0092929308 | I67: 0.0069488528 | J67: 0.0050691956 | K67: 0.0036304529
A71: Backup of variables

Sheet powertrains
A1: variable | B1: unit | C1: 2020 | D1: 2025 | E1: 2030 | F1: 2035 | G1: 2040 | H1: 2045 | I1: 2050 | J1: Annual change | K1: Source | W1: Verification of cited source, which I have some doubts about, using estimates by ChatGPT
A2: Cost of replaced ICE powertrain | B2: SEK/truck | C2: 500 | D2: {=C2*POWER(1+$J2,D$1:I$1-$C$1)} -> 525.50503 | E2: 552.31106 | F2: 580.48448 | G2: 610.09502 | H2: 641.216 | I2: 673.92446 | J2: 0.01 | K2: See comment | L2: All values from Trafikverket's 2021 report "Behov av laddinfrastruktur för snabbladdning av tunga fordon längs större vägar", with adjustments by Nils-Gunnar Vågstedt, Scania (spring 2021)
A3: Cost of replaced ICE powertrain | B3: SEK/kW | C3: 650 | D3: {=C3*POWER(1+$J3,D$1:I$1-$C$1)} -> 683.15653 | E3: 718.00438 | F3: 754.62982 | G3: 793.12353 | H3: 833.5808 | I3: 876.10179 | J3: 0.01 | K3: See comment | W3: Power (kW) | X3: 20 ton | Y3: 40 ton | Z3: diff
A4: Cost of new EV powertrain | B4: SEK/truck | C4: 40000 | D4: {=C4*POWER(1+$J4,D$1:I$1-$C$1)} -> 36156.832 | E4: 32682.912 | F4: 29542.764 | G4: 26704.319 | H4: 24138.589 | I4: 21819.373 | J4: -0.02 | K4: See comment | X4: 190 | Y4: 375 | Z4: =Y4-X4 -> 185
A5: Cost of new EV powertrain | B5: SEK/kW | C5: 190 | D5: {=C5*POWER(1+$J5,D$1:I$1-$C$1)} -> 171.74495 | E5: 155.24383 | F5: 140.32813 | G5: 126.84551 | H5: 114.6583 | I5: 103.64202 | J5: -0.02 | K5: See comment
A6: Vehicle OEM markup | B6: % | C6: 1.48 | D6: {=C6*POWER(1+$J6,D$1:I$1-$C$1)} -> 1.48 | E6: 1.48 | F6: 1.48 | G6: 1.48 | H6: 1.48 | I6: 1.48 | J6: 0 | K6: See comment | W6: ICEV components | X6: 20 ton | Y6: 40 ton | Z6: diff | AA6: kg/kW | AB6: intercept
A7: ICE weight to power ratio | B7: kg/kW | C7: 8.03 | D7: {=C7*POWER(1+$J7,D$1:I$1-$C$1)} -> 8.03 | E7: 8.03 | F7: 8.03 | G7: 8.03 | H7: 8.03 | I7: 8.03 | J7: 0 | K7: See comment | W7: Diesel engine | X7: 1000 | Y7: 1300 | Z7: {=Y7:Y13-X7:X13} -> 300 | AA7: {=_xlfn.ANCHORARRAY(Z7)/Z4} -> 1.6216216 | AB7: {=X7:X13-_xlfn.ANCHORARRAY(AA7)*X4} -> 691.89189
A8: BEV weight to power ratio | B8: kg/kW | C8: 1.07 | D8: {=C8*POWER(1+$J8,D$1:I$1-$C$1)} -> 1.07 | E8: 1.07 | F8: 1.07 | G8: 1.07 | H8: 1.07 | I8: 1.07 | J8: 0 | K8: See comment | W8: Transmission | X8: 300 | Y8: 400 | Z8: 100 | AA8: 0.54054054 | AB8: 197.2973
A9: ICE volume to power ratio | B9: m3/kW | C9: =3/550 -> 0.0054545455 | D9: {=C9*POWER(1+$J9,D$1:I$1-$C$1)} -> 0.0054545455 | E9: 0.0054545455 | F9: 0.0054545455 | G9: 0.0054545455 | H9: 0.0054545455 | I9: 0.0054545455 | J9: 0 | K9: See comment | W9: Fuel tank (full) | X9: 800 | Y9: 1500 | Z9: 700 | AA9: 3.7837838 | AB9: 81.081081
A10: BEV volume to power ratio | B10: m3/kW | C10: =C9*0.5 -> 0.0027272727 | D10: {=C10*POWER(1+$J10,D$1:I$1-$C$1)} -> 0.0027272727 | E10: 0.0027272727 | F10: 0.0027272727 | G10: 0.0027272727 | H10: 0.0027272727 | I10: 0.0027272727 | J10: 0 | W10: Exhaust system | X10: 100 | Y10: 150 | Z10: 50 | AA10: 0.27027027 | AB10: 48.648649
W11: Radiator | X11: 50 | Y11: 75 | Z11: 25 | AA11: 0.13513514 | AB11: 24.324324
A12: Cost diff, excl. battery (SEK) | W12: Starter and alternator | X12: 50 | Y12: 75 | Z12: 25 | AA12: 0.13513514 | AB12: 24.324324
A13: vehicle class | B13: kW | C13: {=C1:I1} -> 2020 | D13: 2025 | E13: 2030 | F13: 2035 | G13: 2040 | H13: 2045 | I13: 2050 | W13: Total | X13: =SUM(X7:X12) -> 2300 | Y13: =SUM(Y7:Y12) -> 3500 | Z13: 1200 | AA13: 6.4864865 | AB13: 1067.5676
A14: HGV60 | B14: 750 | C14: {=(C4:I4-C2:I2+B14:B17*(C5:I5-C3:I3))*C6:I6} -> -452140 | D14: -514932.49 | E14: -577110.92 | F14: -639010.7 | G14: -700949.14 | H14: -763227.86 | I14: -826135.09
A15: HGV40 | B15: 550 | C15: -315980 | D15: -363554.66 | E15: -410533.8 | F15: -457177.4 | G15: -503730.85 | H15: -550426.8 | I15: -597486.99
A16: MGV24 | B16: 300 | C16: -145780 | D16: -174332.38 | E16: -202312.39 | F16: -229885.78 | G16: -257207.99 | H16: -284425.48 | I16: -311676.88 | W16: BEV components | X16: 20 ton | Y16: 40 ton | Z16: diff | AA16: kg/kW | AB16: intercept
A17: MGV16 | B17: 160 | C17: -50468 | D17: -68367.899 | E17: -85708.408 | F17: -102602.47 | G17: -119155.18 | H17: -135464.74 | I17: -151623.21 | W17: Electric motor | X17: 300 | Y17: 400 | Z17: {=Y17:Y23-X17:X23} -> 100 | AA17: {=_xlfn.ANCHORARRAY(Z17)/Z4} -> 0.54054054 | AB17: {=X17:X23-_xlfn.ANCHORARRAY(AA17)*X4} -> 197.2973
W18: Power electronics | X18: 100 | Y18: 150 | Z18: 50 | AA18: 0.27027027 | AB18: 48.648649
A19: Cost diff, excl. battery (EUR) | L19: SEK/Euro | W19: EVSE / charging port | X19: 10 | Y19: 10 | Z19: 0 | AA19: 0 | AB19: 10
A20: {=A13:I13} -> vehicle class | B20: kW | C20: 2020 | D20: 2025 | E20: 2030 | F20: 2035 | G20: 2040 | H20: 2045 | I20: 2050 | L20: 0.096 | W20: Battery cooling system | X20: 100 | Y20: 150 | Z20: 50 | AA20: 0.27027027 | AB20: 48.648649
A21: {=A14:B17} -> HGV60 | B21: 750 | C21: {=L20*_xlfn.ANCHORARRAY(C14)} -> -43405.44 | D21: -49433.519 | E21: -55402.648 | F21: -61345.028 | G21: -67291.118 | H21: -73269.875 | I21: -79308.968 | W21: Electric power steering system | X21: 50 | Y21: 75 | Z21: 25 | AA21: 0.13513514 | AB21: 24.324324
A22: HGV40 | B22: 550 | C22: -30334.08 | D22: -34901.248 | E22: -39411.244 | F22: -43889.031 | G22: -48358.162 | H22: -52840.973 | I22: -57358.751 | W22: Regenerative braking system | X22: 75 | Y22: 100 | Z22: 25 | AA22: 0.13513514 | AB22: 49.324324
A23: MGV24 | B23: 300 | C23: -13994.88 | D23: -16735.908 | E23: -19421.99 | F23: -22069.035 | G23: -24691.967 | H23: -27304.846 | I23: -29920.98 | W23: Total | X23: =SUM(X17:X22) -> 635 | Y23: =SUM(Y17:Y22) -> 885 | Z23: 250 | AA23: 1.3513514 | AB23: 378.24324
A24: MGV16 | B24: 160 | C24: -4844.928 | D24: -6563.3183 | E24: -8228.0072 | F24: -9849.8368 | G24: -11438.897 | H24: -13004.615 | I24: -14555.828
A26: Weight diff, excl. battery (kg) | W26: Driveline components
A27: {=A13:I13} -> vehicle class | B27: kW | C27: 2020 | D27: 2025 | E27: 2030 | F27: 2035 | G27: 2040 | H27: 2045 | I27: 2050 | W27: kW | X27: Diesel | Y27: BEV | Z27: Diff BEV - Diesel
A28: {=_xlfn.ANCHORARRAY(A21)} -> HGV60 | B28: 750 | C28: {=B28:B31*(C8:I8-C7:I7)} -> -5220 | D28: -5220 | E28: -5220 | F28: -5220 | G28: -5220 | H28: -5220 | I28: -5220 | W28: {=B14:B17} -> 750 | X28: {=_xlfn.ANCHORARRAY(W28)*AA13+AB13} -> 5932.4324 | Y28: {=_xlfn.ANCHORARRAY(W28)*AA23+AB23} -> 1391.7568 | Z28: {=_xlfn.ANCHORARRAY(Y28)-_xlfn.ANCHORARRAY(X28)} -> -4540.6757 | AB28: These numbers are close enough to the cited source that I decide to use that one, even though these are probably more accurate.
A29: HGV40 | B29: 550 | C29: -3828 | D29: -3828 | E29: -3828 | F29: -3828 | G29: -3828 | H29: -3828 | I29: -3828 | W29: 550 | X29: 4635.1351 | Y29: 1121.4865 | Z29: -3513.6486
A30: MGV24 | B30: 300 | C30: -2088 | D30: -2088 | E30: -2088 | F30: -2088 | G30: -2088 | H30: -2088 | I30: -2088 | W30: 300 | X30: 3013.5135 | Y30: 783.64865 | Z30: -2229.8649
A31: MGV16 | B31: 160 | C31: -1113.6 | D31: -1113.6 | E31: -1113.6 | F31: -1113.6 | G31: -1113.6 | H31: -1113.6 | I31: -1113.6 | W31: 160 | X31: 2105.4054 | Y31: 594.45946 | Z31: -1510.9459
A33: ICEV powertrain cost change (eur) | W33: Battery pack kg/kWh | X33: {=1/batteries!E21:K21} -> 7.6923077 | Y33: 5.227932 | Z33: 4.0772269 | AA33: 3.3561409 | AB33: 2.8302914 | AC33: 2.4144357 | AD33: 2.071261
A34: {=A13:I13} -> vehicle class | B34: kW | C34: 2020 | D34: 2025 | E34: 2030 | F34: 2035 | G34: 2040 | H34: 2045 | I34: 2050 | W34: 1000 | X34: {=W34:W37*_xlfn.ANCHORARRAY(X33)} -> 7692.3077 | Y34: 5227.932 | Z34: 4077.2269 | AA34: 3356.1409 | AB34: 2830.2914 | AC34: 2414.4357 | AD34: 2071.261
A35: {=A28:A31} -> HGV60 | B35: {=B28:B31} -> 750 | C35: {=(B35*(C$3:I$3-C$3)+C$2:I$2-C$2)*C$6:I$6*L$20} -> 0 | D35: 3536.7839 | E35: 7253.9793 | F35: 11160.789 | G35: 15266.885 | H35: 19582.434 | I35: 24118.118 | W35: 750 | X35: 5769.2308 | Y35: 3920.949 | Z35: 3057.9202 | AA35: 2517.1057 | AB35: 2122.7185 | AC35: 1810.8268 | AD35: 1553.4458
A36: HGV40 | B36: 550 | C36: {=(B36*(C$3:I$3-C$3)+C$2:I$2-C$2)*C$6:I$6*L$20} -> 0 | D36: 2594.6078 | E36: 5321.5667 | F36: 8187.628 | G36: 11199.887 | H36: 14365.802 | I36: 17693.21 | W36: 350 | X36: 2692.3077 | Y36: 1829.7762 | Z36: 1427.0294 | AA36: 1174.6493 | AB36: 990.60199 | AC36: 845.05251 | AD36: 724.94135
A37: MGV24 | B37: 300 | C37: {=(B37*(C$3:I$3-C$3)+C$2:I$2-C$2)*C$6:I$6*L$20} -> 0 | D37: 1416.8878 | E37: 2906.0511 | F37: 4471.1767 | G37: 6116.1395 | H37: 7845.0119 | I37: 9662.0741 | W37: 200 | X37: 1538.4615 | Y37: 1045.5864 | Z37: 815.44539 | AA37: 671.22818 | AB37: 566.05828 | AC37: 482.88715 | AD37: 414.2522
A38: MGV16 | B38: 160 | C38: {=(B38*(C$3:I$3-C$3)+C$2:I$2-C$2)*C$6:I$6*L$20} -> 0 | D38: 757.36458 | E38: 1553.3624 | F38: 2389.964 | G38: 3269.2408 | H38: 4193.3695 | I38: 5164.6381
W39: Total from ChatGPT
A40: BEV powertrain cost (EUR) | B40: {=B34:I34} -> kW | C40: 2020 | D40: 2025 | E40: 2030 | F40: 2035 | G40: 2040 | H40: 2045 | I40: 2050 | W40: kW
A41: {=A14:B17} -> HGV60 | B41: 750 | C41: {=(B41:B44*C5:I5+C4:I4)*L20} -> 17520 | D41: 15836.692 | E41: 14315.116 | F41: 12939.731 | G41: 11696.492 | H41: 10572.702 | I41: 9556.8853 | W41: {=_xlfn.ANCHORARRAY(W28)} -> 750 | X41: {=_xlfn.ANCHORARRAY(X34)+_xlfn.ANCHORARRAY(Z28)} -> 3151.632 | Y41: 687.25635 | Z41: -463.44874 | AA41: -1184.5348 | AB41: -1710.3843 | AC41: -2126.2399 | AD41: -2469.4147
A42: HGV40 | B42: 550 | C42: 13872 | D42: 12539.189 | E42: 11334.434 | F42: 10245.431 | G42: 9261.0578 | H42: 8371.2627 | I42: 7566.9585 | W42: 550 | X42: 2255.5821 | Y42: 407.30037 | Z42: -455.72845 | AA42: -996.54297 | AB42: -1390.9301 | AC42: -1702.8218 | AD42: -1960.2029
A43: MGV24 | B43: 300 | C43: 9312 | D43: 8417.3105 | E43: 7608.582 | F43: 6877.5555 | G43: 6216.7654 | H43: 5619.4636 | I43: 5079.55 | W43: 300 | X43: 462.44283 | Y43: -400.08866 | Z43: -802.83544 | AA43: -1055.2155 | AB43: -1239.2629 | AC43: -1384.8124 | AD43: -1504.9235
A44: MGV16 | B44: 160 | C44: 6758.4 | D44: 6109.0583 | E44: 5522.1049 | F44: 4991.5454 | G44: 4511.9617 | H44: 4078.456 | I44: 3686.6012 | W44: 160 | X44: 27.515593 | Y44: -465.35954 | Z44: -695.50056 | AA44: -839.71777 | AB44: -944.88767 | AC44: -1028.0588 | AD44: -1096.6937
A46: Driveline volume diff (m3) | B46: {=B13:I13} -> kW | C46: 2020 | D46: 2025 | E46: 2030 | F46: 2035 | G46: 2040 | H46: 2045 | I46: 2050 | W46: Total from TRV
A47: {=A14:B17} -> HGV60 | B47: 750 | C47: {=B47:B50*(C9:I9-C10:I10)} -> 2.0454545 | D47: 2.0454545 | E47: 2.0454545 | F47: 2.0454545 | G47: 2.0454545 | H47: 2.0454545 | I47: 2.0454545 | W47: kW
A48: HGV40 | B48: 550 | C48: 1.5 | D48: 1.5 | E48: 1.5 | F48: 1.5 | G48: 1.5 | H48: 1.5 | I48: 1.5 | W48: {=_xlfn.ANCHORARRAY(W41)} -> 750 | X48: {=_xlfn.ANCHORARRAY(C28)+_xlfn.ANCHORARRAY(X34)} -> 2472.3077 | Y48: 7.9320266 | Z48: -1142.7731 | AA48: -1863.8591 | AB48: -2389.7086 | AC48: -2805.5643 | AD48: -3148.739
A49: MGV24 | B49: 300 | C49: 0.81818182 | D49: 0.81818182 | E49: 0.81818182 | F49: 0.81818182 | G49: 0.81818182 | H49: 0.81818182 | I49: 0.81818182 | W49: 550 | X49: 1941.2308 | Y49: 92.94902 | Z49: -770.0798 | AA49: -1310.8943 | AB49: -1705.2815 | AC49: -2017.1732 | AD49: -2274.5542
A50: MGV16 | B50: 160 | C50: 0.43636364 | D50: 0.43636364 | E50: 0.43636364 | F50: 0.43636364 | G50: 0.43636364 | H50: 0.43636364 | I50: 0.43636364 | W50: 300 | X50: 604.30769 | Y50: -258.22379 | Z50: -660.97057 | AA50: -913.35068 | AB50: -1097.398 | AC50: -1242.9475 | AD50: -1363.0586
W51: 160 | X51: 424.86154 | Y51: -68.013595 | Z51: -298.15461 | AA51: -442.37182 | AB51: -547.54172 | AC51: -630.71285 | AD51: -699.3478
W53: Diff TRV - ChatGPT
W54: {=_xlfn.ANCHORARRAY(W48)} -> 750 | X54: {=_xlfn.ANCHORARRAY(X48)-_xlfn.ANCHORARRAY(X41)} -> -679.32432 | Y54: -679.32432 | Z54: -679.32432 | AA54: -679.32432 | AB54: -679.32432 | AC54: -679.32432 | AD54: -679.32432
W55: 550 | X55: -314.35135 | Y55: -314.35135 | Z55: -314.35135 | AA55: -314.35135 | AB55: -314.35135 | AC55: -314.35135 | AD55: -314.35135
W56: 300 | X56: 141.86486 | Y56: 141.86486 | Z56: 141.86486 | AA56: 141.86486 | AB56: 141.86486 | AC56: 141.86486 | AD56: 141.86486
W57: 160 | X57: 397.34595 | Y57: 397.34595 | Z57: 397.34595 | AA57: 397.34595 | AB57: 397.34595 | AC57: 397.34595 | AD57: 397.34595

Sheet vehicles
E2: Year 2020
B3: group | C3: variable | D3: unit | E3: HGV60 | F3: HGV40 | G3: MGV24 | H3: MGV16 | I3: Annual change | K3: Source/reasoning
B4: Common | C4: Annual distance | D4: km | E4: 90000 | F4: 115000 | G4: 80000 | H4: 42000 | I4: 0 | K4: Values for Swedish-registered trucks, from Trafikverket, "Behov av laddinfrastruktur för snabbladdning av tunga fordon längs större vägar", fig. 13
B5: Common | C5: Utilization | D5: calendar days per year | E5: =(52-6)*5 -> 230 | F5: =(52-6)*5 -> 230 | G5: =(52-6)*5 -> 230 | H5: =(52-6)*5 -> 230 | I5: 0 | K5: Informed guess
B6: Common | C6: Max time in transit | D6: h per day | E6: 9 | F6: 11 | G6: 9 | H6: 9 | I6: 0 | K6: Excluding breaks, loading and unloading. Fresh produce sometimes operates with two drivers.
B7: Common | C7: Max time in use | D7: h per day | E7: 12 | F7: 15 | G7: 12 | H7: 12 | I7: 0 | K7: Including breaks, loading and unloading.
B8: Common | C8: Power, peak | D8: kW | E8: 750 | F8: 550 | G8: 300 | H8: 160 | I8: 0 | K8: Nils-Gunnar Vågstedt, Scania, private communication
B9: Common | C9: Tyres | D9: euro per km | E9: 0.11328 | F9: 0.09024 | G9: 0.06144 | H9: 0.03072 | I9: 0 | K9: ASEK 7
B10: Common | C10: Cargo capacity value | D10: euro per ton-km | E10: 0.025 | F10: 0.025 | G10: 0.035 | H10: 0.05 | I10: 0 | K10: Roger Blom, CEO at Ernsts Express, private communication
B11: Common | C11: Cargo capacity value | D11: euro per m3-km | E11: {=0.28*E10:H10} -> 0.007 | F11: 0.007 | G11: 0.0098 | H11: 0.014 | I11: 0 | K11: 280 kg/m3, lost the source
B12: Common | C12: Total weight limit | D12: kg | E12: 60000 | F12: 40000 | G12: 24000 | H12: 16000 | I12: 0 | K12: Definition
B13: Common | C13: Depot stop | D13: h | E13: {=24-E7:H7} -> 12 | F13: 9 | G13: 12 | H13: 12 | I13: 0 | K13: Complement to utilization
B14: Common | C14: Destination stop | D14: h | E14: 1 | F14: 1 | G14: 0.5 | H14: 0.2 | I14: 0 | K14: Guess
B15: Common | C15: Rest stop | D15: h | E15: 0.75 | F15: 0.75 | G15: 0.75 | H15: 0.75 | I15: 0 | K15: Guess
B16: Common | C16: Drive session | D16: h | E16: 4.5 | F16: 4.5 | G16: 4.5 | H16: 4.5 | I16: 0 | K16: EU regulation
B17: Common | C17: Driver cost | D17: euro per h | E17: 33.6 | F17: 33.6 | G17: 30 | H17: 30 | I17: 0 | K17: Roger Blom, CEO at Ernsts Express, private communication
B18: ICEV | C18: Chassis weight | D18: kg | E18: 23000 | F18: 20000 | G18: 10000 | H18: 5000 | I18: 0 | K18: ASEK 7 | AD18: Vi har ingen statistik för hur många timmar bilar nyttjas per dygn. Från dessa figurer verkar det som att en lastbil i enkelskift går ca 100k km per år/230 dagar per år = 435 km per arbetsdag. En arbetsdag får inte vara längre än 9 timmar, varav ca 6 h borde kunna vara körtid. Det ger en medelhastighet på 72 km/h, vilket är ganska rimligt. Då verkar det som att snittanvändningen per dag inte är mycket mer än enkelskift. | AN18: {=E52:K52-E52} -> 0 | AO18: 5 | AP18: 10 | AQ18: 15 | AR18: 20 | AS18: 25 | AT18: 30 | AX18: {=E83:K83} -> 2020 | AY18: 2025 | AZ18: 2030 | BA18: 2035 | BB18: 2040 | BC18: 2045 | BD18: 2050
B19: ICEV | C19: Chassis cost, 2020 | D19: euro | E19: 259200 | F19: 235200 | G19: 148800 | H19: 91200 | I19: 0 | K19: ASEK 7, Kapitel 14 Operativa trafikeringskostnader för godstransporter | AN19: {=POWER(1+I4:I27,AN18:AT18)} -> 1 | AO19: 1 | AP19: 1 | AQ19: 1 | AR19: 1 | AS19: 1 | AT19: 1 | AV19: HGV60 | AW19: {=AV19:AV22&" ICEV"} -> HGV60 ICEV | AX19: {=_xlfn.ANCHORARRAY(E78)} -> 259200 | AY19: 262736.78 | AZ19: 266453.98 | BA19: 270360.79 | BB19: 274466.89 | BC19: 278782.43 | BD19: 283318.12
B20: ICEV | C20: Lifetime | D20: years | E20: 10 | F20: 10 | G20: 7 | H20: 7 | I20: 0 | K20: ASEK 7, Kapitel 14 Operativa trafikeringskostnader för godstransporter | W20: EUR/SEK | X20: 0.096 | AN20: 1 | AO20: 1 | AP20: 1 | AQ20: 1 | AR20: 1 | AS20: 1 | AT20: 1 | AV20: HGV40 | AW20: HGV40 ICEV | AX20: {=_xlfn.ANCHORARRAY(E109)} -> 235200 | AY20: 237794.61 | AZ20: 240521.57 | BA20: 243387.63 | BB20: 246399.89 | BC20: 249565.8 | BD20: 252893.21
B21: ICEV | C21: Maintenance cost | D21: euro per km | E21: 0.09984 | F21: 0.11424 | G21: 0.12096 | H21: 0.10176 | I21: 0 | K21: ASEK 7, Kapitel 14 Operativa trafikeringskostnader för godstransporter | W21: MJ/liter | X21: 36.4 | AN21: 1 | AO21: 1 | AP21: 1 | AQ21: 1 | AR21: 1 | AS21: 1 | AT21: 1 | AV21: MGV24 | AW21: MGV24 ICEV | AX21: {=_xlfn.ANCHORARRAY(E140)} -> 148800 | AY21: 150216.89 | AZ21: 151706.05 | BA21: 153271.18 | BB21: 154916.14 | BC21: 156645.01 | BD21: 158462.07
B22: ICEV | C22: Residual value at end of life | D22: ratio | E22: 0.09 | F22: 0.09 | G22: 0.09 | H22: 0.09 | I22: 0 | K22: ASEK 7, Kapitel 14 Operativa trafikeringskostnader för godstransporter | W22: kWh/MJ | X22: 0.2778 | AN22: 1 | AO22: 1 | AP22: 1 | AQ22: 1 | AR22: 1 | AS22: 1 | AT22: 1 | AV22: MGV16 | AW22: MGV16 ICEV | AX22: {=_xlfn.ANCHORARRAY(E171)} -> 91200 | AY22: 91957.365 | AZ22: 92753.362 | BA22: 93589.964 | BB22: 94469.241 | BC22: 95393.37 | BD22: 96364.638
B23: ICEV | C23: Fuel consumption | D23: liter per km | E23: 0.35 | F23: 0.27 | G23: 0.22 | H23: 0.16 | I23: -0.005 | K23: ASEK 7, Kapitel 14 Operativa trafikeringskostnader för godstransporter (50% body, enligt NG) | W23: ICEV efficiency | X23: 0.35 | AN23: 1 | AO23: 1 | AP23: 1 | AQ23: 1 | AR23: 1 | AS23: 1 | AT23: 1 | AV23: {=AV19:AV22} -> HGV60 | AW23: {=_xlfn.ANCHORARRAY(AV23)&" BEV (excl. bat.)"} -> HGV60 BEV (excl. bat.) | AX23: {=_xlfn.ANCHORARRAY(E80)} -> 215794.56 | AY23: 213303.26 | AZ23: 211051.33 | BA23: 209015.76 | BB23: 207175.77 | BC23: 205512.56 | BD23: 204009.15
B24: BEV | C24: Maintenance cost | D24: euro per km | E24: {=0.4*E21:H21} -> 0.039936 | F24: 0.045696 | G24: 0.048384 | H24: 0.040704 | I24: 0 | K24: 40% av ICEV | W24: BEV efficiency | X24: 0.85 | AN24: 1 | AO24: 1 | AP24: 1 | AQ24: 1 | AR24: 1 | AS24: 1 | AT24: 1 | AV24: HGV40 | AW24: HGV40 BEV (excl. bat.) | AX24: {=_xlfn.ANCHORARRAY(E111)} -> 204865.92 | AY24: 202893.36 | AZ24: 201110.32 | BA24: 199498.6 | BB24: 198041.73 | BC24: 196724.83 | BD24: 195534.46
B25: BEV | C25: Residual value at end of life | D25: ratio | E25: {=E22:H22} -> 0.09 | F25: 0.09 | G25: 0.09 | H25: 0.09 | I25: 0 | K25: Same as ICEV | W25: kWh/liter | X25: =(X23/X24)*X22*X21 -> 4.1637318 | AN25: 1 | AO25: 1 | AP25: 1 | AQ25: 1 | AR25: 1 | AS25: 1 | AT25: 1 | AV25: MGV24 | AW25: MGV24 BEV (excl. bat.) | AX25: {=_xlfn.ANCHORARRAY(E142)} -> 134805.12 | AY25: 133480.98 | AZ25: 132284.06 | BA25: 131202.14 | BB25: 130224.17 | BC25: 129340.17 | BD25: 128541.09
B26: BEV | C26: Energy consumption | D26: kWh per km | E26: {=E23:F23*X25} -> 1.4573061 | F26: 1.1242076 | G26: {=G23:H23*X25*X26} -> 0.64121469 | H26: 0.46633796 | I26: -0.006 | K26: ICEV consumption, diesel energy density and propulsion efficiency difference. With regen, propulsion is a smaller share of total energy. | W26: City multiplier | X26: 0.7 | Y26: BEV regen, ICEV inefficiency | AN26: 1 | AO26: 1 | AP26: 1 | AQ26: 1 | AR26: 1 | AS26: 1 | AT26: 1 | AV26: MGV16 | AW26: MGV16 BEV (excl. bat.) | AX26: {=_xlfn.ANCHORARRAY(E173)} -> 86355.072 | AY26: 85394.046 | AZ26: 84525.355 | BA26: 83740.127 | BB26: 83030.343 | BC26: 82388.755 | BD26: 81808.81
B27: BEV | C27: Min range buffer | D27: km | E27: 50 | F27: 50 | G27: 30 | H27: 20 | I27: 0 | K27: Guess | AN27: 1 | AO27: 1 | AP27: 1 | AQ27: 1 | AR27: 1 | AS27: 1 | AT27: 1 | AV27: {=_xlfn.ANCHORARRAY(AV23)} -> HGV60 | AW27: {=_xlfn.ANCHORARRAY(AV27)&"BEV ("&_xlfn.ANCHORARRAY(AW34)&" km)"} -> HGV60BEV (590 km) | AX27: {=AX34:BD37*batteries!E23:K23+AX23:BD26} -> 572946.66 | AY27: 421769.95 | AZ27: 352357.55 | BA27: 311601.11 | BB27: 284819.54 | BC27: 266165.4 | BD27: 252727.02
B28: BEV | C28: Lifetime 2020 | D28: years | E28: {=E20:H20} -> 10 | F28: 10 | G28: 7 | H28: 7 | I28: ="" | K28: Nils-Gunnar Vågstedt, Scania, and Anders Berger, Volvo Trucks, private communication | AN28: 1 | AO28: 1 | AP28: 1 | AQ28: 1 | AR28: 1 | AS28: 1 | AT28: 1 | AV28: HGV40 | AW28: HGV40BEV (750 km) | AX28: 555099.82 | AY28: 407321.95 | AZ28: 339679.38 | BA28: 300096.82 | BB28: 274181.5 | BC28: 256202.79 | BD28: 243308.64
B29: BEV | C29: Lifetime 2035 | D29: years | E29: 15 | F29: 15 | G29: 12 | H29: 12 | I29: ="" | K29: Nils-Gunnar Vågstedt, Scania, and Anders Berger, Volvo Trucks, private communication | AN29: 1 | AO29: 1 | AP29: 1 | AQ29: 1 | AR29: 1 | AS29: 1 | AT29: 1 | AV29: MGV24 | AW29: MGV24BEV (520 km) | AX29: 273307.49 | AY29: 214323.65 | AZ29: 187082.13 | BA29: 170984.39 | BB29: 160334.16 | BC29: 152861.13 | BD29: 147433.72
B30: BEV | C30: Energy per day of operation | D30: kWh | E30: {=E26:H26*E4:H4/E5:H5} -> 570.25022 | F30: 562.10379 | G30: 223.0312 | H30: 85.157366 | I30: ="" | W30: MGV16 | X30: Lokaldistribution | Y30: Tung 2-axlad lastbil utan släp, totalvikt 3,5- 16 ton. Bil med 2 axlar. | AN30: 1 | AO30: 1 | AP30: 1 | AQ30: 1 | AR30: 1 | AS30: 1 | AT30: 1 | AV30: MGV16 | AW30: MGV16BEV (270 km) | AX30: 138656.67 | AY30: 115922.05 | AZ30: 105218.33 | BA30: 98762.795 | BB30: 94400.55 | BC30: 91270.798 | BD30: 88943.088
W31: MGV24 | X31: Anläggning | Y31: Tung lastbil utan släp, totalvikt 16-24 ton. Bil med 3 axlar. | AN31: 1 | AO31: 1 | AP31: 1 | AQ31: 1 | AR31: 1 | AS31: 1 | AT31: 1
W32: HGV40 | X32: Fjärrlastbil | Y32: Dragbil med släp, totalvikt 25-40 ton. Bil med 3 axlar och släp med 4 axlar. | AN32: 1 | AO32: 1 | AP32: 1 | AQ32: 1 | AR32: 1 | AS32: 1 | AT32: 1
B33: BEV | C33: Power @ 85 km/h | D33: kW | E33: {=E26:H26*85} -> 123.87102 | F33: 95.557644 | G33: 54.503249 | H33: 39.638726 | W33: HGV60 | X33: Fjärrlastbil | Y33: Dragbil med släp, totalvikt 25-60 ton. Bil med 3 axlar och släp med 4 axlar. | AN33: 1 | AO33: 1 | AP33: 1 | AQ33: 1 | AR33: 1 | AS33: 1 | AT33: 1 | AW33: Usable range | AX33: Usable battery kWh
B34: Common | C34: Average speed | D34: km/h | E34: {=E4:H4/(E5:H5*E6:H6)} -> 43.478261 | F34: 45.454545 | G34: 38.647343 | H34: 20.289855 | AN34: 1 | AO34: 1 | AP34: 1 | AQ34: 1 | AR34: 1 | AS34: 1 | AT34: 1 | AV34: {=_xlfn.ANCHORARRAY(AV23)} -> HGV60 | AW34: {=ROUND(TRANSPOSE(E4:H4/E5:H5)*1.5,-1)} -> 590 | AX34: {=AW34*E75:K75} -> 859.81061 | AY34: 834.32397 | AZ34: 809.59281 | BA34: 785.59474 | BB34: 762.30802 | BC34: 739.71157 | BD34: 717.78492
B35: Common | C35: Mean daily distance | D35: km | E35: {=E4:H4/E5:H5} -> 391.30435 | F35: 500 | G35: 347.82609 | H35: 182.6087 | AN35: 1 | AO35: 1 | AP35: 1 | AQ35: 1 | AR35: 1 | AS35: 1 | AT35: 1 | AV35: HGV40 | AW35: 750 | AX35: {=AW35*E106:K106} -> 843.15568 | AY35: 818.16273 | AZ35: 793.91063 | BA35: 770.37741 | BB35: 747.54176 | BC35: 725.38301 | BD35: 703.8811
AN36: 1 | AO36: 1 | AP36: 1 | AQ36: 1 | AR36: 1 | AS36: 1 | AT36: 1 | AV36: MGV24 | AW36: 520 | AX36: {=AW36*E137:K137} -> 333.43164 | AY36: 323.54801 | AZ36: 313.95735 | BA36: 304.65098 | BB36: 295.62047 | BC36: 286.85764 | BD36: 278.35456
E37: 2020 | F37: 2025 | G37: 2030 | H37: 2035 | I37: 2040 | J37: 2045 | K37: 2050 | W37: Estimation of future annual reduction in energy consumption, HGV40 example | AN37: 1 | AO37: 1 | AP37: 1 | AQ37: 1 | AR37: 1 | AS37: 1 | AT37: 1 | AV37: MGV16 | AW37: 270 | AX37: {=AW37*E168:K168} -> 125.91125 | AY37: 122.17897 | AZ37: 118.55732 | BA37: 115.04303 | BB37: 111.6329 | BC37: 108.32386 | BD37: 105.11291
B38: {=TRANSPOSE(E3:H3)} -> HGV60 | C38: ICEV powertrain cost diff vs 2020 | D38: euro | E38: {=powertrains!C35:I38} -> 0 | F38: 3536.7839 | G38: 7253.9793 | H38: 11160.789 | I38: 15266.885 | J38: 19582.434 | K38: 24118.118 | X38: ICET | Y38: BET | AN38: 1 | AO38: 0.97524875 | AP38: 0.95111013 | AQ38: 0.92756897 | AR38: 0.90461048 | AS38: 0.88222024 | AT38: 0.86038419
B39: HGV40 | C39: ICEV powertrain cost diff vs 2020 | D39: euro | E39: 0 | F39: 2594.6078 | G39: 5321.5667 | H39: 8187.628 | I39: 11199.887 | J39: 14365.802 | K39: 17693.21 | V39: Current | W39: Powertrain efficiency | X39: 0.35 | Y39: 0.85 | AN39: 1 | AO39: 1 | AP39: 1 | AQ39: 1 | AR39: 1 | AS39: 1 | AT39: 1
B40: MGV24 | C40: ICEV powertrain cost diff vs 2020 | D40: euro | E40: 0 | F40: 1416.8878 | G40: 2906.0511 | H40: 4471.1767 | I40: 6116.1395 | J40: 7845.0119 | K40: 9662.0741 | W40: kWh/km | X40: =Y40*Y39/X39 -> 2.6714286 | Y40: 1.1 | AN40: 1 | AO40: 1 | AP40: 1 | AQ40: 1 | AR40: 1 | AS40: 1 | AT40: 1
B41: MGV16 | C41: ICEV powertrain cost diff vs 2020 | D41: euro | E41: 0 | F41: 757.36458 | G41: 1553.3624 | H41: 2389.964 | I41: 3269.2408 | J41: 4193.3695 | K41: 5164.6381 | W41: kWh->liter | X41: {=X40:Y40/10} -> 0.26714286 | Y41: 0.11 | AA41: =Y41/X41 -> 0.41176471 | AN41: 1 | AO41: 0.97035785 | AP41: 0.94159435 | AQ41: 0.91368347 | AR41: 0.88659992 | AS41: 0.86031919 | AT41: 0.83481748
B42: {=_xlfn.ANCHORARRAY(B38)} -> HGV60 | C42: BEV vs ICEV cost diff, excl battery | D42: euro | E42: {=_xlfn.ANCHORARRAY(powertrains!C21)} -> -43405.44 | F42: -49433.519 | G42: -55402.648 | H42: -61345.028 | I42: -67291.118 | J42: -73269.875 | K42: -79308.968 | W42: kWh powertrain | X42: {=(1-X39:Y39)*X40:Y40} -> 1.7364286 | Y42: 0.165 | AA42: =X42/X40 -> 0.65 | AB42: =Y42/Y40 -> 0.15 | AN42: 1 | AO42: 1 | AP42: 1 | AQ42: 1 | AR42: 1 | AS42: 1 | AT42: 1
B43: HGV40 | C43: BEV vs ICEV cost diff, excl battery | D43: euro | E43: -30334.08 | F43: -34901.248 | G43: -39411.244 | H43: -43889.031 | I43: -48358.162 | J43: -52840.973 | K43: -57358.751 | W43: kWh useful work | X43: {=X40:Y40-_xlfn.ANCHORARRAY(X42)} -> 0.935 | Y43: 0.935
B44: MGV24 | C44: BEV vs ICEV cost diff, excl battery | D44: euro | E44: -13994.88 | F44: -16735.908 | G44: -19421.99 | H44: -22069.035 | I44: -24691.967 | J44: -27304.846 | K44: -29920.98
B45: MGV16 | C45: BEV vs ICEV cost diff, excl battery | D45: euro | E45: -4844.928 | F45: -6563.3183 | G45: -8228.0072 | H45: -9849.8368 | I45: -11438.897 | J45: -13004.615 | K45: -14555.828 | V45: Historic | W45: %/y, total | X45: -0.01
B46: {=_xlfn.ANCHORARRAY(B38)} -> HGV60 | C46: BEV vs ICEV weight diff, excl battery | D46: kg | E46: {=_xlfn.ANCHORARRAY(powertrains!C28)} -> -5220 | F46: -5220 | G46: -5220 | H46: -5220 | I46: -5220 | J46: -5220 | K46: -5220 | W46: kWh/y, total | X46: =X45*X40 -> -0.026714286
B47: HGV40 | C47: BEV vs ICEV weight diff, excl battery | D47: kg | E47: -3828 | F47: -3828 | G47: -3828 | H47: -3828 | I47: -3828 | J47: -3828 | K47: -3828 | W47: kWh/y, powertrain | X47: =0.5*X46 -> -0.013357143
B48: MGV24 | C48: BEV vs ICEV weight diff, excl battery | D48: kg | E48: -2088 | F48: -2088 | G48: -2088 | H48: -2088 | I48: -2088 | J48: -2088 | K48: -2088 | W48: kWh/y, useful work | X48: =X47 -> -0.013357143
B49: MGV16 | C49: BEV vs ICEV weight diff, excl battery | D49: kg | E49: -1113.6 | F49: -1113.6 | G49: -1113.6 | H49: -1113.6 | I49: -1113.6 | J49: -1113.6 | K49: -1113.6 | W49: %/y, powertrain | X49: {=X47:X48/X42:X43} -> -0.0076923077
W50: %/y, useful work | X50: -0.014285714
A52: group | B52: subgroup | C52: variable | D52: unit | E52: 2020 | F52: 2025 | G52: 2030 | H52: 2035 | I52: 2040 | J52: 2045 | K52: 2050 | V52: Future | W52: {=W49:W50} -> %/y, powertrain | X52: 0 | Y52: =X49 -> -0.0076923077
A53: HGV60 | B53: {=B4:D27} -> Common | C53: Annual distance | D53: km | E53: {=E$4:E$27*_xlfn.ANCHORARRAY(AN19)} -> 90000 | F53: 90000 | G53: 90000 | H53: 90000 | I53: 90000 | J53: 90000 | K53: 90000 | W53: %/y, useful work | X53: =X50 -> -0.014285714 | Y53: =X53 -> -0.014285714
A54: =A53 -> HGV60 | B54: Common | C54: Utilization | D54: calendar days per year | E54: 230 | F54: 230 | G54: 230 | H54: 230 | I54: 230 | J54: 230 | K54: 230 | W54: {=W47:W48} -> kWh/y, powertrain | X54: {=X52:Y53*X42:Y43} -> 0 | Y54: -0.0012692308
A55: =A54 -> HGV60 | B55: Common | C55: Max time in transit | D55: h per day | E55: 9 | F55: 9 | G55: 9 | H55: 9 | I55: 9 | J55: 9 | K55: 9 | W55: kWh/y, useful work | X55: -0.013357143 | Y55: -0.013357143
A56: =A55 -> HGV60 | B56: Common | C56: Max time in use | D56: h per day | E56: 12 | F56: 12 | G56: 12 | H56: 12 | I56: 12 | J56: 12 | K56: 12 | W56: =W46 -> kWh/y, total | X56: =SUM(X54:X55) -> -0.013357143 | Y56: =SUM(Y54:Y55) -> -0.014626374
A57: =A55 -> HGV60 | B57: Common | C57: Power, peak | D57: kW | E57: 750 | F57: 750 | G57: 750 | H57: 750 | I57: 750 | J57: 750 | K57: 750 | W57: =W45 -> %/y, total | X57: {=X56:Y56/X40:Y40} -> -0.005 | Y57: -0.013296703
A58: =A57 -> HGV60 | B58: Common | C58: Tyres | D58: euro per km | E58: 0.11328 | F58: 0.11328 | G58: 0.11328 | H58: 0.11328 | I58: 0.11328 | J58: 0.11328 | K58: 0.11328
A59: =A58 -> HGV60 | B59: Common | C59: Cargo capacity value | D59: euro per ton-km | E59: 0.025 | F59: 0.025 | G59: 0.025 | H59: 0.025 | I59: 0.025 | J59: 0.025 | K59: 0.025
A60: =A59 -> HGV60 | B60: Common | C60: Cargo capacity value | D60: euro per m3-km | E60: 0.007 | F60: 0.007 | G60: 0.007 | H60: 0.007 | I60: 0.007 | J60: 0.007 | K60: 0.007
A61: =A60 -> HGV60 | B61: Common | C61: Total weight limit | D61: kg | E61: 60000 | F61: 60000 | G61: 60000 | H61: 60000 | I61: 60000 | J61: 60000 | K61: 60000
A62: =A61 -> HGV60 | B62: Common | C62: Depot stop | D62: h | E62: 12 | F62: 12 | G62: 12 | H62: 12 | I62: 12 | J62: 12 | K62: 12
A63: =A62 -> HGV60 | B63: Common | C63: Destination stop | D63: h | E63: 1 | F63: 1 | G63: 1 | H63: 1 | I63: 1 | J63: 1 | K63: 1
A64: =A63 -> HGV60 | B64: Common | C64: Rest stop | D64: h | E64: 0.75 | F64: 0.75 | G64: 0.75 | H64: 0.75 | I64: 0.75 | J64: 0.75 | K64: 0.75
A65: =A64 -> HGV60 | B65: Common | C65: Drive session | D65: h | E65: 4.5 | F65: 4.5 | G65: 4.5 | H65: 4.5 | I65: 4.5 | J65: 4.5 | K65: 4.5
A66: =A65 -> HGV60 | B66: Common | C66: Driver cost | D66: euro per h | E66: 33.6 | F66: 33.6 | G66: 33.6 | H66: 33.6 | I66: 33.6 | J66: 33.6 | K66: 33.6
A67: =A66 -> HGV60 | B67: ICEV | C67: Chassis weight | D67: kg | E67: 23000 | F67: 23000 | G67: 23000 | H67: 23000 | I67: 23000 | J67: 23000 | K67: 23000
A68: =A67 -> HGV60 | B68: ICEV | C68: Chassis cost, 2020 | D68: euro | E68: 259200 | F68: 259200 | G68: 259200 | H68: 259200 | I68: 259200 | J68: 259200 | K68: 259200
A69: =A68 -> HGV60 | B69: ICEV | C69: Lifetime | D69: years | E69: 10 | F69: 10 | G69: 10 | H69: 10 | I69: 10 | J69: 10 | K69: 10
... A73: =A72 -> HGV60 | B73: BEV | C73: Maintenance cost | D73: euro per km | E73: 0.039936 | F73: 0.039936 | G73: 0.039936 | H73: 0.039936 | I73: 0.039936 | J73: 0.039936 | K73: 0.039936
A74: =A71 -> HGV60 | B74: BEV | C74: Residual value at end of life | D74: ratio | E74: 0.09 | F74: 0.09 | G74: 0.09 | H74: 0.09 | I74: 0.09 | J74: 0.09 | K74: 0.09
A75: =A72 -> HGV60 | B75: BEV | C75: Energy consumption | D75: kWh per km | E75: 1.4573061 | F75: 1.4141084 | G75: 1.3721912 | H75: 1.3315165 | I75: 1.2920475 | J75: 1.2537484 | K75: 1.2165846
A76: =A73 -> HGV60 | B76: BEV | C76: Min range buffer | D76: km | E76: 50 | F76: 50 | G76: 50 | H76: 50 | I76: 50 | J76: 50 | K76: 50
A77: =A76 -> HGV60 | B77: BEV | C77: Lifetime | D77: years | E77: =E$28 -> 10 | F77: =E$28+(E$29-E$28)/3 -> 11.666667 | G77: =E$28+(E$29-E$28)*2/3 -> 13.333333 | H77: =$E$29 -> 15 | I77: =$E$29 -> 15 | J77: =$E$29 -> 15 | K77: =$E$29 -> 15
A78: =A77 -> HGV60 | B78: ICEV | C78: Chassis cost | D78: euro | E78: {=E68:K68+E$38:K$38} -> 259200 | F78: 262736.78 | G78: 266453.98 | H78: 270360.79 | I78: 274466.89 | J78: 278782.43 | K78: 283318.12 | L78: {=_xlfn.ANCHORARRAY(E78)/(E69:K69*E53:K53)+E58:K58+E70:K70} -> 0.50112 | M78: 0.50504976 | N78: 0.50917998 | O78: 0.51352088 | P78: 0.51808321 | Q78: 0.52287826 | R78: 0.52791791
A79: =A78 -> HGV60 | B79: BEV | C79: Chassis weight, excl battery | D79: kg | E79: {=E67:K67+E$46:K$46} -> 17780 | F79: 17780 | G79: 17780 | H79: 17780 | I79: 17780 | J79: 17780 | K79: 17780
A80: =A79 -> HGV60 | B80: BEV | C80: Chassis cost, excl battery | D80: euro | E80: {=_xlfn.ANCHORARRAY(E78)+E$42:K$42} -> 215794.56 | F80: 213303.26 | G80: 211051.33 | H80: 209015.76 | I80: 207175.77 | J80: 205512.56 | K80: 204009.15 | L80: {=_xlfn.ANCHORARRAY(E80)/(E75:K75*E53:K53)+E58:K58+E73:K73} -> 1.7985239 | M80: 1.8292093 | N80: 1.8621723 | O80: 1.8973907 | P80: 1.9348479 | Q80: 1.9745327 | R80: 2.0164389
A81: =A80 -> HGV60 | B81: BEV | C81: Min net battery capacity | D81: kWh | E81: {=E57:K57/batteries!E$20:K$20} -> 216.66667 | F81: 226.02995 | G81: 205.4841 | H81: 176.99056 | I81: 148.80116 | J81: 123.67132 | K81: 102.21085
A83: {=A52:D52} -> group | B83: subgroup | C83: variable | D83: unit | E83: 2020 | F83: 2025 | G83: 2030 | H83: 2035 | I83: 2040 | J83: 2045 | K83: 2050
A84: HGV40 | B84: {=B53:D80} -> Common | C84: Annual distance | D84: km | E84: {=F$4:F$27*_xlfn.ANCHORARRAY(AN19)} -> 115000 | F84: 115000 | G84: 115000 | H84: 115000 | I84: 115000 | J84: 115000 | K84: 115000
A85: =A84 -> HGV40 | B85: Common | C85: Utilization | D85: calendar days per year | E85: 230 | F85: 230 | G85: 230 | H85: 230 | I85: 230 | J85: 230 | K85: 230
A86: =A85 -> HGV40 | B86: Common | C86: Max time in transit | D86: h per day | E86: 11 | F86: 11 | G86: 11 | H86: 11 | I86: 11 | J86: 11 | K86: 11
A87: =A86 -> HGV40 | B87: Common | C87: Max time in use | D87: h per day | E87: 15 | F87: 15 | G87: 15 | H87: 15 | I87: 15 | J87: 15 | K87: 15
A88: =A86 -> HGV40 | B88: Common | C88: Power, peak | D88: kW | E88: 550 | F88: 550 | G88: 550 | H88: 550 | I88: 550 | J88: 550 | K88: 550
A89: =A88 -> HGV40 | B89: Common | C89: Tyres | D89: euro per km | E89: 0.09024 | F89: 0.09024 | G89: 0.09024 | H89: 0.09024 | I89: 0.09024 | J89: 0.09024 | K89: 0.09024
A90: =A89 -> HGV40 | B90: Common | C90: Cargo capacity value | D90: euro per ton-km | E90: 0.025 | F90: 0.025 | G90: 0.025 | H90: 0.025 | I90: 0.025 | J90: 0.025 | K90: 0.025
A91: =A90 -> HGV40 | B91: Common | C91: Cargo capacity value | D91: euro per m3-km | E91: 0.007 | F91: 0.007 | G91: 0.007 | H91: 0.007 | I91: 0.007 | J91: 0.007 | K91: 0.007
A92: =A91 -> HGV40 | B92: Common | C92: Total weight limit | D92: kg | E92: 40000 | F92: 40000 | G92: 40000 | H92: 40000 | I92: 40000 | J92: 40000 | K92: 40000
A93: =A92 -> HGV40 | B93: Common | C93: Depot stop | D93: h | E93: 9 | F93: 9 | G93: 9 | H93: 9 | I93: 9 | J93: 9 | K93: 9
A94: =A93 -> HGV40 | B94: Common | C94: Destination stop | D94: h | E94: 1 | F94: 1 | G94: 1 | H94: 1 | I94: 1 | J94: 1 | K94: 1
A95: =A94 -> HGV40 | B95: Common | C95: Rest stop | D95: h | E95: 0.75 | F95: 0.75 | G95: 0.75 | H95: 0.75 | I95: 0.75 | J95: 0.75 | K95: 0.75
A96: =A95 -> HGV40 | B96: Common | C96: Drive session | D96: h | E96: 4.5 | F96: 4.5 | G96: 4.5 | H96: 4.5 | I96: 4.5 | J96: 4.5 | K96: 4.5
A97: =A96 -> HGV40 | B97: Common | C97: Driver cost | D97: euro per h | E97: 33.6 | F97: 33.6 | G97: 33.6 | H97: 33.6 | I97: 33.6 | J97: 33.6 | K97: 33.6
A98: =A97 -> HGV40 | B98: ICEV | C98: Chassis weight | D98: kg | E98: 20000 | F98: 20000 | G98: 20000 | H98: 20000 | I98: 20000 | J98: 20000 | K98: 20000
A99: =A98 -> HGV40 | B99: ICEV | C99: Chassis cost, 2020 | D99: euro | E99: 235200 | F99: 235200 | G99: 235200 | H99: 235200 | I99: 235200 | J99: 235200 | K99: 235200
A100: =A99 -> HGV40 | B100: ICEV | C100: Lifetime | D100: years | E100: 10 | F100: 10 | G100: 10 | H100: 10 | I100: 10 | J100: 10 | K100: 10
... A104: =A103 -> HGV40 | B104: BEV | C104: Maintenance cost | D104: euro per km | E104: 0.045696 | F104: 0.045696 | G104: 0.045696 | H104: 0.045696 | I104: 0.045696 | J104: 0.045696 | K104: 0.045696
A105: =A102 -> HGV40 | B105: BEV | C105: Residual value at end of life | D105: ratio | E105: 0.09 | F105: 0.09 | G105: 0.09 | H105: 0.09 | I105: 0.09 | J105: 0.09 | K105: 0.09
A106: =A103 -> HGV40 | B106: BEV | C106: Energy consumption | D106: kWh per km | E106: 1.1242076 | F106: 1.0908836 | G106: 1.0585475 | H106: 1.0271699 | I106: 0.99672235 | J106: 0.96717735 | K106: 0.93850813
A107: =A104 -> HGV40 | B107: BEV | C107: Min range buffer | D107: km | E107: 50 | F107: 50 | G107: 50 | H107: 50 | I107: 50 | J107: 50 | K107: 50
A108: =A105 -> HGV40 | B108: BEV | C108: Lifetime | D108: years | E108: =F$28 -> 10 | F108: =F$28+(F$29-F$28)/3 -> 11.666667 | G108: =F$28+(F$29-F$28)*2/3 -> 13.333333 | H108: =$F$29 -> 15 | I108: =$F$29 -> 15 | J108: =$F$29 -> 15 | K108: =$F$29 -> 15
A109: =A106 -> HGV40 | B109: ICEV | C109: Chassis cost | D109: euro | E109: {=E99:K99+E$39:K$39} -> 235200 | F109: 237794.61 | G109: 240521.57 | H109: 243387.63 | I109: 246399.89 | J109: 249565.8 | K109: 252893.21
...

Sheet code
A1: long_name | B1: group | C1: subgroup | D1: variable | E1: unit | F1: 2020 | G1: 2025 | H1: 2030 | I1: 2035 | J1: 2040 | K1: 2045 | L1: 2050 | M1: Type | N1: COPY THIS
B3: HGV60Internal : VehicleType | N3: =IF(C3="",IF(B2="","","} ")&IF(B4="","","public class "&B3&" {"),"public override ParameterTimeSeries<"&M3&"> "&A3&" { get; } = new ParameterTimeSeries<"&M3&"> { "&_xlfn.TEXTJOIN("f, ",TRUE,F3:L3)&"f };") -> public class HGV60Internal : VehicleType {
A4: {=SUBSTITUTE(SUBSTITUTE(SUBSTITUTE(SUBSTITUTE(SUBSTITUTE(SUBSTITUTE(SUBSTITUTE(SUBSTITUTE(IF(C4:C260<>0,C4:C260&"_","")&D4:D260&"_"&E4:E260," ","_"),",",""),"(",""),")",""),"/","_per_"),"₂","2"),"-","_"),"€","euro")} -> Common_Annual_distance_km | B4: {=vehicles!A53:K81} -> HGV60 | C4: Common | D4: Annual distance | E4: km | F4: 90000 | G4: 90000 | H4: 90000 | I4: 90000 | J4: 90000 | K4: 90000 | L4: 90000 | M4: KilometersPerYear | N4: =IF(C4="",IF(B3="","","} ")&IF(B5="","","public class "&B4&" {"),"public override ParameterTimeSeries<"&M4&"> "&A4&" { get; } = new ParameterTimeSeries<"&M4&"> { "&_xlfn.TEXTJOIN("f, ",TRUE,F4:L4)&"f };") -> public override ParameterTimeSeries<KilometersPerYear> Common_Annual_distance_km { get; } = new ParameterTimeSeries<KilometersPerYear> { 90000f, 90000f, 90000f, 90000f, 90000f, 90000f, 90000f };
A5: Common_Utilization_calendar_days_per_year | B5: HGV60 | C5: Common | D5: Utilization | E5: calendar days per year | F5: 230 | G5: 230 | H5: 230 | I5: 230 | J5: 230 | K5: 230 | L5: 230 | M5: Dimensionless | N5: =IF(C5="",IF(B4="","","} ")&IF(B6="","","public class "&B5&" {"),"public override ParameterTimeSeries<"&M5&"> "&A5&" { get; } = new ParameterTimeSeries<"&M5&"> { "&_xlfn.TEXTJOIN("f, ",TRUE,F5:L5)&"f };") -> public override ParameterTimeSeries<Dimensionless> Common_Utilization_calendar_days_per_year { get; } = new ParameterTimeSeries<Dimensionless> { 230f, 230f, 230f, 230f, 230f, 230f, 230f };
A6: Common_Max_time_in_transit_h_per_day | B6: HGV60 | C6: Common | D6: Max time in transit | E6: h per day | F6: 9 | G6: 9 | H6: 9 | I6: 9 | J6: 9 | K6: 9 | L6: 9 | M6: Hours | N6: =IF(C6="",IF(B5="","","} ")&IF(B8="","","public class "&B6&" {"),"public override ParameterTimeSeries<"&M6&"> "&A6&" { get; } = new ParameterTimeSeries<"&M6&"> { "&_xlfn.TEXTJOIN("f, ",TRUE,F6:L6)&"f };") -> public override ParameterTimeSeries<Hours> Common_Max_time_in_transit_h_per_day { get; } = new ParameterTimeSeries<Hours> { 9f, 9f, 9f, 9f, 9f, 9f, 9f };
A7: Common_Max_time_in_use_h_per_day | B7: HGV60 | C7: Common | D7: Max time in use | E7: h per day | F7: 12 | G7: 12 | H7: 12 | I7: 12 | J7: 12 | K7: 12 | L7: 12 | M7: Hours | N7: =IF(C7="",IF(B6="","","} ")&IF(B9="","","public class "&B7&" {"),"public override ParameterTimeSeries<"&M7&"> "&A7&" { get; } = new ParameterTimeSeries<"&M7&"> { "&_xlfn.TEXTJOIN("f, ",TRUE,F7:L7)&"f };") -> public override ParameterTimeSeries<Hours> Common_Max_time_in_use_h_per_day { get; } = new ParameterTimeSeries<Hours> { 12f, 12f, 12f, 12f, 12f, 12f, 12f };
A8: Common_Power_peak_kW | B8: HGV60 | C8: Common | D8: Power, peak | E8: kW | F8: 750 | G8: 750 | H8: 750 | I8: 750 | J8: 750 | K8: 750 | L8: 750 | M8: KiloWatts | N8: =IF(C8="",IF(B6="","","} ")&IF(B9="","","public class "&B8&" {"),"public override ParameterTimeSeries<"&M8&"> "&A8&" { get; } = new ParameterTimeSeries<"&M8&"> { "&_xlfn.TEXTJOIN("f, ",TRUE,F8:L8)&"f };") -> public override ParameterTimeSeries<KiloWatts> Common_Power_peak_kW { get; } = new ParameterTimeSeries<KiloWatts> { 750f, 750f, 750f, 750f, 750f, 750f, 750f };
A9: Common_Tyres_euro_per_km | B9: HGV60 | C9: Common | D9: Tyres | E9: euro per km | F9: 0.11328 | G9: 0.11328 | H9: 0.11328 | I9: 0.11328 | J9: 0.11328 | K9: 0.11328 | L9: 0.11328 | M9: EuroPerKilometer | N9: =IF(C9="",IF(B8="","","} ")&IF(B10="","","public class "&B9&" {"),"public override ParameterTimeSeries<"&M9&"> "&A9&" { get; } = new ParameterTimeSeries<"&M9&"> { "&_xlfn.TEXTJOIN("f, ",TRUE,F9:L9)&"f };") -> public override ParameterTimeSeries<EuroPerKilometer> Common_Tyres_euro_per_km { get; } = new ParameterTimeSeries<EuroPerKilometer> { 0.11328f, 0.11328f, 0.11328f, 0.11328f, 0.11328f, 0.11328f, 0.11328f };
A10: Common_Cargo_capacity_value_euro_per_ton_km | B10: HGV60 | C10: Common | D10: Cargo capacity value | E10: euro per ton-km | F10: 0.025 | G10: 0.025 | H10: 0.025 | I10: 0.025 | J10: 0.025 | K10: 0.025 | L10: 0.025 | M10: EuroPerTonKilometer | N10: =IF(C10="",IF(B9="","","} ")&IF(B11="","","public class "&B10&" {"),"public override ParameterTimeSeries<"&M10&"> "&A10&" { get; } = new ParameterTimeSeries<"&M10&"> { "&_xlfn.TEXTJOIN("f, ",TRUE,F10:L10)&"f };") -> public override ParameterTimeSeries<EuroPerTonKilometer> Common_Cargo_capacity_value_euro_per_ton_km { get; } = new ParameterTimeSeries<EuroPerTonKilometer> { 0.025f, 0.025f, 0.025f, 0.025f, 0.025f, 0.025f, 0.025f };
A11: Common_Cargo_capacity_value_euro_per_m3_km | B11: HGV60 | C11: Common | D11: Cargo capacity value | E11: euro per m3-km | F11: 0.007 | G11: 0.007 | H11: 0.007 | I11: 0.007 | J11: 0.007 | K11: 0.007 | L11: 0.007 | M11: EuroPerCubicMeter | N11: =IF(C11="",IF(B10="","","} ")&IF(B12="","","public class "&B11&" {"),"public override ParameterTimeSeries<"&M11&"> "&A11&" { get; } = new ParameterTimeSeries<"&M11&"> { "&_xlfn.TEXTJOIN("f, ",TRUE,F11:L11)&"f };") -> public override ParameterTimeSeries<EuroPerCubicMeter> Common_Cargo_capacity_value_euro_per_m3_km { get; } = new ParameterTimeSeries<EuroPerCubicMeter> { 0.007f, 0.007f, 0.007f, 0.007f, 0.007f, 0.007f, 0.007f };
A12: Common_Total_weight_limit_kg | B12: HGV60 | C12: Common | D12: Total weight limit | E12: kg | F12: 60000 | G12: 60000 | H12: 60000 | I12: 60000 | J12: 60000 | K12: 60000 | L12: 60000 | M12: Kilogram | N12: =IF(C12="",IF(B11="","","} ")&IF(B13="","","public class "&B12&" {"),"public override ParameterTimeSeries<"&M12&"> "&A12&" { get; } = new ParameterTimeSeries<"&M12&"> { "&_xlfn.TEXTJOIN("f, ",TRUE,F12:L12)&"f };") -> public override ParameterTimeSeries<Kilogram> Common_Total_weight_limit_kg { get; } = new ParameterTimeSeries<Kilogram> { 60000f, 60000f, 60000f, 60000f, 60000f, 60000f, 60000f };
A13: Common_Depot_stop_h | B13: HGV60 | C13: Common | D13: Depot stop | E13: h | F13: 12 | G13: 12 | H13: 12 | I13: 12 | J13: 12 | K13: 12 | L13: 12 | M13: Hours | N13: =IF(C13="",IF(B12="","","} ")&IF(B14="","","public class "&B13&" {"),"public override ParameterTimeSeries<"&M13&"> "&A13&" { get; } = new ParameterTimeSeries<"&M13&"> { "&_xlfn.TEXTJOIN("f, ",TRUE,F13:L13)&"f };") -> public override ParameterTimeSeries<Hours> Common_Depot_stop_h { get; } = new ParameterTimeSeries<Hours> { 12f, 12f, 12f, 12f, 12f, 12f, 12f };
A14: Common_Destination_stop_h | B14: HGV60 | C14: Common | D14: Destination stop | E14: h | F14: 1 | G14: 1 | H14: 1 | I14: 1 | J14: 1 | K14: 1 | L14: 1 | M14: Hours | N14: =IF(C14="",IF(B13="","","} ")&IF(B15="","","public class "&B14&" {"),"public override ParameterTimeSeries<"&M14&"> "&A14&" { get; } = new ParameterTimeSeries<"&M14&"> { "&_xlfn.TEXTJOIN("f, ",TRUE,F14:L14)&"f };") -> public override ParameterTimeSeries<Hours> Common_Destination_stop_h { get; } = new ParameterTimeSeries<Hours> { 1f, 1f, 1f, 1f, 1f, 1f, 1f };
A15: Common_Rest_stop_h | B15: HGV60 | C15: Common | D15: Rest stop | E15: h | F15: 0.75 | G15: 0.75 | H15: 0.75 | I15: 0.75 | J15: 0.75 | K15: 0.75 | L15: 0.75 | M15: Hours | N15: =IF(C15="",IF(B14="","","} ")&IF(B16="","","public class "&B15&" {"),"public override ParameterTimeSeries<"&M15&"> "&A15&" { get; } = new ParameterTimeSeries<"&M15&"> { "&_xlfn.TEXTJOIN("f, ",TRUE,F15:L15)&"f };") -> public override ParameterTimeSeries<Hours> Common_Rest_stop_h { get; } = new ParameterTimeSeries<Hours> { 0.75f, 0.75f, 0.75f, 0.75f, 0.75f, 0.75f, 0.75f };
A16: Common_Drive_session_h | B16: HGV60 | C16: Common | D16: Drive session | E16: h | F16: 4.5 | G16: 4.5 | H16: 4.5 | I16: 4.5 | J16: 4.5 | K16: 4.5 | L16: 4.5 | M16: Hours | N16: =IF(C16="",IF(B15="","","} ")&IF(B17="","","public class "&B16&" {"),"public override ParameterTimeSeries<"&M16&"> "&A16&" { get; } = new ParameterTimeSeries<"&M16&"> { "&_xlfn.TEXTJOIN("f, ",TRUE,F16:L16)&"f };") -> public override ParameterTimeSeries<Hours> Common_Drive_session_h { get; } = new ParameterTimeSeries<Hours> { 4.5f, 4.5f, 4.5f, 4.5f, 4.5f, 4.5f, 4.5f };
A17: Common_Driver_cost_euro_per_h | B17: HGV60 | C17: Common | D17: Driver cost | E17: euro per h | F17: 33.6 | G17: 33.6 | H17: 33.6 | I17: 33.6 | J17: 33.6 | K17: 33.6 | L17: 33.6 | M17: EuroPerHour | N17: =IF(C17="",IF(B16="","","} ")&IF(B18="","","public class "&B17&" {"),"public override ParameterTimeSeries<"&M17&"> "&A17&" { get; } = new ParameterTimeSeries<"&M17&"> { "&_xlfn.TEXTJOIN("f, ",TRUE,F17:L17)&"f };") -> public override ParameterTimeSeries<EuroPerHour> Common_Driver_cost_euro_per_h { get; } = new ParameterTimeSeries<EuroPerHour> { 33.6f, 33.6f, 33.6f, 33.6f, 33.6f, 33.6f, 33.6f };
A18: ICEV_Chassis_weight_kg | B18: HGV60 | C18: ICEV | D18: Chassis weight | E18: kg | F18: 23000 | G18: 23000 | H18: 23000 | I18: 23000 | J18: 23000 | K18: 23000 | L18: 23000 | M18: Kilogram | N18: =IF(C18="",IF(B17="","","} ")&IF(B19="","","public class "&B18&" {"),"public override ParameterTimeSeries<"&M18&"> "&A18&" { get; } = new ParameterTimeSeries<"&M18&"> { "&_xlfn.TEXTJOIN("f, ",TRUE,F18:L18)&"f };") -> public override ParameterTimeSeries<Kilogram> ICEV_Chassis_weight_kg { get; } = new ParameterTimeSeries<Kilogram> { 23000f, 23000f, 23000f, 23000f, 23000f, 23000f, 23000f };
A19: ICEV_Chassis_cost_2020_euro | B19: HGV60 | C19: ICEV | D19: Chassis cost, 2020 | E19: euro | F19: 259200 | G19: 259200 | H19: 259200 | I19: 259200 | J19: 259200 | K19: 259200 | L19: 259200 | M19: Euro | N19: =IF(C19="",IF(B18="","","} ")&IF(B20="","","public class "&B19&" {"),"public override ParameterTimeSeries<"&M19&"> "&A19&" { get; } = new ParameterTimeSeries<"&M19&"> { "&_xlfn.TEXTJOIN("f, ",TRUE,F19:L19)&"f };") -> public override ParameterTimeSeries<Euro> ICEV_Chassis_cost_2020_euro { get; } = new ParameterTimeSeries<Euro> { 259200f, 259200f, 259200f, 259200f, 259200f, 259200f, 259200f };
A20: ICEV_Lifetime_years | B20: HGV60 | C20: ICEV | D20: Lifetime | E20: years | F20: 10 | G20: 10 | H20: 10 | I20: 10 | J20: 10 | K20: 10 | L20: 10 | M20: Years | N20: =IF(C20="",IF(B19="","","} ")&IF(B21="","","public class "&B20&" {"),"public override ParameterTimeSeries<"&M20&"> "&A20&" { get; } = new ParameterTimeSeries<"&M20&"> { "&_xlfn.TEXTJOIN("f, ",TRUE,F20:L20)&"f };") -> public override ParameterTimeSeries<Years> ICEV_Lifetime_years { get; } = new ParameterTimeSeries<Years> { 10f, 10f, 10f, 10f, 10f, 10f, 10f };
... A32: BEV_Min_net_battery_capacity_kWh | B32: HGV60 | C32: BEV | D32: Min net battery capacity | E32: kWh | F32: 216.66667 | G32: 226.02995 | H32: 205.4841 | I32: 176.99056 | J32: 148.80116 | K32: 123.67132 | L32: 102.21085 | M32: KiloWattHours | N32: =IF(C32="",IF(B31="","","} ")&IF(B33="","","public class "&B32&" {"),"public override ParameterTimeSeries<"&M32&"> "&A32&" { get; } = new ParameterTimeSeries<"&M32&"> { "&_xlfn.TEXTJOIN("f, ",TRUE,F32:L32)&"f };") -> public override ParameterTimeSeries<KiloWattHours> BEV_Min_net_battery_capacity_kWh { get; } = new ParameterTimeSeries<KiloWattHours> { 216.666666666667f, 226.029954358822f, 205.48410135118f, 176.990560239856f, 148.80116058438f, 123.671320743104f, 102.21085008598f };
A33: _ | B33: HGV40Internal : VehicleType | N33: =IF(C33="",IF(B32="","","} ")&IF(B34="","","public class "&B33&" {"),"public override ParameterTimeSeries<"&M33&"> "&A33&" { get; } = new ParameterTimeSeries<"&M33&"> { "&_xlfn.TEXTJOIN("f, ",TRUE,F33:L33)&"f };") -> } public class HGV40Internal : VehicleType {
A34: Common_Annual_distance_km | B34: {=vehicles!A84:K112} -> HGV40 | C34: Common | D34: Annual distance | E34: km | F34: 115000 | G34: 115000 | H34: 115000 | I34: 115000 | J34: 115000 | K34: 115000 | L34: 115000 | M34: {=M4:M32} -> KilometersPerYear | N34: =IF(C34="",IF(B33="","","} ")&IF(B35="","","public class "&B34&" {"),"public override ParameterTimeSeries<"&M34&"> "&A34&" { get; } = new ParameterTimeSeries<"&M34&"> { "&_xlfn.TEXTJOIN("f, ",TRUE,F34:L34)&"f };") -> public override ParameterTimeSeries<KilometersPerYear> Common_Annual_distance_km { get; } = new ParameterTimeSeries<KilometersPerYear> { 115000f, 115000f, 115000f, 115000f, 115000f, 115000f, 115000f };
A35: Common_Utilization_calendar_days_per_year | B35: HGV40 | C35: Common | D35: Utilization | E35: calendar days per year | F35: 230 | G35: 230 | H35: 230 | I35: 230 | J35: 230 | K35: 230 | L35: 230 | M35: Dimensionless | N35: =IF(C35="",IF(B34="","","} ")&IF(B36="","","public class "&B35&" {"),"public override ParameterTimeSeries<"&M35&"> "&A35&" { get; } = new ParameterTimeSeries<"&M35&"> { "&_xlfn.TEXTJOIN("f, ",TRUE,F35:L35)&"f };") -> public override ParameterTimeSeries<Dimensionless> Common_Utilization_calendar_days_per_year { get; } = new ParameterTimeSeries<Dimensionless> { 230f, 230f, 230f, 230f, 230f, 230f, 230f };
A36: Common_Max_time_in_transit_h_per_day | B36: HGV40 | C36: Common | D36: Max time in transit | E36: h per day | F36: 11 | G36: 11 | H36: 11 | I36: 11 | J36: 11 | K36: 11 | L36: 11 | M36: Hours | N36: =IF(C36="",IF(B35="","","} ")&IF(B38="","","public class "&B36&" {"),"public override ParameterTimeSeries<"&M36&"> "&A36&" { get; } = new ParameterTimeSeries<"&M36&"> { "&_xlfn.TEXTJOIN("f, ",TRUE,F36:L36)&"f };") -> public override ParameterTimeSeries<Hours> Common_Max_time_in_transit_h_per_day { get; } = new ParameterTimeSeries<Hours> { 11f, 11f, 11f, 11f, 11f, 11f, 11f };
A37: Common_Max_time_in_use_h_per_day | B37: HGV40 | C37: Common | D37: Max time in use | E37: h per day | F37: 15 | G37: 15 | H37: 15 | I37: 15 | J37: 15 | K37: 15 | L37: 15 | M37: Hours | N37: =IF(C37="",IF(B36="","","} ")&IF(B39="","","public class "&B37&" {"),"public override ParameterTimeSeries<"&M37&"> "&A37&" { get; } = new ParameterTimeSeries<"&M37&"> { "&_xlfn.TEXTJOIN("f, ",TRUE,F37:L37)&"f };") -> public override ParameterTimeSeries<Hours> Common_Max_time_in_use_h_per_day { get; } = new ParameterTimeSeries<Hours> { 15f, 15f, 15f, 15f, 15f, 15f, 15f };
A38: Common_Power_peak_kW | B38: HGV40 | C38: Common | D38: Power, peak | E38: kW | F38: 550 | G38: 550 | H38: 550 | I38: 550 | J38: 550 | K38: 550 | L38: 550 | M38: KiloWatts | N38: =IF(C38="",IF(B36="","","} ")&IF(B39="","","public class "&B38&" {"),"public override ParameterTimeSeries<"&M38&"> "&A38&" { get; } = new ParameterTimeSeries<"&M38&"> { "&_xlfn.TEXTJOIN("f, ",TRUE,F38:L38)&"f };") -> public override ParameterTimeSeries<KiloWatts> Common_Power_peak_kW { get; } = new ParameterTimeSeries<KiloWatts> { 550f, 550f, 550f, 550f, 550f, 550f, 550f };
A39: Common_Tyres_euro_per_km | B39: HGV40 | C39: Common | D39: Tyres | E39: euro per km | F39: 0.09024 | G39: 0.09024 | H39: 0.09024 | I39: 0.09024 | J39: 0.09024 | K39: 0.09024 | L39: 0.09024 | M39: EuroPerKilometer | N39: =IF(C39="",IF(B38="","","} ")&IF(B40="","","public class "&B39&" {"),"public override ParameterTimeSeries<"&M39&"> "&A39&" { get; } = new ParameterTimeSeries<"&M39&"> { "&_xlfn.TEXTJOIN("f, ",TRUE,F39:L39)&"f };") -> public override ParameterTimeSeries<EuroPerKilometer> Common_Tyres_euro_per_km { get; } = new ParameterTimeSeries<EuroPerKilometer> { 0.09024f, 0.09024f, 0.09024f, 0.09024f, 0.09024f, 0.09024f, 0.09024f };
A40: Common_Cargo_capacity_value_euro_per_ton_km | B40: HGV40 | C40: Common | D40: Cargo capacity value | E40: euro per ton-km | F40: 0.025 | G40: 0.025 | H40: 0.025 | I40: 0.025 | J40: 0.025 | K40: 0.025 | L40: 0.025 | M40: EuroPerTonKilometer | N40: =IF(C40="",IF(B39="","","} ")&IF(B41="","","public class "&B40&" {"),"public override ParameterTimeSeries<"&M40&"> "&A40&" { get; } = new ParameterTimeSeries<"&M40&"> { "&_xlfn.TEXTJOIN("f, ",TRUE,F40:L40)&"f };") -> public override ParameterTimeSeries<EuroPerTonKilometer> Common_Cargo_capacity_value_euro_per_ton_km { get; } = new ParameterTimeSeries<EuroPerTonKilometer> { 0.025f, 0.025f, 0.025f, 0.025f, 0.025f, 0.025f, 0.025f };
A41: Common_Cargo_capacity_value_euro_per_m3_km | B41: HGV40 | C41: Common | D41: Cargo capacity value | E41: euro per m3-km | F41: 0.007 | G41: 0.007 | H41: 0.007 | I41: 0.007 | J41: 0.007 | K41: 0.007 | L41: 0.007 | M41: EuroPerCubicMeter | N41: =IF(C41="",IF(B40="","","} ")&IF(B42="","","public class "&B41&" {"),"public override ParameterTimeSeries<"&M41&"> "&A41&" { get; } = new ParameterTimeSeries<"&M41&"> { "&_xlfn.TEXTJOIN("f, ",TRUE,F41:L41)&"f };") -> public override ParameterTimeSeries<EuroPerCubicMeter> Common_Cargo_capacity_value_euro_per_m3_km { get; } = new ParameterTimeSeries<EuroPerCubicMeter> { 0.007f, 0.007f, 0.007f, 0.007f, 0.007f, 0.007f, 0.007f };
A42: Common_Total_weight_limit_kg | B42: HGV40 | C42: Common | D42: Total weight limit | E42: kg | F42: 40000 | G42: 40000 | H42: 40000 | I42: 40000 | J42: 40000 | K42: 40000 | L42: 40000 | M42: Kilogram | N42: =IF(C42="",IF(B41="","","} ")&IF(B43="","","public class "&B42&" {"),"public override ParameterTimeSeries<"&M42&"> "&A42&" { get; } = new ParameterTimeSeries<"&M42&"> { "&_xlfn.TEXTJOIN("f, ",TRUE,F42:L42)&"f };") -> public override ParameterTimeSeries<Kilogram> Common_Total_weight_limit_kg { get; } = new ParameterTimeSeries<Kilogram> { 40000f, 40000f, 40000f, 40000f, 40000f, 40000f, 40000f };
A43: Common_Depot_stop_h | B43: HGV40 | C43: Common | D43: Depot stop | E43: h | F43: 9 | G43: 9 | H43: 9 | I43: 9 | J43: 9 | K43: 9 | L43: 9 | M43: Hours | N43: =IF(C43="",IF(B42="","","} ")&IF(B44="","","public class "&B43&" {"),"public override ParameterTimeSeries<"&M43&"> "&A43&" { get; } = new ParameterTimeSeries<"&M43&"> { "&_xlfn.TEXTJOIN("f, ",TRUE,F43:L43)&"f };") -> public override ParameterTimeSeries<Hours> Common_Depot_stop_h { get; } = new ParameterTimeSeries<Hours> { 9f, 9f, 9f, 9f, 9f, 9f, 9f };
A44: Common_Destination_stop_h | B44: HGV40 | C44: Common | D44: Destination stop | E44: h | F44: 1 | G44: 1 | H44: 1 | I44: 1 | J44: 1 | K44: 1 | L44: 1 | M44: Hours | N44: =IF(C44="",IF(B43="","","} ")&IF(B45="","","public class "&B44&" {"),"public override ParameterTimeSeries<"&M44&"> "&A44&" { get; } = new ParameterTimeSeries<"&M44&"> { "&_xlfn.TEXTJOIN("f, ",TRUE,F44:L44)&"f };") -> public override ParameterTimeSeries<Hours> Common_Destination_stop_h { get; } = new ParameterTimeSeries<Hours> { 1f, 1f, 1f, 1f, 1f, 1f, 1f };
A45: Common_Rest_stop_h | B45: HGV40 | C45: Common | D45: Rest stop | E45: h | F45: 0.75 | G45: 0.75 | H45: 0.75 | I45: 0.75 | J45: 0.75 | K45: 0.75 | L45: 0.75 | M45: Hours | N45: =IF(C45="",IF(B44="","","} ")&IF(B46="","","public class "&B45&" {"),"public override ParameterTimeSeries<"&M45&"> "&A45&" { get; } = new ParameterTimeSeries<"&M45&"> { "&_xlfn.TEXTJOIN("f, ",TRUE,F45:L45)&"f };") -> public override ParameterTimeSeries<Hours> Common_Rest_stop_h { get; } = new ParameterTimeSeries<Hours> { 0.75f, 0.75f, 0.75f, 0.75f, 0.75f, 0.75f, 0.75f };
A46: Common_Drive_session_h | B46: HGV40 | C46: Common | D46: Drive session | E46: h | F46: 4.5 | G46: 4.5 | H46: 4.5 | I46: 4.5 | J46: 4.5 | K46: 4.5 | L46: 4.5 | M46: Hours | N46: =IF(C46="",IF(B45="","","} ")&IF(B47="","","public class "&B46&" {"),"public override ParameterTimeSeries<"&M46&"> "&A46&" { get; } = new ParameterTimeSeries<"&M46&"> { "&_xlfn.TEXTJOIN("f, ",TRUE,F46:L46)&"f };") -> public override ParameterTimeSeries<Hours> Common_Drive_session_h { get; } = new ParameterTimeSeries<Hours> { 4.5f, 4.5f, 4.5f, 4.5f, 4.5f, 4.5f, 4.5f };
A47: Common_Driver_cost_euro_per_h | B47: HGV40 | C47: Common | D47: Driver cost | E47: euro per h | F47: 33.6 | G47: 33.6 | H47: 33.6 | I47: 33.6 | J47: 33.6 | K47: 33.6 | L47: 33.6 | M47: EuroPerHour | N47: =IF(C47="",IF(B46="","","} ")&IF(B48="","","public class "&B47&" {"),"public override ParameterTimeSeries<"&M47&"> "&A47&" { get; } = new ParameterTimeSeries<"&M47&"> { "&_xlfn.TEXTJOIN("f, ",TRUE,F47:L47)&"f };") -> public override ParameterTimeSeries<EuroPerHour> Common_Driver_cost_euro_per_h { get; } = new ParameterTimeSeries<EuroPerHour> { 33.6f, 33.6f, 33.6f, 33.6f, 33.6f, 33.6f, 33.6f };
A48: ICEV_Chassis_weight_kg | B48: HGV40 | C48: ICEV | D48: Chassis weight | E48: kg | F48: 20000 | G48: 20000 | H48: 20000 | I48: 20000 | J48: 20000 | K48: 20000 | L48: 20000 | M48: Kilogram | N48: =IF(C48="",IF(B47="","","} ")&IF(B49="","","public class "&B48&" {"),"public override ParameterTimeSeries<"&M48&"> "&A48&" { get; } = new ParameterTimeSeries<"&M48&"> { "&_xlfn.TEXTJOIN("f, ",TRUE,F48:L48)&"f };") -> public override ParameterTimeSeries<Kilogram> ICEV_Chassis_weight_kg { get; } = new ParameterTimeSeries<Kilogram> { 20000f, 20000f, 20000f, 20000f, 20000f, 20000f, 20000f };
A49: ICEV_Chassis_cost_2020_euro | B49: HGV40 | C49: ICEV | D49: Chassis cost, 2020 | E49: euro | F49: 235200 | G49: 235200 | H49: 235200 | I49: 235200 | J49: 235200 | K49: 235200 | L49: 235200 | M49: Euro | N49: =IF(C49="",IF(B48="","","} ")&IF(B50="","","public class "&B49&" {"),"public override ParameterTimeSeries<"&M49&"> "&A49&" { get; } = new ParameterTimeSeries<"&M49&"> { "&_xlfn.TEXTJOIN("f, ",TRUE,F49:L49)&"f };") -> public override ParameterTimeSeries<Euro> ICEV_Chassis_cost_2020_euro { get; } = new ParameterTimeSeries<Euro> { 235200f, 235200f, 235200f, 235200f, 235200f, 235200f, 235200f };
A50: ICEV_Lifetime_years | B50: HGV40 | C50: ICEV | D50: Lifetime | E50: years | F50: 10 | G50: 10 | H50: 10 | I50: 10 | J50: 10 | K50: 10 | L50: 10 | M50: Years | N50: =IF(C50="",IF(B49="","","} ")&IF(B51="","","public class "&B50&" {"),"public override ParameterTimeSeries<"&M50&"> "&A50&" { get; } = new ParameterTimeSeries<"&M50&"> { "&_xlfn.TEXTJOIN("f, ",TRUE,F50:L50)&"f };") -> public override ParameterTimeSeries<Years> ICEV_Lifetime_years { get; } = new ParameterTimeSeries<Years> { 10f, 10f, 10f, 10f, 10f, 10f, 10f };
... A62: BEV_Min_net_battery_capacity_kWh | B62: HGV40 | C62: BEV | D62: Min net battery capacity | E62: kWh | F62: 158.88889 | G62: 165.7553 | H62: 150.68834 | I62: 129.79308 | J62: 109.12085 | K62: 90.692302 | L62: 74.954623 | M62: KiloWattHours | N62: =IF(C62="",IF(B61="","","} ")&IF(B63="","","public class "&B62&" {"),"public override ParameterTimeSeries<"&M62&"> "&A62&" { get; } = new ParameterTimeSeries<"&M62&"> { "&_xlfn.TEXTJOIN("f, ",TRUE,F62:L62)&"f };") -> public override ParameterTimeSeries<KiloWattHours> BEV_Min_net_battery_capacity_kWh { get; } = new ParameterTimeSeries<KiloWattHours> { 158.888888888889f, 165.755299863136f, 150.688340990866f, 129.793077509228f, 109.120851095212f, 90.692301878276f, 74.9546233963855f };
A63: _ | B63: MGV24Internal : VehicleType | N63: =IF(C63="",IF(B62="","","} ")&IF(B64="","","public class "&B63&" {"),"public override ParameterTimeSeries<"&M63&"> "&A63&" { get; } = new ParameterTimeSeries<"&M63&"> { "&_xlfn.TEXTJOIN("f, ",TRUE,F63:L63)&"f };") -> } public class MGV24Internal : VehicleType {
A64: Common_Annual_distance_km | B64: {=vehicles!A115:K143} -> MGV24 | C64: Common | D64: Annual distance | E64: km | F64: 80000 | G64: 80000 | H64: 80000 | I64: 80000 | J64: 80000 | K64: 80000 | L64: 80000 | M64: {=M34:M62} -> KilometersPerYear | N64: =IF(C64="",IF(B63="","","} ")&IF(B65="","","public class "&B64&" {"),"public override ParameterTimeSeries<"&M64&"> "&A64&" { get; } = new ParameterTimeSeries<"&M64&"> { "&_xlfn.TEXTJOIN("f, ",TRUE,F64:L64)&"f };") -> public override ParameterTimeSeries<KilometersPerYear> Common_Annual_distance_km { get; } = new ParameterTimeSeries<KilometersPerYear> { 80000f, 80000f, 80000f, 80000f, 80000f, 80000f, 80000f };
A65: Common_Utilization_calendar_days_per_year | B65: MGV24 | C65: Common | D65: Utilization | E65: calendar days per year | F65: 230 | G65: 230 | H65: 230 | I65: 230 | J65: 230 | K65: 230 | L65: 230 | M65: Dimensionless | N65: =IF(C65="",IF(B64="","","} ")&IF(B66="","","public class "&B65&" {"),"public override ParameterTimeSeries<"&M65&"> "&A65&" { get; } = new ParameterTimeSeries<"&M65&"> { "&_xlfn.TEXTJOIN("f, ",TRUE,F65:L65)&"f };") -> public override ParameterTimeSeries<Dimensionless> Common_Utilization_calendar_days_per_year { get; } = new ParameterTimeSeries<Dimensionless> { 230f, 230f, 230f, 230f, 230f, 230f, 230f };
A66: Common_Max_time_in_transit_h_per_day | B66: MGV24 | C66: Common | D66: Max time in transit | E66: h per day | F66: 9 | G66: 9 | H66: 9 | I66: 9 | J66: 9 | K66: 9 | L66: 9 | M66: Hours | N66: =IF(C66="",IF(B65="","","} ")&IF(B68="","","public class "&B66&" {"),"public override ParameterTimeSeries<"&M66&"> "&A66&" { get; } = new ParameterTimeSeries<"&M66&"> { "&_xlfn.TEXTJOIN("f, ",TRUE,F66:L66)&"f };") -> public override ParameterTimeSeries<Hours> Common_Max_time_in_transit_h_per_day { get; } = new ParameterTimeSeries<Hours> { 9f, 9f, 9f, 9f, 9f, 9f, 9f };
A67: Common_Max_time_in_use_h_per_day | B67: MGV24 | C67: Common | D67: Max time in use | E67: h per day | F67: 12 | G67: 12 | H67: 12 | I67: 12 | J67: 12 | K67: 12 | L67: 12 | M67: Hours | N67: =IF(C67="",IF(B66="","","} ")&IF(B69="","","public class "&B67&" {"),"public override ParameterTimeSeries<"&M67&"> "&A67&" { get; } = new ParameterTimeSeries<"&M67&"> { "&_xlfn.TEXTJOIN("f, ",TRUE,F67:L67)&"f };") -> public override ParameterTimeSeries<Hours> Common_Max_time_in_use_h_per_day { get; } = new ParameterTimeSeries<Hours> { 12f, 12f, 12f, 12f, 12f, 12f, 12f };
A68: Common_Power_peak_kW | B68: MGV24 | C68: Common | D68: Power, peak | E68: kW | F68: 300 | G68: 300 | H68: 300 | I68: 300 | J68: 300 | K68: 300 | L68: 300 | M68: KiloWatts | N68: =IF(C68="",IF(B66="","","} ")&IF(B69="","","public class "&B68&" {"),"public override ParameterTimeSeries<"&M68&"> "&A68&" { get; } = new ParameterTimeSeries<"&M68&"> { "&_xlfn.TEXTJOIN("f, ",TRUE,F68:L68)&"f };") -> public override ParameterTimeSeries<KiloWatts> Common_Power_peak_kW { get; } = new ParameterTimeSeries<KiloWatts> { 300f, 300f, 300f, 300f, 300f, 300f, 300f };
A69: Common_Tyres_euro_per_km | B69: MGV24 | C69: Common | D69: Tyres | E69: euro per km | F69: 0.06144 | G69: 0.06144 | H69: 0.06144 | I69: 0.06144 | J69: 0.06144 | K69: 0.06144 | L69: 0.06144 | M69: EuroPerKilometer | N69: =IF(C69="",IF(B68="","","} ")&IF(B70="","","public class "&B69&" {"),"public override ParameterTimeSeries<"&M69&"> "&A69&" { get; } = new ParameterTimeSeries<"&M69&"> { "&_xlfn.TEXTJOIN("f, ",TRUE,F69:L69)&"f };") -> public override ParameterTimeSeries<EuroPerKilometer> Common_Tyres_euro_per_km { get; } = new ParameterTimeSeries<EuroPerKilometer> { 0.06144f, 0.06144f, 0.06144f, 0.06144f, 0.06144f, 0.06144f, 0.06144f };
A70: Common_Cargo_capacity_value_euro_per_ton_km | B70: MGV24 | C70: Common | D70: Cargo capacity value | E70: euro per ton-km | F70: 0.035 | G70: 0.035 | H70: 0.035 | I70: 0.035 | J70: 0.035 | K70: 0.035 | L70: 0.035 | M70: EuroPerTonKilometer | N70: =IF(C70="",IF(B69="","","} ")&IF(B71="","","public class "&B70&" {"),"public override ParameterTimeSeries<"&M70&"> "&A70&" { get; } = new ParameterTimeSeries<"&M70&"> { "&_xlfn.TEXTJOIN("f, ",TRUE,F70:L70)&"f };") -> public override ParameterTimeSeries<EuroPerTonKilometer> Common_Cargo_capacity_value_euro_per_ton_km { get; } = new ParameterTimeSeries<EuroPerTonKilometer> { 0.035f, 0.035f, 0.035f, 0.035f, 0.035f, 0.035f, 0.035f };
A71: Common_Cargo_capacity_value_euro_per_m3_km | B71: MGV24 | C71: Common | D71: Cargo capacity value | E71: euro per m3-km | F71: 0.0098 | G71: 0.0098 | H71: 0.0098 | I71: 0.0098 | J71: 0.0098 | K71: 0.0098 | L71: 0.0098 | M71: EuroPerCubicMeter | N71: =IF(C71="",IF(B70="","","} ")&IF(B72="","","public class "&B71&" {"),"public override ParameterTimeSeries<"&M71&"> "&A71&" { get; } = new ParameterTimeSeries<"&M71&"> { "&_xlfn.TEXTJOIN("f, ",TRUE,F71:L71)&"f };") -> public override ParameterTimeSeries<EuroPerCubicMeter> Common_Cargo_capacity_value_euro_per_m3_km { get; } = new ParameterTimeSeries<EuroPerCubicMeter> { 0.0098f, 0.0098f, 0.0098f, 0.0098f, 0.0098f, 0.0098f, 0.0098f };
A72: Common_Total_weight_limit_kg | B72: MGV24 | C72: Common | D72: Total weight limit | E72: kg | F72: 24000 | G72: 24000 | H72: 24000 | I72: 24000 | J72: 24000 | K72: 24000 | L72: 24000 | M72: Kilogram | N72: =IF(C72="",IF(B71="","","} ")&IF(B73="","","public class "&B72&" {"),"public override ParameterTimeSeries<"&M72&"> "&A72&" { get; } = new ParameterTimeSeries<"&M72&"> { "&_xlfn.TEXTJOIN("f, ",TRUE,F72:L72)&"f };") -> public override ParameterTimeSeries<Kilogram> Common_Total_weight_limit_kg { get; } = new ParameterTimeSeries<Kilogram> { 24000f, 24000f, 24000f, 24000f, 24000f, 24000f, 24000f };
A73: Common_Depot_stop_h | B73: MGV24 | C73: Common | D73: Depot stop | E73: h | F73: 12 | G73: 12 | H73: 12 | I73: 12 | J73: 12 | K73: 12 | L73: 12 | M73: Hours | N73: =IF(C73="",IF(B72="","","} ")&IF(B74="","","public class "&B73&" {"),"public override ParameterTimeSeries<"&M73&"> "&A73&" { get; } = new ParameterTimeSeries<"&M73&"> { "&_xlfn.TEXTJOIN("f, ",TRUE,F73:L73)&"f };") -> public override ParameterTimeSeries<Hours> Common_Depot_stop_h { get; } = new ParameterTimeSeries<Hours> { 12f, 12f, 12f, 12f, 12f, 12f, 12f };
A74: Common_Destination_stop_h | B74: MGV24 | C74: Common | D74: Destination stop | E74: h | F74: 0.5 | G74: 0.5 | H74: 0.5 | I74: 0.5 | J74: 0.5 | K74: 0.5 | L74: 0.5 | M74: Hours | N74: =IF(C74="",IF(B73="","","} ")&IF(B75="","","public class "&B74&" {"),"public override ParameterTimeSeries<"&M74&"> "&A74&" { get; } = new ParameterTimeSeries<"&M74&"> { "&_xlfn.TEXTJOIN("f, ",TRUE,F74:L74)&"f };") -> public override ParameterTimeSeries<Hours> Common_Destination_stop_h { get; } = new ParameterTimeSeries<Hours> { 0.5f, 0.5f, 0.5f, 0.5f, 0.5f, 0.5f, 0.5f };
A75: Common_Rest_stop_h | B75: MGV24 | C75: Common | D75: Rest stop | E75: h | F75: 0.75 | G75: 0.75 | H75: 0.75 | I75: 0.75 | J75: 0.75 | K75: 0.75 | L75: 0.75 | M75: Hours | N75: =IF(C75="",IF(B74="","","} ")&IF(B76="","","public class "&B75&" {"),"public override ParameterTimeSeries<"&M75&"> "&A75&" { get; } = new ParameterTimeSeries<"&M75&"> { "&_xlfn.TEXTJOIN("f, ",TRUE,F75:L75)&"f };") -> public override ParameterTimeSeries<Hours> Common_Rest_stop_h { get; } = new ParameterTimeSeries<Hours> { 0.75f, 0.75f, 0.75f, 0.75f, 0.75f, 0.75f, 0.75f };
A76: Common_Drive_session_h | B76: MGV24 | C76: Common | D76: Drive session | E76: h | F76: 4.5 | G76: 4.5 | H76: 4.5 | I76: 4.5 | J76: 4.5 | K76: 4.5 | L76: 4.5 | M76: Hours | N76: =IF(C76="",IF(B75="","","} ")&IF(B77="","","public class "&B76&" {"),"public override ParameterTimeSeries<"&M76&"> "&A76&" { get; } = new ParameterTimeSeries<"&M76&"> { "&_xlfn.TEXTJOIN("f, ",TRUE,F76:L76)&"f };") -> public override ParameterTimeSeries<Hours> Common_Drive_session_h { get; } = new ParameterTimeSeries<Hours> { 4.5f, 4.5f, 4.5f, 4.5f, 4.5f, 4.5f, 4.5f };
A77: Common_Driver_cost_euro_per_h | B77: MGV24 | C77: Common | D77: Driver cost | E77: euro per h | F77: 30 | G77: 30 | H77: 30 | I77: 30 | J77: 30 | K77: 30 | L77: 30 | M77: EuroPerHour | N77: =IF(C77="",IF(B76="","","} ")&IF(B78="","","public class "&B77&" {"),"public override ParameterTimeSeries<"&M77&"> "&A77&" { get; } = new ParameterTimeSeries<"&M77&"> { "&_xlfn.TEXTJOIN("f, ",TRUE,F77:L77)&"f };") -> public override ParameterTimeSeries<EuroPerHour> Common_Driver_cost_euro_per_h { get; } = new ParameterTimeSeries<EuroPerHour> { 30f, 30f, 30f, 30f, 30f, 30f, 30f };
A78: ICEV_Chassis_weight_kg | B78: MGV24 | C78: ICEV | D78: Chassis weight | E78: kg | F78: 10000 | G78: 10000 | H78: 10000 | I78: 10000 | J78: 10000 | K78: 10000 | L78: 10000 | M78: Kilogram | N78: =IF(C78="",IF(B77="","","} ")&IF(B79="","","public class "&B78&" {"),"public override ParameterTimeSeries<"&M78&"> "&A78&" { get; } = new ParameterTimeSeries<"&M78&"> { "&_xlfn.TEXTJOIN("f, ",TRUE,F78:L78)&"f };") -> public override ParameterTimeSeries<Kilogram> ICEV_Chassis_weight_kg { get; } = new ParameterTimeSeries<Kilogram> { 10000f, 10000f, 10000f, 10000f, 10000f, 10000f, 10000f };
A79: ICEV_Chassis_cost_2020_euro | B79: MGV24 | C79: ICEV | D79: Chassis cost, 2020 | E79: euro | F79: 148800 | G79: 148800 | H79: 148800 | I79: 148800 | J79: 148800 | K79: 148800 | L79: 148800 | M79: Euro | N79: =IF(C79="",IF(B78="","","} ")&IF(B80="","","public class "&B79&" {"),"public override ParameterTimeSeries<"&M79&"> "&A79&" { get; } = new ParameterTimeSeries<"&M79&"> { "&_xlfn.TEXTJOIN("f, ",TRUE,F79:L79)&"f };") -> public override ParameterTimeSeries<Euro> ICEV_Chassis_cost_2020_euro { get; } = new ParameterTimeSeries<Euro> { 148800f, 148800f, 148800f, 148800f, 148800f, 148800f, 148800f };
A80: ICEV_Lifetime_years | B80: MGV24 | C80: ICEV | D80: Lifetime | E80: years | F80: 7 | G80: 7 | H80: 7 | I80: 7 | J80: 7 | K80: 7 | L80: 7 | M80: Years | N80: =IF(C80="",IF(B79="","","} ")&IF(B81="","","public class "&B80&" {"),"public override ParameterTimeSeries<"&M80&"> "&A80&" { get; } = new ParameterTimeSeries<"&M80&"> { "&_xlfn.TEXTJOIN("f, ",TRUE,F80:L80)&"f };") -> public override ParameterTimeSeries<Years> ICEV_Lifetime_years { get; } = new ParameterTimeSeries<Years> { 7f, 7f, 7f, 7f, 7f, 7f, 7f };
... A92: BEV_Min_net_battery_capacity_kWh | B92: MGV24 | C92: BEV | D92: Min net battery capacity | E92: kWh | F92: 86.666667 | G92: 90.411982 | H92: 82.193641 | I92: 70.796224 | J92: 59.520464 | K92: 49.468528 | L92: 40.88434 | M92: KiloWattHours | N92: =IF(C92="",IF(B91="","","} ")&IF(B93="","","public class "&B92&" {"),"public override ParameterTimeSeries<"&M92&"> "&A92&" { get; } = new ParameterTimeSeries<"&M92&"> { "&_xlfn.TEXTJOIN("f, ",TRUE,F92:L92)&"f };") -> public override ParameterTimeSeries<KiloWattHours> BEV_Min_net_battery_capacity_kWh { get; } = new ParameterTimeSeries<KiloWattHours> { 86.6666666666667f, 90.4119817435287f, 82.1936405404721f, 70.7962240959425f, 59.5204642337518f, 49.4685282972415f, 40.8843400343921f };
A93: _ | B93: MGV16Internal : VehicleType | N93: =IF(C93="",IF(B92="","","} ")&IF(B94="","","public class "&B93&" {"),"public override ParameterTimeSeries<"&M93&"> "&A93&" { get; } = new ParameterTimeSeries<"&M93&"> { "&_xlfn.TEXTJOIN("f, ",TRUE,F93:L93)&"f };") -> } public class MGV16Internal : VehicleType {
A94: Common_Annual_distance_km | B94: {=vehicles!A146:K174} -> MGV16 | C94: Common | D94: Annual distance | E94: km | F94: 42000 | G94: 42000 | H94: 42000 | I94: 42000 | J94: 42000 | K94: 42000 | L94: 42000 | M94: {=M64:M92} -> KilometersPerYear | N94: =IF(C94="",IF(B93="","","} ")&IF(B95="","","public class "&B94&" {"),"public override ParameterTimeSeries<"&M94&"> "&A94&" { get; } = new ParameterTimeSeries<"&M94&"> { "&_xlfn.TEXTJOIN("f, ",TRUE,F94:L94)&"f };") -> public override ParameterTimeSeries<KilometersPerYear> Common_Annual_distance_km { get; } = new ParameterTimeSeries<KilometersPerYear> { 42000f, 42000f, 42000f, 42000f, 42000f, 42000f, 42000f };
A95: Common_Utilization_calendar_days_per_year | B95: MGV16 | C95: Common | D95: Utilization | E95: calendar days per year | F95: 230 | G95: 230 | H95: 230 | I95: 230 | J95: 230 | K95: 230 | L95: 230 | M95: Dimensionless | N95: =IF(C95="",IF(B94="","","} ")&IF(B96="","","public class "&B95&" {"),"public override ParameterTimeSeries<"&M95&"> "&A95&" { get; } = new ParameterTimeSeries<"&M95&"> { "&_xlfn.TEXTJOIN("f, ",TRUE,F95:L95)&"f };") -> public override ParameterTimeSeries<Dimensionless> Common_Utilization_calendar_days_per_year { get; } = new ParameterTimeSeries<Dimensionless> { 230f, 230f, 230f, 230f, 230f, 230f, 230f };
A96: Common_Max_time_in_transit_h_per_day | B96: MGV16 | C96: Common | D96: Max time in transit | E96: h per day | F96: 9 | G96: 9 | H96: 9 | I96: 9 | J96: 9 | K96: 9 | L96: 9 | M96: Hours | N96: =IF(C96="",IF(B95="","","} ")&IF(B98="","","public class "&B96&" {"),"public override ParameterTimeSeries<"&M96&"> "&A96&" { get; } = new ParameterTimeSeries<"&M96&"> { "&_xlfn.TEXTJOIN("f, ",TRUE,F96:L96)&"f };") -> public override ParameterTimeSeries<Hours> Common_Max_time_in_transit_h_per_day { get; } = new ParameterTimeSeries<Hours> { 9f, 9f, 9f, 9f, 9f, 9f, 9f };
A97: Common_Max_time_in_use_h_per_day | B97: MGV16 | C97: Common | D97: Max time in use | E97: h per day | F97: 12 | G97: 12 | H97: 12 | I97: 12 | J97: 12 | K97: 12 | L97: 12 | M97: Hours | N97: =IF(C97="",IF(B96="","","} ")&IF(B99="","","public class "&B97&" {"),"public override ParameterTimeSeries<"&M97&"> "&A97&" { get; } = new ParameterTimeSeries<"&M97&"> { "&_xlfn.TEXTJOIN("f, ",TRUE,F97:L97)&"f };") -> public override ParameterTimeSeries<Hours> Common_Max_time_in_use_h_per_day { get; } = new ParameterTimeSeries<Hours> { 12f, 12f, 12f, 12f, 12f, 12f, 12f };
A98: Common_Power_peak_kW | B98: MGV16 | C98: Common | D98: Power, peak | E98: kW | F98: 160 | G98: 160 | H98: 160 | I98: 160 | J98: 160 | K98: 160 | L98: 160 | M98: KiloWatts | N98: =IF(C98="",IF(B96="","","} ")&IF(B99="","","public class "&B98&" {"),"public override ParameterTimeSeries<"&M98&"> "&A98&" { get; } = new ParameterTimeSeries<"&M98&"> { "&_xlfn.TEXTJOIN("f, ",TRUE,F98:L98)&"f };") -> public override ParameterTimeSeries<KiloWatts> Common_Power_peak_kW { get; } = new ParameterTimeSeries<KiloWatts> { 160f, 160f, 160f, 160f, 160f, 160f, 160f };
A99: Common_Tyres_euro_per_km | B99: MGV16 | C99: Common | D99: Tyres | E99: euro per km | F99: 0.03072 | G99: 0.03072 | H99: 0.03072 | I99: 0.03072 | J99: 0.03072 | K99: 0.03072 | L99: 0.03072 | M99: EuroPerKilometer | N99: =IF(C99="",IF(B98="","","} ")&IF(B100="","","public class "&B99&" {"),"public override ParameterTimeSeries<"&M99&"> "&A99&" { get; } = new ParameterTimeSeries<"&M99&"> { "&_xlfn.TEXTJOIN("f, ",TRUE,F99:L99)&"f };") -> public override ParameterTimeSeries<EuroPerKilometer> Common_Tyres_euro_per_km { get; } = new ParameterTimeSeries<EuroPerKilometer> { 0.03072f, 0.03072f, 0.03072f, 0.03072f, 0.03072f, 0.03072f, 0.03072f };
A100: Common_Cargo_capacity_value_euro_per_ton_km | B100: MGV16 | C100: Common | D100: Cargo capacity value | E100: euro per ton-km | F100: 0.05 | G100: 0.05 | H100: 0.05 | I100: 0.05 | J100: 0.05 | K100: 0.05 | L100: 0.05 | M100: EuroPerTonKilometer | N100: =IF(C100="",IF(B99="","","} ")&IF(B101="","","public class "&B100&" {"),"public override ParameterTimeSeries<"&M100&"> "&A100&" { get; } = new ParameterTimeSeries<"&M100&"> { "&_xlfn.TEXTJOIN("f, ",TRUE,F100:L100)&"f };") -> public override ParameterTimeSeries<EuroPerTonKilometer> Common_Cargo_capacity_value_euro_per_ton_km { get; } = new ParameterTimeSeries<EuroPerTonKilometer> { 0.05f, 0.05f, 0.05f, 0.05f, 0.05f, 0.05f, 0.05f };
A101: Common_Cargo_capacity_value_euro_per_m3_km | B101: MGV16 | C101: Common | D101: Cargo capacity value | E101: euro per m3-km | F101: 0.014 | G101: 0.014 | H101: 0.014 | I101: 0.014 | J101: 0.014 | K101: 0.014 | L101: 0.014 | M101: EuroPerCubicMeter | N101: =IF(C101="",IF(B100="","","} ")&IF(B102="","","public class "&B101&" {"),"public override ParameterTimeSeries<"&M101&"> "&A101&" { get; } = new ParameterTimeSeries<"&M101&"> { "&_xlfn.TEXTJOIN("f, ",TRUE,F101:L101)&"f };") -> public override ParameterTimeSeries<EuroPerCubicMeter> Common_Cargo_capacity_value_euro_per_m3_km { get; } = new ParameterTimeSeries<EuroPerCubicMeter> { 0.014f, 0.014f, 0.014f, 0.014f, 0.014f, 0.014f, 0.014f };
A102: Common_Total_weight_limit_kg | B102: MGV16 | C102: Common | D102: Total weight limit | E102: kg | F102: 16000 | G102: 16000 | H102: 16000 | I102: 16000 | J102: 16000 | K102: 16000 | L102: 16000 | M102: Kilogram | N102: =IF(C102="",IF(B101="","","} ")&IF(B103="","","public class "&B102&" {"),"public override ParameterTimeSeries<"&M102&"> "&A102&" { get; } = new ParameterTimeSeries<"&M102&"> { "&_xlfn.TEXTJOIN("f, ",TRUE,F102:L102)&"f };") -> public override ParameterTimeSeries<Kilogram> Common_Total_weight_limit_kg { get; } = new ParameterTimeSeries<Kilogram> { 16000f, 16000f, 16000f, 16000f, 16000f, 16000f, 16000f };
A103: Common_Depot_stop_h | B103: MGV16 | C103: Common | D103: Depot stop | E103: h | F103: 12 | G103: 12 | H103: 12 | I103: 12 | J103: 12 | K103: 12 | L103: 12 | M103: Hours | N103: =IF(C103="",IF(B102="","","} ")&IF(B104="","","public class "&B103&" {"),"public override ParameterTimeSeries<"&M103&"> "&A103&" { get; } = new ParameterTimeSeries<"&M103&"> { "&_xlfn.TEXTJOIN("f, ",TRUE,F103:L103)&"f };") -> public override ParameterTimeSeries<Hours> Common_Depot_stop_h { get; } = new ParameterTimeSeries<Hours> { 12f, 12f, 12f, 12f, 12f, 12f, 12f };
A104: Common_Destination_stop_h | B104: MGV16 | C104: Common | D104: Destination stop | E104: h | F104: 0.2 | G104: 0.2 | H104: 0.2 | I104: 0.2 | J104: 0.2 | K104: 0.2 | L104: 0.2 | M104: Hours | N104: =IF(C104="",IF(B103="","","} ")&IF(B105="","","public class "&B104&" {"),"public override ParameterTimeSeries<"&M104&"> "&A104&" { get; } = new ParameterTimeSeries<"&M104&"> { "&_xlfn.TEXTJOIN("f, ",TRUE,F104:L104)&"f };") -> public override ParameterTimeSeries<Hours> Common_Destination_stop_h { get; } = new ParameterTimeSeries<Hours> { 0.2f, 0.2f, 0.2f, 0.2f, 0.2f, 0.2f, 0.2f };
A105: Common_Rest_stop_h | B105: MGV16 | C105: Common | D105: Rest stop | E105: h | F105: 0.75 | G105: 0.75 | H105: 0.75 | I105: 0.75 | J105: 0.75 | K105: 0.75 | L105: 0.75 | M105: Hours | N105: =IF(C105="",IF(B104="","","} ")&IF(B106="","","public class "&B105&" {"),"public override ParameterTimeSeries<"&M105&"> "&A105&" { get; } = new ParameterTimeSeries<"&M105&"> { "&_xlfn.TEXTJOIN("f, ",TRUE,F105:L105)&"f };") -> public override ParameterTimeSeries<Hours> Common_Rest_stop_h { get; } = new ParameterTimeSeries<Hours> { 0.75f, 0.75f, 0.75f, 0.75f, 0.75f, 0.75f, 0.75f };
A106: Common_Drive_session_h | B106: MGV16 | C106: Common | D106: Drive session | E106: h | F106: 4.5 | G106: 4.5 | H106: 4.5 | I106: 4.5 | J106: 4.5 | K106: 4.5 | L106: 4.5 | M106: Hours | N106: =IF(C106="",IF(B105="","","} ")&IF(B107="","","public class "&B106&" {"),"public override ParameterTimeSeries<"&M106&"> "&A106&" { get; } = new ParameterTimeSeries<"&M106&"> { "&_xlfn.TEXTJOIN("f, ",TRUE,F106:L106)&"f };") -> public override ParameterTimeSeries<Hours> Common_Drive_session_h { get; } = new ParameterTimeSeries<Hours> { 4.5f, 4.5f, 4.5f, 4.5f, 4.5f, 4.5f, 4.5f };
A107: Common_Driver_cost_euro_per_h | B107: MGV16 | C107: Common | D107: Driver cost | E107: euro per h | F107: 30 | G107: 30 | H107: 30 | I107: 30 | J107: 30 | K107: 30 | L107: 30 | M107: EuroPerHour | N107: =IF(C107="",IF(B106="","","} ")&IF(B108="","","public class "&B107&" {"),"public override ParameterTimeSeries<"&M107&"> "&A107&" { get; } = new ParameterTimeSeries<"&M107&"> { "&_xlfn.TEXTJOIN("f, ",TRUE,F107:L107)&"f };") -> public override ParameterTimeSeries<EuroPerHour> Common_Driver_cost_euro_per_h { get; } = new ParameterTimeSeries<EuroPerHour> { 30f, 30f, 30f, 30f, 30f, 30f, 30f };
A108: ICEV_Chassis_weight_kg | B108: MGV16 | C108: ICEV | D108: Chassis weight | E108: kg | F108: 5000 | G108: 5000 | H108: 5000 | I108: 5000 | J108: 5000 | K108: 5000 | L108: 5000 | M108: Kilogram | N108: =IF(C108="",IF(B107="","","} ")&IF(B109="","","public class "&B108&" {"),"public override ParameterTimeSeries<"&M108&"> "&A108&" { get; } = new ParameterTimeSeries<"&M108&"> { "&_xlfn.TEXTJOIN("f, ",TRUE,F108:L108)&"f };") -> public override ParameterTimeSeries<Kilogram> ICEV_Chassis_weight_kg { get; } = new ParameterTimeSeries<Kilogram> { 5000f, 5000f, 5000f, 5000f, 5000f, 5000f, 5000f };
A109: ICEV_Chassis_cost_2020_euro | B109: MGV16 | C109: ICEV | D109: Chassis cost, 2020 | E109: euro | F109: 91200 | G109: 91200 | H109: 91200 | I109: 91200 | J109: 91200 | K109: 91200 | L109: 91200 | M109: Euro | N109: =IF(C109="",IF(B108="","","} ")&IF(B110="","","public class "&B109&" {"),"public override ParameterTimeSeries<"&M109&"> "&A109&" { get; } = new ParameterTimeSeries<"&M109&"> { "&_xlfn.TEXTJOIN("f, ",TRUE,F109:L109)&"f };") -> public override ParameterTimeSeries<Euro> ICEV_Chassis_cost_2020_euro { get; } = new ParameterTimeSeries<Euro> { 91200f, 91200f, 91200f, 91200f, 91200f, 91200f, 91200f };
A110: ICEV_Lifetime_years | B110: MGV16 | C110: ICEV | D110: Lifetime | E110: years | F110: 7 | G110: 7 | H110: 7 | I110: 7 | J110: 7 | K110: 7 | L110: 7 | M110: Years | N110: =IF(C110="",IF(B109="","","} ")&IF(B111="","","public class "&B110&" {"),"public override ParameterTimeSeries<"&M110&"> "&A110&" { get; } = new ParameterTimeSeries<"&M110&"> { "&_xlfn.TEXTJOIN("f, ",TRUE,F110:L110)&"f };") -> public override ParameterTimeSeries<Years> ICEV_Lifetime_years { get; } = new ParameterTimeSeries<Years> { 7f, 7f, 7f, 7f, 7f, 7f, 7f };
... A122: BEV_Min_net_battery_capacity_kWh | B122: MGV16 | C122: BEV | D122: Min net battery capacity | E122: kWh | F122: 46.222222 | G122: 48.219724 | H122: 43.836608 | I122: 37.757986 | J122: 31.744248 | K122: 26.383215 | L122: 21.804981 | M122: KiloWattHours | N122: =IF(C122="",IF(B121="","","} ")&IF(B123="","","public class "&B122&" {"),"public override ParameterTimeSeries<"&M122&"> "&A122&" { get; } = new ParameterTimeSeries<"&M122&"> { "&_xlfn.TEXTJOIN("f, ",TRUE,F122:L122)&"f };") -> public override ParameterTimeSeries<KiloWattHours> BEV_Min_net_battery_capacity_kWh { get; } = new ParameterTimeSeries<KiloWattHours> { 46.2222222222222f, 48.2197235965486f, 43.8366082882518f, 37.7579861845027f, 31.7442475913343f, 26.3832150918621f, 21.8049813516758f };
A123: _ | B123: WorldInternal | N123: =IF(C123="",IF(B122="","","} ")&IF(B124="","","public class "&B123&" {"),"public ParameterTimeSeries<"&M123&"> "&A123&" { get; } = new ParameterTimeSeries<"&M123&"> { "&_xlfn.TEXTJOIN("f, ",TRUE,F123:L123)&"f };") -> } public class WorldInternal {
A124: Economy_Public_sector_interest_rate_percent | B124: {=world!A2:K34} -> World | C124: Economy | D124: Public sector interest rate | E124: percent | F124: 0.02 | G124: 0.02 | H124: 0.02 | I124: 0.02 | J124: 0.02 | K124: 0.02 | L124: 0.02 | M124: OtherUnit | N124: =IF(C124="",IF(B123="","","} ")&IF(B125="","","public class "&B124&" {"),"public ParameterTimeSeries<"&M124&"> "&A124&" { get; } = new ParameterTimeSeries<"&M124&"> { "&_xlfn.TEXTJOIN("f, ",TRUE,F124:L124)&"f };") -> public ParameterTimeSeries<OtherUnit> Economy_Public_sector_interest_rate_percent { get; } = new ParameterTimeSeries<OtherUnit> { 0.02f, 0.02f, 0.02f, 0.02f, 0.02f, 0.02f, 0.02f };
A125: Economy_Private_sector_interest_public_charging_and_trucks_percent | B125: World | C125: Economy | D125: Private sector interest public charging and trucks | E125: percent | F125: 0.03 | G125: 0.03 | H125: 0.03 | I125: 0.03 | J125: 0.03 | K125: 0.03 | L125: 0.03 | M125: OtherUnit | N125: =IF(C125="",IF(B124="","","} ")&IF(B127="","","public class "&B125&" {"),"public ParameterTimeSeries<"&M125&"> "&A125&" { get; } = new ParameterTimeSeries<"&M125&"> { "&_xlfn.TEXTJOIN("f, ",TRUE,F125:L125)&"f };") -> public ParameterTimeSeries<OtherUnit> Economy_Private_sector_interest_public_charging_and_trucks_percent { get; } = new ParameterTimeSeries<OtherUnit> { 0.03f, 0.03f, 0.03f, 0.03f, 0.03f, 0.03f, 0.03f };
A126: Economy_Private_sector_interest_depot_charging_percent | B126: World | C126: Economy | D126: Private sector interest depot charging | E126: percent | F126: 0.07 | G126: 0.07 | H126: 0.07 | I126: 0.07 | J126: 0.07 | K126: 0.07 | L126: 0.07 | M126: OtherUnit | N126: =IF(C126="",IF(B125="","","} ")&IF(B129="","","public class "&B126&" {"),"public ParameterTimeSeries<"&M126&"> "&A126&" { get; } = new ParameterTimeSeries<"&M126&"> { "&_xlfn.TEXTJOIN("f, ",TRUE,F126:L126)&"f };") -> public ParameterTimeSeries<OtherUnit> Economy_Private_sector_interest_depot_charging_percent { get; } = new ParameterTimeSeries<OtherUnit> { 0.07f, 0.07f, 0.07f, 0.07f, 0.07f, 0.07f, 0.07f };
A127: Economy_Heavy_traffic_volume_vs_2020_percent | B127: World | C127: Economy | D127: Heavy traffic volume vs 2020 | E127: percent | F127: 2.5 | G127: 2.6667803 | H127: 2.8446868 | I127: 3.0344619 | J127: 3.2368973 | K127: 3.4528375 | L127: 3.6831836 | M127: Dimensionless | N127: =IF(C127="",IF(B125="","","} ")&IF(B129="","","public class "&B127&" {"),"public ParameterTimeSeries<"&M127&"> "&A127&" { get; } = new ParameterTimeSeries<"&M127&"> { "&_xlfn.TEXTJOIN("f, ",TRUE,F127:L127)&"f };") -> public ParameterTimeSeries<Dimensionless> Economy_Heavy_traffic_volume_vs_2020_percent { get; } = new ParameterTimeSeries<Dimensionless> { 2.5f, 2.66678028294073f, 2.84468683099258f, 3.03446190081287f, 3.23689726656904f, 3.45283752335643f, 3.68318361099394f };
A128: Economy_Logistic_BEV_penalty_percent | B128: World | C128: Economy | D128: Logistic BEV penalty | E128: percent | F128: 0.15 | G128: 0.125 | H128: 0.1 | I128: 0.075 | J128: 0.05 | K128: 0.025 | L128: 0 | M128: Dimensionless | N128: =IF(C128="",IF(B126="","","} ")&IF(B130="","","public class "&B128&" {"),"public ParameterTimeSeries<"&M128&"> "&A128&" { get; } = new ParameterTimeSeries<"&M128&"> { "&_xlfn.TEXTJOIN("f, ",TRUE,F128:L128)&"f };") -> public ParameterTimeSeries<Dimensionless> Economy_Logistic_BEV_penalty_percent { get; } = new ParameterTimeSeries<Dimensionless> { 0.15f, 0.125f, 0.1f, 0.075f, 0.05f, 0.025f, 0f };
A129: Charging_Extra_stop_overhead_h | B129: World | C129: Charging | D129: Extra stop overhead | E129: h | F129: 0.25 | G129: 0.21468351 | H129: 0.18435603 | I129: 0.1583128 | J129: 0.13594859 | K129: 0.11674368 | L129: 0.10025177 | M129: Hours | N129: =IF(C129="",IF(B127="","","} ")&IF(B130="","","public class "&B129&" {"),"public ParameterTimeSeries<"&M129&"> "&A129&" { get; } = new ParameterTimeSeries<"&M129&"> { "&_xlfn.TEXTJOIN("f, ",TRUE,F129:L129)&"f };") -> public ParameterTimeSeries<Hours> Charging_Extra_stop_overhead_h { get; } = new ParameterTimeSeries<Hours> { 0.25f, 0.214683506425f, 0.184356031723732f, 0.158312797284197f, 0.135948585731687f, 0.116743676313593f, 0.100251767135789f };
A130: CO2_SCC_euro_per_kg | B130: World | C130: CO₂ | D130: SCC | E130: euro per kg | F130: 0.08 | G130: 0.165 | H130: 0.25 | I130: 0.3875 | J130: 0.525 | K130: 0.6625 | L130: 0.8 | M130: EuroPerKilogram | N130: =IF(C130="",IF(B129="","","} ")&IF(B131="","","public class "&B130&" {"),"public ParameterTimeSeries<"&M130&"> "&A130&" { get; } = new ParameterTimeSeries<"&M130&"> { "&_xlfn.TEXTJOIN("f, ",TRUE,F130:L130)&"f };") -> public ParameterTimeSeries<EuroPerKilogram> CO2_SCC_euro_per_kg { get; } = new ParameterTimeSeries<EuroPerKilogram> { 0.08f, 0.165f, 0.25f, 0.3875f, 0.525f, 0.6625f, 0.8f };
A131: CO2_Tax_ratio_of_SCC | B131: World | C131: CO₂ | D131: Tax | E131: ratio of SCC | F131: 0.7 | G131: 0.75 | H131: 0.8 | I131: 0.85 | J131: 0.9 | K131: 0.95 | L131: 1 | M131: Dimensionless | N131: =IF(C131="",IF(B130="","","} ")&IF(B138="","","public class "&B131&" {"),"public ParameterTimeSeries<"&M131&"> "&A131&" { get; } = new ParameterTimeSeries<"&M131&"> { "&_xlfn.TEXTJOIN("f, ",TRUE,F131:L131)&"f };") -> public ParameterTimeSeries<Dimensionless> CO2_Tax_ratio_of_SCC { get; } = new ParameterTimeSeries<Dimensionless> { 0.7f, 0.75f, 0.8f, 0.85f, 0.9f, 0.95f, 1f };
A132: FossilDiesel_Price_euro_per_liter | B132: World | C132: FossilDiesel | D132: Price | E132: euro per liter | F132: 0.6 | G132: 0.63687443 | H132: 0.67601507 | I132: 0.71756118 | J132: 0.76166062 | K132: 0.80847029 | L132: 0.85815676 | M132: EuroPerLiter | N132: =IF(C132="",IF(B131="","","} ")&IF(B139="","","public class "&B132&" {"),"public ParameterTimeSeries<"&M132&"> "&A132&" { get; } = new ParameterTimeSeries<"&M132&"> { "&_xlfn.TEXTJOIN("f, ",TRUE,F132:L132)&"f };") -> public ParameterTimeSeries<EuroPerLiter> FossilDiesel_Price_euro_per_liter { get; } = new ParameterTimeSeries<EuroPerLiter> { 0.6f, 0.636874430357299f, 0.676015066738224f, 0.71756118423643f, 0.761660617428475f, 0.808470286417248f, 0.858156755204646f };
A133: RenewableDiesel_Price_euro_per_liter | B133: World | C133: RenewableDiesel | D133: Price | E133: euro per liter | F133: 1.5 | G133: 1.5 | H133: 1.5921861 | I133: 1.6900377 | J133: 1.793903 | K133: 1.9041515 | L133: 2.0211757 | M133: EuroPerLiter | N133: =IF(C133="",IF(B132="","","} ")&IF(B140="","","public class "&B133&" {"),"public ParameterTimeSeries<"&M133&"> "&A133&" { get; } = new ParameterTimeSeries<"&M133&"> { "&_xlfn.TEXTJOIN("f, ",TRUE,F133:L133)&"f };") -> public ParameterTimeSeries<EuroPerLiter> RenewableDiesel_Price_euro_per_liter { get; } = new ParameterTimeSeries<EuroPerLiter> { 1.5f, 1.5f, 1.59218607589325f, 1.69003766684556f, 1.79390296059107f, 1.90415154357119f, 2.02117571604312f };
A134: RenewableDiesel_Supply_cap_liter_per_year | B134: World | C134: RenewableDiesel | D134: Supply cap | E134: liter per year | F134: 175000000 | G134: 1.9321414e+08 | H134: 2.1332402e+08 | I134: 2.3552696e+08 | J134: 2.6004079e+08 | K134: 2.8710605e+08 | L134: 3.1698828e+08 | M134: LiterPerYear | N134: =IF(C134="",IF(B133="","","} ")&IF(B141="","","public class "&B134&" {"),"public ParameterTimeSeries<"&M134&"> "&A134&" { get; } = new ParameterTimeSeries<"&M134&"> { "&_xlfn.TEXTJOIN("f, ",TRUE,F134:L134)&"f };") -> public ParameterTimeSeries<LiterPerYear> RenewableDiesel_Supply_cap_liter_per_year { get; } = new ParameterTimeSeries<LiterPerYear> { 175000000f, 193214140.56f, 213324023.499083f, 235526959.206723f, 260040794.296212f, 287106049.031328f, 316988277.218087f };
A135: RenewableDiesel_Blend_guess_ratio | B135: World | C135: RenewableDiesel | D135: Blend guess | E135: ratio | F135: 0.05 | G135: 0.06 | H135: 0.08 | I135: 0.28812154 | J135: 0.44916202 | K135: 0.57377207 | L135: 0.67019295 | M135: Dimensionless | N135: =IF(C135="",IF(B133="","","} ")&IF(B141="","","public class "&B135&" {"),"public ParameterTimeSeries<"&M135&"> "&A135&" { get; } = new ParameterTimeSeries<"&M135&"> { "&_xlfn.TEXTJOIN("f, ",TRUE,F135:L135)&"f };") -> public ParameterTimeSeries<Dimensionless> RenewableDiesel_Blend_guess_ratio { get; } = new ParameterTimeSeries<Dimensionless> { 0.05f, 0.06f, 0.08f, 0.2881215375f, 0.449162015900691f, 0.573772068253027f, 0.670192951384141f };
A136: FossilDiesel_Emissions_kg_CO2_per_liter | B136: World | C136: FossilDiesel | D136: Emissions | E136: kg CO₂ per liter | F136: 3.23 | G136: 3.23 | H136: 3.23 | I136: 3.23 | J136: 3.23 | K136: 3.23 | L136: 3.23 | M136: KilogramPerLiter | N136: =IF(C136="",IF(B135="","","} ")&IF(B142="","","public class "&B136&" {"),"public ParameterTimeSeries<"&M136&"> "&A136&" { get; } = new ParameterTimeSeries<"&M136&"> { "&_xlfn.TEXTJOIN("f, ",TRUE,F136:L136)&"f };") -> public ParameterTimeSeries<KilogramPerLiter> FossilDiesel_Emissions_kg_CO2_per_liter { get; } = new ParameterTimeSeries<KilogramPerLiter> { 3.23f, 3.23f, 3.23f, 3.23f, 3.23f, 3.23f, 3.23f };
A137: RenewableDiesel_Emissions_kg_CO2_per_liter | B137: World | C137: RenewableDiesel | D137: Emissions | E137: kg CO₂ per liter | F137: 0.67 | G137: 0.51843323 | H137: 0.40115375 | I137: 0.31040512 | J137: 0.24018557 | K137: 0.18585101 | L137: 0.14380797 | M137: KilogramPerLiter | N137: =IF(C137="",IF(B136="","","} ")&IF(B143="","","public class "&B137&" {"),"public ParameterTimeSeries<"&M137&"> "&A137&" { get; } = new ParameterTimeSeries<"&M137&"> { "&_xlfn.TEXTJOIN("f, ",TRUE,F137:L137)&"f };") -> public ParameterTimeSeries<KilogramPerLiter> RenewableDiesel_Emissions_kg_CO2_per_liter { get; } = new ParameterTimeSeries<KilogramPerLiter> { 0.67f, 0.518433228125f, 0.401153749289714f, 0.310405124207035f, 0.240185568013723f, 0.185851013991629f, 0.143807971841768f };
A138: Diesel_Price_euro_per_liter | B138: World | C138: Diesel | D138: Price | E138: euro per liter | F138: 0.645 | G138: 0.68866196 | H138: 0.74930875 | I138: 0.9977526 | J138: 1.2253047 | K138: 1.4371416 | L138: 1.6376039 | M138: EuroPerLiter | N138: =IF(C138="",IF(B131="","","} ")&IF(B139="","","public class "&B138&" {"),"public ParameterTimeSeries<"&M138&"> "&A138&" { get; } = new ParameterTimeSeries<"&M138&"> { "&_xlfn.TEXTJOIN("f, ",TRUE,F138:L138)&"f };") -> public ParameterTimeSeries<EuroPerLiter> Diesel_Price_euro_per_liter { get; } = new ParameterTimeSeries<EuroPerLiter> { 0.645f, 0.688661964535861f, 0.749308747470626f, 0.997752603588364f, 1.22530466918144f, 1.43714158748054f, 1.6376038650847f };
A139: Diesel_Emissions_kg_CO2_per_liter | B139: World | C139: Diesel | D139: Emissions | E139: kg CO₂ per liter | F139: 3.102 | G139: 3.067306 | H139: 3.0036923 | I139: 2.3888018 | J139: 1.8870889 | K139: 1.4833523 | L139: 1.1616559 | M139: KilogramPerLiter | N139: =IF(C139="",IF(B138="","","} ")&IF(B140="","","public class "&B139&" {"),"public ParameterTimeSeries<"&M139&"> "&A139&" { get; } = new ParameterTimeSeries<"&M139&"> { "&_xlfn.TEXTJOIN("f, ",TRUE,F139:L139)&"f };") -> public ParameterTimeSeries<KilogramPerLiter> Diesel_Emissions_kg_CO2_per_liter { get; } = new ParameterTimeSeries<KilogramPerLiter> { 3.102f, 3.0673059936875f, 3.00369229994318f, 2.38880183550941f, 1.88708892256006f, 1.48335234022762f, 1.16165585611043f };
A140: Diesel_CO2_tax_euro_per_liter | B140: World | C140: Diesel | D140: CO₂ tax | E140: euro per liter | F140: 0.173712 | G140: 0.37957912 | H140: 0.60073846 | I140: 0.7868116 | J140: 0.89164952 | K140: 0.93358488 | L140: 0.92932468 | M140: EuroPerLiter | N140: =IF(C140="",IF(B139="","","} ")&IF(B142="","","public class "&B140&" {"),"public ParameterTimeSeries<"&M140&"> "&A140&" { get; } = new ParameterTimeSeries<"&M140&"> { "&_xlfn.TEXTJOIN("f, ",TRUE,F140:L140)&"f };") -> public ParameterTimeSeries<EuroPerLiter> Diesel_CO2_tax_euro_per_liter { get; } = new ParameterTimeSeries<EuroPerLiter> { 0.173712f, 0.379579116718828f, 0.600738459988635f, 0.786811604570912f, 0.89164951590963f, 0.93358487913076f, 0.929324684888341f };
A141: Diesel_Pollution_tax_euro_per_liter | B141: World | C141: Diesel | D141: Pollution tax | E141: euro per liter | F141: 0.02 | G141: 0.0322102 | H141: 0.051874849 | I141: 0.083544963 | J141: 0.13455 | K141: 0.21669412 | L141: 0.34898805 | M141: EuroPerLiter | N141: =IF(C141="",IF(B140="","","} ")&IF(B143="","","public class "&B141&" {"),"public ParameterTimeSeries<"&M141&"> "&A141&" { get; } = new ParameterTimeSeries<"&M141&"> { "&_xlfn.TEXTJOIN("f, ",TRUE,F141:L141)&"f };") -> public ParameterTimeSeries<EuroPerLiter> Diesel_Pollution_tax_euro_per_liter { get; } = new ParameterTimeSeries<EuroPerLiter> { 0.02f, 0.0322102f, 0.051874849202f, 0.0835449633883131f, 0.134549998986512f, 0.216694118867768f, 0.348988045377729f };
A142: Diesel_Road_tax_euro_per_liter | B142: World | C142: Diesel | D142: Road tax | E142: euro per liter | F142: 0.4 | G142: 0.4 | H142: 0.4 | I142: 0.4 | J142: 0.4 | K142: 0.4 | L142: 0.4 | M142: EuroPerLiter | N142: =IF(C142="",IF(B140="","","} ")&IF(B143="","","public class "&B142&" {"),"public ParameterTimeSeries<"&M142&"> "&A142&" { get; } = new ParameterTimeSeries<"&M142&"> { "&_xlfn.TEXTJOIN("f, ",TRUE,F142:L142)&"f };") -> public ParameterTimeSeries<EuroPerLiter> Diesel_Road_tax_euro_per_liter { get; } = new ParameterTimeSeries<EuroPerLiter> { 0.4f, 0.4f, 0.4f, 0.4f, 0.4f, 0.4f, 0.4f };
A143: Electricity_Conversion_ratio_kWh_per_liter | B143: World | C143: Electricity | D143: Conversion ratio | E143: kWh per liter | F143: 4.1637318 | G143: 4.1637318 | H143: 4.1637318 | I143: 4.1637318 | J143: 4.1637318 | K143: 4.1637318 | L143: 4.1637318 | M143: KiloWattHoursPerLiter | N143: =IF(C143="",IF(B142="","","} ")&IF(B144="","","public class "&B143&" {"),"public ParameterTimeSeries<"&M143&"> "&A143&" { get; } = new ParameterTimeSeries<"&M143&"> { "&_xlfn.TEXTJOIN("f, ",TRUE,F143:L143)&"f };") -> public ParameterTimeSeries<KiloWattHoursPerLiter> Electricity_Conversion_ratio_kWh_per_liter { get; } = new ParameterTimeSeries<KiloWattHoursPerLiter> { 4.16373176470588f, 4.16373176470588f, 4.16373176470588f, 4.16373176470588f, 4.16373176470588f, 4.16373176470588f, 4.16373176470588f };
A144: Electricity_Road_tax_euro_per_kWh | B144: World | C144: Electricity | D144: Road tax | E144: euro per kWh | F144: 0.096067668 | G144: 0.096067668 | H144: 0.096067668 | I144: 0.096067668 | J144: 0.096067668 | K144: 0.096067668 | L144: 0.096067668 | M144: EuroPerKiloWattHour | N144: =IF(C144="",IF(B143="","","} ")&IF(B145="","","public class "&B144&" {"),"public ParameterTimeSeries<"&M144&"> "&A144&" { get; } = new ParameterTimeSeries<"&M144&"> { "&_xlfn.TEXTJOIN("f, ",TRUE,F144:L144)&"f };") -> public ParameterTimeSeries<EuroPerKiloWattHour> Electricity_Road_tax_euro_per_kWh { get; } = new ParameterTimeSeries<EuroPerKiloWattHour> { 0.096067667804786f, 0.096067667804786f, 0.096067667804786f, 0.096067667804786f, 0.096067667804786f, 0.096067667804786f, 0.096067667804786f };
A145: SE12_Price_min_euro_per_kWh | B145: SE12 | C145: SE12 | D145: Price min | E145: euro per kWh | F145: 0.071295288 | G145: 0.071295288 | H145: 0.071295288 | I145: 0.071295288 | J145: 0.071295288 | K145: 0.071295288 | L145: 0.071295288 | M145: EuroPerKiloWattHour | N145: =IF(C145="",IF(B144="","","} ")&IF(B146="","","public class "&B145&" {"),"public ParameterTimeSeries<"&M145&"> "&A145&" { get; } = new ParameterTimeSeries<"&M145&"> { "&_xlfn.TEXTJOIN("f, ",TRUE,F145:L145)&"f };") -> public ParameterTimeSeries<EuroPerKiloWattHour> SE12_Price_min_euro_per_kWh { get; } = new ParameterTimeSeries<EuroPerKiloWattHour> { 0.0712952876712329f, 0.0712952876712329f, 0.0712952876712329f, 0.0712952876712329f, 0.0712952876712329f, 0.0712952876712329f, 0.0712952876712329f };
...

Sheet battery wear
A1: Year of manufacture | C1: {=batteries!E1:K1} -> 2020 | D1: 2025 | E1: 2030 | F1: 2035 | G1: 2040 | H1: 2045 | I1: 2050
A2: Calendar lifetime | B2: years | C2: {=_xlfn.ANCHORARRAY(batteries!E15)} -> 20.769231 | D2: 18 | E2: 17.753425 | F2: 18.352941 | G2: 19.322684 | H2: 20.473934 | I2: 21.718775
A3: {=batteries!C4:K4} -> Cycle lifetime | B3: cycles | C3: 1500 | D3: 2007.3384 | E3: 2686.2715 | F3: 3594.8373 | G3: 4810.7032 | H3: 6437.8061 | I3: 8615.2368
A4: {=batteries!C19:K19} -> Max permitted charging rate | B4: c | C4: 2.3076923 | D4: 2.2120962 | E4: 2.4332783 | F4: 2.8250094 | G4: 3.3601888 | H4: 4.0429745 | I4: 4.8918486
A5: {=batteries!C17:K17} -> Reference charging rate | B5: c | C5: 1.5384615 | D5: 1.4747308 | E5: 1.6221855 | F5: 1.8833396 | G5: 2.2401259 | H5: 2.6953164 | I5: 3.2612324
C7: {=vehicles!E83:K83} -> 2020 | D7: 2025 | E7: 2030 | F7: 2035 | G7: 2040 | H7: 2045 | I7: 2050
A8: Pack size | B8: kWh | C8: 250 | D8: 250 | E8: 250 | F8: 250 | G8: 250 | H8: 250 | I8: 250
A9: Energy consumption | B9: kWh/km | C9: {=vehicles!E106:K106} -> 1.1242076 | D9: 1.0908836 | E9: 1.0585475 | F9: 1.0271699 | G9: 0.99672235 | H9: 0.96717735 | I9: 0.93850813
A10: Annual distance | B10: km | C10: {=vehicles!E84:K84} -> 115000 | D10: 115000 | E10: 115000 | F10: 115000 | G10: 115000 | H10: 115000 | I10: 115000
B11: cycles per year | C11: {=_xlfn.ANCHORARRAY(C10)*_xlfn.ANCHORARRAY(C9)/C8:I8} -> 517.13549 | D11: 501.80648 | E11: 486.93185 | F11: 472.49814 | G11: 458.49228 | H11: 444.90158 | I11: 431.71374
B12: calendar ageing per cycle | C12: {=1/(_xlfn.ANCHORARRAY(C2)*_xlfn.ANCHORARRAY(C11))} -> 9.3105481e-05 | D12: 0.00011071112 | E12: 0.00011567771 | F12: 0.00011531724 | G12: 0.00011287572 | H12: 0.00010978292 | I12: 0.00010665195
B14: Year of manufacture | C14: 2020 | D14: 2020 | E14: 2020 | F14: 2030 | G14: 2030 | H14: 2030 | I14: 2040 | J14: 2040 | K14: 2040 | L14: 2050 | M14: 2050 | N14: 2050
B15: c-rate | C15: 0.75 | D15: 1.5 | E15: 3 | F15: {=C15:E15*1.5} -> 1.125 | G15: 2.25 | H15: 4.5 | I15: {=F15:H15*1.5} -> 1.6875 | J15: 3.375 | K15: 6.75 | L15: {=I15:K15*1.5} -> 2.53125 | M15: 5.0625 | N15: 10.125
A16: Cycle | B16: 100 | C16: =MAX(0,1-$B16*(MAX(0.75,POWER(C$15/$C$4,2)))/$C$3-$B16*$C$12) -> 0.94068945 | D16: =MAX(0,1-$B16*(MAX(0.75,POWER(D$15/$C$4,2)))/$C$3-$B16*$C$12) -> 0.94068945 | E16: =MAX(0,1-$B16*(MAX(0.75,POWER(E$15/$C$4,2)))/$C$3-$B16*$C$12) -> 0.87802279 | F16: =MAX(0,1-$B16*(MAX(0.75,POWER(F$15/$E$4,2)))/$E$3-$B16*$E$12) -> 0.96051249 | G16: =MAX(0,1-$B16*(MAX(0.75,POWER(G$15/$E$4,2)))/$E$3-$B16*$E$12) -> 0.9566026 | H16: =MAX(0,1-$B16*(MAX(0.75,POWER(H$15/$E$4,2)))/$E$3-$B16*$E$12) -> 0.86111372 | I16: =MAX(0,1-$B16*(MAX(0.75,POWER(I$15/$G$4,2)))/$G$3-$B16*$G$12) -> 0.97312219 | J16: =MAX(0,1-$B16*(MAX(0.75,POWER(J$15/$G$4,2)))/$G$3-$B16*$G$12) -> 0.96774179 | K16: =MAX(0,1-$B16*(MAX(0.75,POWER(K$15/$G$4,2)))/$G$3-$B16*$G$12) -> 0.90482988 | L16: =MAX(0,1-$B16*(MAX(0.75,POWER(L$15/$I$4,2)))/$I$3-$B16*$I$12) -> 0.9806293 | M16: =MAX(0,1-$B16*(MAX(0.75,POWER(M$15/$I$4,2)))/$I$3-$B16*$I$12) -> 0.9769035 | N16: =MAX(0,1-$B16*(MAX(0.75,POWER(N$15/$I$4,2)))/$I$3-$B16*$I$12) -> 0.93960957 | Q16: {=MAX($B16:$B115*(C16:C115>0))} -> 1600 | R16: {=MAX($B16:$B115*(D16:D115>0))} -> 1600 | S16: {=MAX($B16:$B115*(E16:E115>0))} -> 800 | T16: {=MAX($B16:$B115*(F16:F115>0))} -> 2500 | U16: {=MAX($B16:$B115*(G16:G115>0))} -> 2300 | V16: {=MAX($B16:$B115*(H16:H115>0))} -> 700 | W16: {=MAX($B16:$B115*(I16:I115>0))} -> 3700 | X16: {=MAX($B16:$B115*(J16:J115>0))} -> 3000 | ... AB16: {=MAX($B16:$B115*(N16:N115>0))} -> 1600
A17: Note: 0% means 80% state of health | B17: 200 | C17: =MAX(0,1-$B17*(MAX(0.75,POWER(C$15/$C$4,2)))/$C$3-$B17*$C$12) -> 0.8813789 | D17: =MAX(0,1-$B17*(MAX(0.75,POWER(D$15/$C$4,2)))/$C$3-$B17*$C$12) -> 0.8813789 | E17: =MAX(0,1-$B17*(MAX(0.75,POWER(E$15/$C$4,2)))/$C$3-$B17*$C$12) -> 0.75604557 | F17: =MAX(0,1-$B17*(MAX(0.75,POWER(F$15/$E$4,2)))/$E$3-$B17*$E$12) -> 0.92102498 | G17: =MAX(0,1-$B17*(MAX(0.75,POWER(G$15/$E$4,2)))/$E$3-$B17*$E$12) -> 0.9132052 | H17: =MAX(0,1-$B17*(MAX(0.75,POWER(H$15/$E$4,2)))/$E$3-$B17*$E$12) -> 0.72222743 | I17: =MAX(0,1-$B17*(MAX(0.75,POWER(I$15/$G$4,2)))/$G$3-$B17*$G$12) -> 0.94624438 | J17: =MAX(0,1-$B17*(MAX(0.75,POWER(J$15/$G$4,2)))/$G$3-$B17*$G$12) -> 0.93548358 | K17: =MAX(0,1-$B17*(MAX(0.75,POWER(K$15/$G$4,2)))/$G$3-$B17*$G$12) -> 0.80965976 | L17: =MAX(0,1-$B17*(MAX(0.75,POWER(L$15/$I$4,2)))/$I$3-$B17*$I$12) -> 0.9612586 | M17: =MAX(0,1-$B17*(MAX(0.75,POWER(M$15/$I$4,2)))/$I$3-$B17*$I$12) -> 0.95380699 | N17: =MAX(0,1-$B17*(MAX(0.75,POWER(N$15/$I$4,2)))/$I$3-$B17*$I$12) -> 0.87921914 | Q17: {=Q16:S16/C11} -> 3.0939668 | R17: 3.0939668 | S17: 1.5469834 | T17: {=T16:V16/E11} -> 5.1341887 | U17: 4.7234536 | V17: 1.4375728 | W17: {=W16:Y16/G11} -> 8.0699287 | X17: 6.5431854 | Y17: 2.1810618 | Z17: {=Z16:AB16/I11} -> 11.813384 | AA17: 9.9603038 | AB17: 3.7061595
B18: 300 | C18: =MAX(0,1-$B18*(MAX(0.75,POWER(C$15/$C$4,2)))/$C$3-$B18*$C$12) -> 0.82206836 | D18: =MAX(0,1-$B18*(MAX(0.75,POWER(D$15/$C$4,2)))/$C$3-$B18*$C$12) -> 0.82206836 | E18: =MAX(0,1-$B18*(MAX(0.75,POWER(E$15/$C$4,2)))/$C$3-$B18*$C$12) -> 0.63406836 | F18: =MAX(0,1-$B18*(MAX(0.75,POWER(F$15/$E$4,2)))/$E$3-$B18*$E$12) -> 0.88153747 | G18: =MAX(0,1-$B18*(MAX(0.75,POWER(G$15/$E$4,2)))/$E$3-$B18*$E$12) -> 0.8698078 | H18: =MAX(0,1-$B18*(MAX(0.75,POWER(H$15/$E$4,2)))/$E$3-$B18*$E$12) -> 0.58334115 | I18: =MAX(0,1-$B18*(MAX(0.75,POWER(I$15/$G$4,2)))/$G$3-$B18*$G$12) -> 0.91936658 | J18: =MAX(0,1-$B18*(MAX(0.75,POWER(J$15/$G$4,2)))/$G$3-$B18*$G$12) -> 0.90322537 | K18: =MAX(0,1-$B18*(MAX(0.75,POWER(K$15/$G$4,2)))/$G$3-$B18*$G$12) -> 0.71448964 | L18: =MAX(0,1-$B18*(MAX(0.75,POWER(L$15/$I$4,2)))/$I$3-$B18*$I$12) -> 0.94188789 | M18: =MAX(0,1-$B18*(MAX(0.75,POWER(M$15/$I$4,2)))/$I$3-$B18*$I$12) -> 0.93071049 | N18: =MAX(0,1-$B18*(MAX(0.75,POWER(N$15/$I$4,2)))/$I$3-$B18*$I$12) -> 0.81882871
B19: 400 | C19: =MAX(0,1-$B19*(MAX(0.75,POWER(C$15/$C$4,2)))/$C$3-$B19*$C$12) -> 0.76275781 | D19: =MAX(0,1-$B19*(MAX(0.75,POWER(D$15/$C$4,2)))/$C$3-$B19*$C$12) -> 0.76275781 | E19: =MAX(0,1-$B19*(MAX(0.75,POWER(E$15/$C$4,2)))/$C$3-$B19*$C$12) -> 0.51209114 | F19: =MAX(0,1-$B19*(MAX(0.75,POWER(F$15/$E$4,2)))/$E$3-$B19*$E$12) -> 0.84204996 | G19: =MAX(0,1-$B19*(MAX(0.75,POWER(G$15/$E$4,2)))/$E$3-$B19*$E$12) -> 0.8264104 | H19: =MAX(0,1-$B19*(MAX(0.75,POWER(H$15/$E$4,2)))/$E$3-$B19*$E$12) -> 0.44445486 | I19: =MAX(0,1-$B19*(MAX(0.75,POWER(I$15/$G$4,2)))/$G$3-$B19*$G$12) -> 0.89248877 | J19: =MAX(0,1-$B19*(MAX(0.75,POWER(J$15/$G$4,2)))/$G$3-$B19*$G$12) -> 0.87096717 | K19: =MAX(0,1-$B19*(MAX(0.75,POWER(K$15/$G$4,2)))/$G$3-$B19*$G$12) -> 0.61931952 | L19: =MAX(0,1-$B19*(MAX(0.75,POWER(L$15/$I$4,2)))/$I$3-$B19*$I$12) -> 0.92251719 | M19: =MAX(0,1-$B19*(MAX(0.75,POWER(M$15/$I$4,2)))/$I$3-$B19*$I$12) -> 0.90761398 | N19: =MAX(0,1-$B19*(MAX(0.75,POWER(N$15/$I$4,2)))/$I$3-$B19*$I$12) -> 0.75843828
B20: 500 | C20: =MAX(0,1-$B20*(MAX(0.75,POWER(C$15/$C$4,2)))/$C$3-$B20*$C$12) -> 0.70344726 | D20: =MAX(0,1-$B20*(MAX(0.75,POWER(D$15/$C$4,2)))/$C$3-$B20*$C$12) -> 0.70344726 | E20: =MAX(0,1-$B20*(MAX(0.75,POWER(E$15/$C$4,2)))/$C$3-$B20*$C$12) -> 0.39011393 | F20: =MAX(0,1-$B20*(MAX(0.75,POWER(F$15/$E$4,2)))/$E$3-$B20*$E$12) -> 0.80256245 | G20: =MAX(0,1-$B20*(MAX(0.75,POWER(G$15/$E$4,2)))/$E$3-$B20*$E$12) -> 0.783013 | H20: =MAX(0,1-$B20*(MAX(0.75,POWER(H$15/$E$4,2)))/$E$3-$B20*$E$12) -> 0.30556858 | I20: =MAX(0,1-$B20*(MAX(0.75,POWER(I$15/$G$4,2)))/$G$3-$B20*$G$12) -> 0.86561096 | J20: =MAX(0,1-$B20*(MAX(0.75,POWER(J$15/$G$4,2)))/$G$3-$B20*$G$12) -> 0.83870896 | K20: =MAX(0,1-$B20*(MAX(0.75,POWER(K$15/$G$4,2)))/$G$3-$B20*$G$12) -> 0.5241494 | L20: =MAX(0,1-$B20*(MAX(0.75,POWER(L$15/$I$4,2)))/$I$3-$B20*$I$12) -> 0.90314649 | M20: =MAX(0,1-$B20*(MAX(0.75,POWER(M$15/$I$4,2)))/$I$3-$B20*$I$12) -> 0.88451748 | N20: =MAX(0,1-$B20*(MAX(0.75,POWER(N$15/$I$4,2)))/$I$3-$B20*$I$12) -> 0.69804785
